Workbook

Sheet GLOBALIZADA COPASA
C2: SECRETARIA DE ESTADO DE JUSTIÇA E SEGURANÇA PÚBLICA - CNPJ: 05.487.631/0001-09 | P2: DEZEMBRO | X2: JANEIRO | AI2: FEVEREIRO | AT2: MARÇO | BE2: ABRIL | BP2: MAIO | CA2: JUNHO | CL2: JULHO | CW2: AGOSTO | DH2: SETEMBRO | DS2: OUTUBRO | ED2: NOVEMBRO | EO2: DEZEMBRO
C4: UNIDADES PRISIONAIS | D4: UNIDADE EXECUTORA | E4: UPG | F4: HIDRÔMETRO | G4: MATRÍCULA | H4: CONCESSIONÁRIA | I4: CNPJ | J4: IDENTIFICADOR (1) | K4: IDENTIFICADOR (2) | L4: EMPENHO (FONTE 10) | M4: EMPENHO DE ENCARGOS (FONTE 10) | N4: EMPENHO (FONTE 60) | O4: EMPENHO DE ENCARGOS (FONTE 60) | P4: IR (12) | Q4: ENCARGOS (12) | R4: LÍQUIDO (12) | S4: M³ (12) | T4: Nº SEI | U4: VENCIMENTO | V4: Variação Consumo | W4: Variação Financeiro | X4: BRUTO (1) | Y4: IR (1) | Z4: ENCARGOS (1) | AA4: LÍQUIDO (1) | AB4: M³ (1) | AC4: VENCIMENTO (1) | AD4: Nº SEI (1) | AE4: ENVIADO AO DED (1) | AF4: PAGO (1) | AG4: Variação Consumo (1) | AH4: Variação Financeiro (1) | AI4: BRUTO (2) | AJ4: IR (2) | AK4: ENCARGOS (2) | AL4: LÍQUIDO (1)2 | AM4: M³ (2) | AN4: VENCIMENTO (2) | AO4: Nº SEI (2) | AP4: ENVIADO AO DED (1)2 | AQ4: PAGO (1)3 | AR4: Variação Consumo (2) | AS4: Variação Financeiro (2) | AT4: BRUTO (3) | AU4: IR (3)3 | AV4: ENCARGOS (3) | AW4: LÍQUIDO (3) | AX4: M³ (3) | AY4: VENCIMENTO (3) | AZ4: Nº SEI (3) | BA4: ENVIADO AO DED (1)3 | BB4: PAGO (1)4 | BC4: Variação Consumo (3) | BD4: Variação Financeiro (3) | BE4: BRUTO (4) | BF4: IR (4) | BG4: ENCARGOS (4) | BH4: LÍQUIDO (4) | BI4: M³ (4) | BJ4: VENCIMENTO (4) | BK4: Nº SEI (4) | BL4: ENVIADO AO DED (1)22 | BM4: PAGO (1)33 | BN4: Variação Consumo (4) | BO4: Variação Financeiro (4) | BP4: BRUTO (3)2 | BQ4: IR (3)33 | BR4: ENCARGOS (3)4 | BS4: LÍQUIDO (3)5 | BT4: M³ (3)6 | BU4: VENCIMENTO (3)7 | BV4: Nº SEI (3)8 | BW4: ENVIADO AO DED (1)39 | BX4: PAGO (1)410 | BY4: Variação Consumo (3)11 | BZ4: Variação Financeiro (3)12 | CA4: BRUTO (4)13 | CB4: IR (4)14 | CC4: ENCARGOS (4)15 | CD4: LÍQUIDO (4)16 | CE4: M³ (4)17 | CF4: VENCIMENTO (4)18 | CG4: Nº SEI (4)19 | CH4: ENVIADO AO DED (1)2220 | CI4: PAGO (1)3321 | CJ4: Variação Consumo (4)22 | CK4: Variação Financeiro (4)23 | CL4: BRUTO (3)3 | CM4: IR (3)34 | CN4: ENCARGOS (3)5 | CO4: LÍQUIDO (3)6 | CP4: M³ (3)7 | CQ4: VENCIMENTO (3)8 | CR4: Nº SEI (3)9 | CS4: ENVIADO AO DED (1)310 | CT4: PAGO (1)411 | CU4: Variação Consumo (3)12 | CV4: Variação Financeiro (3)13 | CW4: BRUTO (4)14 | CX4: IR (4)15 | CY4: ENCARGOS (4)16 | CZ4: LÍQUIDO (4)17 | DA4: M³ (4)18 | DB4: VENCIMENTO (4)19 | DC4: Nº SEI (4)20 | DD4: ENVIADO AO DED (1)2221 | DE4: PAGO (1)3322 | DF4: Variação Consumo (4)23 | DG4: Variação Financeiro (4)24 | DH4: BRUTO (3)32 | DI4: IR (3)343 | DJ4: ENCARGOS (3)54 | DK4: LÍQUIDO (3)65 | DL4: M³ (3)76 | DM4: VENCIMENTO (3)87 | DN4: Nº SEI (3)98 | DO4: ENVIADO AO DED (1)3109 | DP4: PAGO (1)41110 | DQ4: Variação Consumo (3)1211 | DR4: Variação Financeiro (3)1312 | DS4: BRUTO (4)1413 | DT4: IR (4)1514 | DU4: ENCARGOS (4)1615 | DV4: LÍQUIDO (4)1716 | DW4: M³ (4)1817 | DX4: VENCIMENTO (4)1918 | DY4: Nº SEI (4)2019 | DZ4: ENVIADO AO DED (1)222120 | EA4: PAGO (1)332221 | EB4: Variação Consumo (4)2322 | EC4: Variação Financeiro (4)2423 | ED4: BRUTO (3)322 | EE4: IR (3)3433 | EF4: ENCARGOS (3)544 | EG4: LÍQUIDO (3)655 | EH4: M³ (3)766 | EI4: VENCIMENTO (3)877 | EJ4: Nº SEI (3)988 | EK4: ENVIADO AO DED (1)31099 | EL4: PAGO (1)4111010 | EM4: Variação Consumo (3)121111 | EN4: Variação Financeiro (3)131212 | EO4: BRUTO (4)141313 | EP4: IR (4)151414 | EQ4: ENCARGOS (4)161515 | ER4: LÍQUIDO (4)171616 | ES4: M³ (4)181717 | ET4: VENCIMENTO (4)191818 | EU4: Nº SEI (4)201919 | EV4: ENVIADO AO DED (1)22212020 | EW4: PAGO (1)33222121 | EX4: Variação Consumo (4)232222 | EY4: Variação Financeiro (4)242323
C5: 3ª AISP ED. JK (BH) | D5: 1450022 | E5: 184 | F5: A24H0000770 | G5: 00013610520 | H5: COMPANHIA DE SANEAMENTO DE MINAS GERAIS COPASA MG | I5: 17.281.106/0001-03 | N5: 107 | P5: 73.12 | R5: 1450.23 | S5: 70 | T5: 1450.01.0005511/2026-51 | X5: =AA5 + ABS(Y5) + ABS(Z5) -> 1701.94 | Y5: -81.69 | Z5: 0 | AA5: 1620.25 | AB5: 76 | AC5: 10/03/2026 | AD5: 1450.01.0029372/2026-78 | AE5: TRUE | AF5: TRUE | AG5: =(AB5-S5)/S5 -> 0.085714286 | AH5: =(AA5-R5)/R5 -> 0.11723658 | AI5: =AL5 + ABS(AJ5) + ABS(AK5) -> 2281.33 | AJ5: -109.5 | AK5: 0 | AL5: 2171.83 | AM5: 95 | AN5: 46122 | AO5: 1450.01.0046622/2026-25 | AP5: TRUE | AQ5: TRUE | AR5: =(AM5-AB5)/AB5 -> 0.25 | AS5: =(AL5-AA5)/AA5 -> 0.34042895 | AT5: =AW5 + ABS(AU5) + ABS(AV5) -> 0 | BA5: FALSE | BB5: FALSE | BC5: =(AX5-AM5)/AM5 -> -1 | BD5: =(AW5-AL5)/AL5 -> -1 | BE5: =BH5 + ABS(BF5) + ABS(BG5) -> 0 | BL5: FALSE | BM5: FALSE | BN5: =(BI5-AZ5)/AZ5 -> #DIV/0! | BO5: =(BH5-AW5)/AW5 -> #DIV/0! | BP5: =BS5 + ABS(BQ5) + ABS(BR5) -> 0 | BW5: FALSE | BX5: FALSE | BY5: =(BT5-BI5)/BI5 -> #DIV/0! | BZ5: =(BS5-BH5)/BH5 -> #DIV/0! | CA5: =CD5 + ABS(CB5) + ABS(CC5) -> 0 | CH5: FALSE | CI5: FALSE | CJ5: =(CE5-BV5)/BV5 -> #DIV/0! | CK5: =(CD5-BS5)/BS5 -> #DIV/0! | CL5: =CO5 + ABS(CM5) + ABS(CN5) -> 0 | CS5: FALSE | CT5: FALSE | CU5: =(CP5-CE5)/CE5 -> #DIV/0! | CV5: =(CO5-CD5)/CD5 -> #DIV/0! | CW5: =CZ5 + ABS(CX5) + ABS(CY5) -> 0 | DD5: FALSE | DE5: FALSE | DF5: =(DA5-CR5)/CR5 -> #DIV/0! | DG5: =(CZ5-CO5)/CO5 -> #DIV/0! | DH5: =DK5 + ABS(DI5) + ABS(DJ5) -> 0 | DO5: FALSE | DP5: FALSE | DQ5: =(DL5-DA5)/DA5 -> #DIV/0! | DR5: =(DK5-CZ5)/CZ5 -> #DIV/0! | DS5: =DV5 + ABS(DT5) + ABS(DU5) -> 0 | DZ5: FALSE | EA5: FALSE | EB5: =(DW5-DN5)/DN5 -> #DIV/0! | EC5: =(DV5-DK5)/DK5 -> #DIV/0! | ED5: =EG5 + ABS(EE5) + ABS(EF5) -> 0 | EK5: FALSE | EL5: FALSE | EM5: =(EH5-DW5)/DW5 -> #DIV/0! | EN5: =(EG5-DV5)/DV5 -> #DIV/0! | EO5: =ER5 + ABS(EP5) + ABS(EQ5) -> 0 | EV5: FALSE | EW5: FALSE | EX5: =(ES5-EJ5)/EJ5 -> #DIV/0! | EY5: =(ER5-EG5)/EG5 -> #DIV/0!
C6: 12ª RISP (DRAP IPATINGA) | D6: 1450022 | E6: 198 | F6: Y19G0986114 | G6: 00115043942 | H6: COMPANHIA DE SANEAMENTO DE MINAS GERAIS COPASA MG | I6: 17.281.106/0001-03 | N6: 107 | P6: 15.69 | R6: 311.2 | S6: 20 | T6: 1450.01.0005511/2026-51 | X6: =AA6 + ABS(Y6) + ABS(Z6) -> 208.97 | Y6: -10.03 | Z6: 0 | AA6: 198.94 | AB6: 13 | AC6: 10/03/2026 | AD6: 1450.01.0029372/2026-78 | AE6: TRUE | AF6: TRUE | AG6: =(AB6-S6)/S6 -> -0.35 | AH6: =(AA6-R6)/R6 -> -0.36073265 | AI6: =AL6 + ABS(AJ6) + ABS(AK6) -> 259.04 | AJ6: -12.43 | AK6: 0 | AL6: 246.61 | AM6: 15 | AN6: 46122 | AO6: 1450.01.0046622/2026-25 | AP6: TRUE | AQ6: TRUE | AR6: =(AM6-AB6)/AB6 -> 0.15384615 | AS6: =(AL6-AA6)/AA6 -> 0.23961999 | AT6: =AW6 + ABS(AU6) + ABS(AV6) -> 0 | BA6: FALSE | BB6: FALSE | BC6: =(AX6-AM6)/AM6 -> -1 | BD6: =(AW6-AL6)/AL6 -> -1 | BE6: =BH6 + ABS(BF6) + ABS(BG6) -> 0 | BL6: FALSE | BM6: FALSE | BN6: =(BI6-AZ6)/AZ6 -> #DIV/0! | BO6: =(BH6-AW6)/AW6 -> #DIV/0! | BP6: =BS6 + ABS(BQ6) + ABS(BR6) -> 0 | BW6: FALSE | BX6: FALSE | BY6: =(BT6-BI6)/BI6 -> #DIV/0! | BZ6: =(BS6-BH6)/BH6 -> #DIV/0! | CA6: =CD6 + ABS(CB6) + ABS(CC6) -> 0 | CH6: FALSE | CI6: FALSE | CJ6: =(CE6-BV6)/BV6 -> #DIV/0! | CK6: =(CD6-BS6)/BS6 -> #DIV/0! | CL6: =CO6 + ABS(CM6) + ABS(CN6) -> 0 | CS6: FALSE | CT6: FALSE | CU6: =(CP6-CE6)/CE6 -> #DIV/0! | CV6: =(CO6-CD6)/CD6 -> #DIV/0! | CW6: =CZ6 + ABS(CX6) + ABS(CY6) -> 0 | DD6: FALSE | DE6: FALSE | DF6: =(DA6-CR6)/CR6 -> #DIV/0! | DG6: =(CZ6-CO6)/CO6 -> #DIV/0! | DH6: =DK6 + ABS(DI6) + ABS(DJ6) -> 0 | DO6: FALSE | DP6: FALSE | DQ6: =(DL6-DA6)/DA6 -> #DIV/0! | DR6: =(DK6-CZ6)/CZ6 -> #DIV/0! | DS6: =DV6 + ABS(DT6) + ABS(DU6) -> 0 | DZ6: FALSE | EA6: FALSE | EB6: =(DW6-DN6)/DN6 -> #DIV/0! | EC6: =(DV6-DK6)/DK6 -> #DIV/0! | ED6: =EG6 + ABS(EE6) + ABS(EF6) -> 0 | EK6: FALSE | EL6: FALSE | EM6: =(EH6-DW6)/DW6 -> #DIV/0! | EN6: =(EG6-DV6)/DV6 -> #DIV/0! | EO6: =ER6 + ABS(EP6) + ABS(EQ6) -> 0 | EV6: FALSE | EW6: FALSE | EX6: =(ES6-EJ6)/EJ6 -> #DIV/0! | EY6: =(ER6-EG6)/EG6 -> #DIV/0!
C7: 13ª RISP (BARBACENA) | D7: 1450022 | E7: 259 | F7: Y21G1271058 | G7: 00164218301 | H7: COMPANHIA DE SANEAMENTO DE MINAS GERAIS COPASA MG | I7: 17.281.106/0001-03 | N7: 107 | P7: 1.72 | R7: 34.18 | S7: 1 | T7: 1450.01.0005511/2026-51 | X7: =AA7 + ABS(Y7) + ABS(Z7) -> 35.9 | Y7: -1.72 | Z7: 0 | AA7: 34.18 | AB7: 1 | AC7: 10/03/2026 | AD7: 1450.01.0029372/2026-78 | AE7: TRUE | AF7: TRUE | AG7: =(AB7-S7)/S7 -> 0 | AH7: =(AA7-R7)/R7 -> 0 | AI7: =AL7 + ABS(AJ7) + ABS(AK7) -> 36.25 | AJ7: -1.74 | AK7: 0 | AL7: 34.51 | AM7: 0 | AN7: 46122 | AO7: 1450.01.0046622/2026-25 | AP7: TRUE | AQ7: TRUE | AR7: =(AM7-AB7)/AB7 -> -1 | AS7: =(AL7-AA7)/AA7 -> 0.0096547689 | AT7: =AW7 + ABS(AU7) + ABS(AV7) -> 0 | BA7: FALSE | BB7: FALSE | BC7: =(AX7-AM7)/AM7 -> #DIV/0! | BD7: =(AW7-AL7)/AL7 -> -1 | BE7: =BH7 + ABS(BF7) + ABS(BG7) -> 0 | BL7: FALSE | BM7: FALSE | BN7: =(BI7-AZ7)/AZ7 -> #DIV/0! | BO7: =(BH7-AW7)/AW7 -> #DIV/0! | BP7: =BS7 + ABS(BQ7) + ABS(BR7) -> 0 | BW7: FALSE | BX7: FALSE | BY7: =(BT7-BI7)/BI7 -> #DIV/0! | BZ7: =(BS7-BH7)/BH7 -> #DIV/0! | CA7: =CD7 + ABS(CB7) + ABS(CC7) -> 0 | CH7: FALSE | CI7: FALSE | CJ7: =(CE7-BV7)/BV7 -> #DIV/0! | CK7: =(CD7-BS7)/BS7 -> #DIV/0! | CL7: =CO7 + ABS(CM7) + ABS(CN7) -> 0 | CS7: FALSE | CT7: FALSE | CU7: =(CP7-CE7)/CE7 -> #DIV/0! | CV7: =(CO7-CD7)/CD7 -> #DIV/0! | CW7: =CZ7 + ABS(CX7) + ABS(CY7) -> 0 | DD7: FALSE | DE7: FALSE | DF7: =(DA7-CR7)/CR7 -> #DIV/0! | DG7: =(CZ7-CO7)/CO7 -> #DIV/0! | DH7: =DK7 + ABS(DI7) + ABS(DJ7) -> 0 | DO7: FALSE | DP7: FALSE | DQ7: =(DL7-DA7)/DA7 -> #DIV/0! | DR7: =(DK7-CZ7)/CZ7 -> #DIV/0! | DS7: =DV7 + ABS(DT7) + ABS(DU7) -> 0 | DZ7: FALSE | EA7: FALSE | EB7: =(DW7-DN7)/DN7 -> #DIV/0! | EC7: =(DV7-DK7)/DK7 -> #DIV/0! | ED7: =EG7 + ABS(EE7) + ABS(EF7) -> 0 | EK7: FALSE | EL7: FALSE | EM7: =(EH7-DW7)/DW7 -> #DIV/0! | EN7: =(EG7-DV7)/DV7 -> #DIV/0! | EO7: =ER7 + ABS(EP7) + ABS(EQ7) -> 0 | EV7: FALSE | EW7: FALSE | EX7: =(ES7-EJ7)/EJ7 -> #DIV/0! | EY7: =(ER7-EG7)/EG7 -> #DIV/0!
C8: 17ª RISP (POUSO ALEGRE) | D8: 1450022 | E8: 263 | F8: Y24S0064490 | G8: 00024659207 | H8: COMPANHIA DE SANEAMENTO DE MINAS GERAIS COPASA MG | I8: 17.281.106/0001-03 | N8: 107 | P8: 33.01 | R8: 654.76 | S8: 37 | T8: 1450.01.0005511/2026-51 | X8: =AA8 + ABS(Y8) + ABS(Z8) -> 87.48 | Y8: -4.2 | Z8: 0 | AA8: 83.28 | AB8: 4 | AC8: 10/03/2026 | AD8: 1450.01.0029372/2026-78 | AE8: TRUE | AF8: TRUE | AG8: =(AB8-S8)/S8 -> -0.89189189 | AH8: =(AA8-R8)/R8 -> -0.87280836 | AI8: =AL8 + ABS(AJ8) + ABS(AK8) -> 113.88 | AJ8: -5.47 | AK8: 0 | AL8: 108.41 | AM8: 6 | AN8: 46122 | AO8: 1450.01.0046622/2026-25 | AP8: TRUE | AQ8: TRUE | AR8: =(AM8-AB8)/AB8 -> 0.5 | AS8: =(AL8-AA8)/AA8 -> 0.30175312 | AT8: =AW8 + ABS(AU8) + ABS(AV8) -> 0 | BA8: FALSE | BB8: FALSE | BC8: =(AX8-AM8)/AM8 -> -1 | BD8: =(AW8-AL8)/AL8 -> -1 | BE8: =BH8 + ABS(BF8) + ABS(BG8) -> 0 | BL8: FALSE | BM8: FALSE | BN8: =(BI8-AZ8)/AZ8 -> #DIV/0! | BO8: =(BH8-AW8)/AW8 -> #DIV/0! | BP8: =BS8 + ABS(BQ8) + ABS(BR8) -> 0 | BW8: FALSE | BX8: FALSE | BY8: =(BT8-BI8)/BI8 -> #DIV/0! | BZ8: =(BS8-BH8)/BH8 -> #DIV/0! | CA8: =CD8 + ABS(CB8) + ABS(CC8) -> 0 | CH8: FALSE | CI8: FALSE | CJ8: =(CE8-BV8)/BV8 -> #DIV/0! | CK8: =(CD8-BS8)/BS8 -> #DIV/0! | CL8: =CO8 + ABS(CM8) + ABS(CN8) -> 0 | CS8: FALSE | CT8: FALSE | CU8: =(CP8-CE8)/CE8 -> #DIV/0! | CV8: =(CO8-CD8)/CD8 -> #DIV/0! | CW8: =CZ8 + ABS(CX8) + ABS(CY8) -> 0 | DD8: FALSE | DE8: FALSE | DF8: =(DA8-CR8)/CR8 -> #DIV/0! | DG8: =(CZ8-CO8)/CO8 -> #DIV/0! | DH8: =DK8 + ABS(DI8) + ABS(DJ8) -> 0 | DO8: FALSE | DP8: FALSE | DQ8: =(DL8-DA8)/DA8 -> #DIV/0! | DR8: =(DK8-CZ8)/CZ8 -> #DIV/0! | DS8: =DV8 + ABS(DT8) + ABS(DU8) -> 0 | DZ8: FALSE | EA8: FALSE | EB8: =(DW8-DN8)/DN8 -> #DIV/0! | EC8: =(DV8-DK8)/DK8 -> #DIV/0! | ED8: =EG8 + ABS(EE8) + ABS(EF8) -> 0 | EK8: FALSE | EL8: FALSE | EM8: =(EH8-DW8)/DW8 -> #DIV/0! | EN8: =(EG8-DV8)/DV8 -> #DIV/0! | EO8: =ER8 + ABS(EP8) + ABS(EQ8) -> 0 | EV8: FALSE | EW8: FALSE | EX8: =(ES8-EJ8)/EJ8 -> #DIV/0! | EY8: =(ER8-EG8)/EG8 -> #DIV/0!
C9: 17ª RISP (POUSO ALEGRE) | D9: 1450022 | E9: 263 | F9: Y22G1372195 | G9: 00024659185 | H9: COMPANHIA DE SANEAMENTO DE MINAS GERAIS COPASA MG | I9: 17.281.106/0001-03 | N9: 107 | P9: 2.6 | R9: 51.52 | T9: 1450.01.0005511/2026-51 | X9: =AA9 + ABS(Y9) + ABS(Z9) -> 54.12 | Y9: -2.6 | Z9: 0 | AA9: 51.52 | AB9: 0 | AC9: 10/03/2026 | AD9: 1450.01.0029372/2026-78 | AE9: TRUE | AF9: TRUE | AG9: 0 | AH9: =(AA9-R9)/R9 -> 0 | AI9: =AL9 + ABS(AJ9) + ABS(AK9) -> 58.28 | AJ9: -2.8 | AK9: 0 | AL9: 55.48 | AM9: 0 | AN9: 46122 | AO9: 1450.01.0046622/2026-25 | AP9: TRUE | AQ9: TRUE | AR9: 0 | AS9: =(AL9-AA9)/AA9 -> 0.076863354 | AT9: =AW9 + ABS(AU9) + ABS(AV9) -> 0 | BA9: FALSE | BB9: FALSE | BC9: =(AX9-AM9)/AM9 -> #DIV/0! | BD9: =(AW9-AL9)/AL9 -> -1 | BE9: =BH9 + ABS(BF9) + ABS(BG9) -> 0 | BL9: FALSE | BM9: FALSE | BN9: =(BI9-AZ9)/AZ9 -> #DIV/0! | BO9: =(BH9-AW9)/AW9 -> #DIV/0! | BP9: =BS9 + ABS(BQ9) + ABS(BR9) -> 0 | BW9: FALSE | BX9: FALSE | BY9: =(BT9-BI9)/BI9 -> #DIV/0! | BZ9: =(BS9-BH9)/BH9 -> #DIV/0! | CA9: =CD9 + ABS(CB9) + ABS(CC9) -> 0 | CH9: FALSE | CI9: FALSE | CJ9: =(CE9-BV9)/BV9 -> #DIV/0! | CK9: =(CD9-BS9)/BS9 -> #DIV/0! | CL9: =CO9 + ABS(CM9) + ABS(CN9) -> 0 | CS9: FALSE | CT9: FALSE | CU9: =(CP9-CE9)/CE9 -> #DIV/0! | CV9: =(CO9-CD9)/CD9 -> #DIV/0! | CW9: =CZ9 + ABS(CX9) + ABS(CY9) -> 0 | DD9: FALSE | DE9: FALSE | DF9: =(DA9-CR9)/CR9 -> #DIV/0! | DG9: =(CZ9-CO9)/CO9 -> #DIV/0! | DH9: =DK9 + ABS(DI9) + ABS(DJ9) -> 0 | DO9: FALSE | DP9: FALSE | DQ9: =(DL9-DA9)/DA9 -> #DIV/0! | DR9: =(DK9-CZ9)/CZ9 -> #DIV/0! | DS9: =DV9 + ABS(DT9) + ABS(DU9) -> 0 | DZ9: FALSE | EA9: FALSE | EB9: =(DW9-DN9)/DN9 -> #DIV/0! | EC9: =(DV9-DK9)/DK9 -> #DIV/0! | ED9: =EG9 + ABS(EE9) + ABS(EF9) -> 0 | EK9: FALSE | EL9: FALSE | EM9: =(EH9-DW9)/DW9 -> #DIV/0! | EN9: =(EG9-DV9)/DV9 -> #DIV/0! | EO9: =ER9 + ABS(EP9) + ABS(EQ9) -> 0 | EV9: FALSE | EW9: FALSE | EX9: =(ES9-EJ9)/EJ9 -> #DIV/0! | EY9: =(ER9-EG9)/EG9 -> #DIV/0!
C10: ALMOXARIFADO CENTRAL - DMP ( Parque Norte) | D10: 1450022 | E10: 5 | F10: Y22G1259272 | G10: 00133540464 | H10: COMPANHIA DE SANEAMENTO DE MINAS GERAIS COPASA MG | I10: 17.281.106/0001-03 | N10: 107 | P10: 38.54 | R10: 764.37 | S10: 42 | T10: 1450.01.0005511/2026-51 | X10: =AA10 + ABS(Y10) + ABS(Z10) -> 624.08 | Y10: -29.96 | Z10: 0 | AA10: 594.12 | AB10: 34 | AC10: 10/03/2026 | AD10: 1450.01.0029372/2026-78 | AE10: TRUE | AF10: TRUE | AG10: =(AB10-S10)/S10 -> -0.19047619 | AH10: =(AA10-R10)/R10 -> -0.22273245 | AI10: =AL10 + ABS(AJ10) + ABS(AK10) -> 704.83 | AJ10: -33.83 | AK10: 0 | AL10: 671 | AM10: 36 | AN10: 46122 | AO10: 1450.01.0046622/2026-25 | AP10: TRUE | AQ10: TRUE | AR10: =(AM10-AB10)/AB10 -> 0.058823529 | AS10: =(AL10-AA10)/AA10 -> 0.12940147 | AT10: =AW10 + ABS(AU10) + ABS(AV10) -> 0 | BA10: FALSE | BB10: FALSE | BC10: =(AX10-AM10)/AM10 -> -1 | BD10: =(AW10-AL10)/AL10 -> -1 | BE10: =BH10 + ABS(BF10) + ABS(BG10) -> 0 | BL10: FALSE | BM10: FALSE | BN10: =(BI10-AZ10)/AZ10 -> #DIV/0! | BO10: =(BH10-AW10)/AW10 -> #DIV/0! | BP10: =BS10 + ABS(BQ10) + ABS(BR10) -> 0 | BW10: FALSE | BX10: FALSE | BY10: =(BT10-BI10)/BI10 -> #DIV/0! | BZ10: =(BS10-BH10)/BH10 -> #DIV/0! | CA10: =CD10 + ABS(CB10) + ABS(CC10) -> 0 | CH10: FALSE | CI10: FALSE | CJ10: =(CE10-BV10)/BV10 -> #DIV/0! | CK10: =(CD10-BS10)/BS10 -> #DIV/0! | CL10: =CO10 + ABS(CM10) + ABS(CN10) -> 0 | CS10: FALSE | CT10: FALSE | CU10: =(CP10-CE10)/CE10 -> #DIV/0! | CV10: =(CO10-CD10)/CD10 -> #DIV/0! | CW10: =CZ10 + ABS(CX10) + ABS(CY10) -> 0 | DD10: FALSE | DE10: FALSE | DF10: =(DA10-CR10)/CR10 -> #DIV/0! | DG10: =(CZ10-CO10)/CO10 -> #DIV/0! | DH10: =DK10 + ABS(DI10) + ABS(DJ10) -> 0 | DO10: FALSE | DP10: FALSE | DQ10: =(DL10-DA10)/DA10 -> #DIV/0! | DR10: =(DK10-CZ10)/CZ10 -> #DIV/0! | DS10: =DV10 + ABS(DT10) + ABS(DU10) -> 0 | DZ10: FALSE | EA10: FALSE | EB10: =(DW10-DN10)/DN10 -> #DIV/0! | EC10: =(DV10-DK10)/DK10 -> #DIV/0! | ED10: =EG10 + ABS(EE10) + ABS(EF10) -> 0 | EK10: FALSE | EL10: FALSE | EM10: =(EH10-DW10)/DW10 -> #DIV/0! | EN10: =(EG10-DV10)/DV10 -> #DIV/0! | EO10: =ER10 + ABS(EP10) + ABS(EQ10) -> 0 | EV10: FALSE | EW10: FALSE | EX10: =(ES10-EJ10)/EJ10 -> #DIV/0! | EY10: =(ER10-EG10)/EG10 -> #DIV/0!
C11: CASA DO ALBERGADO PRESIDENTE JOÃO PESSOA | D11: 1450022 | E11: 50 | F11: E25H0000317 | G11: 00011368799 | H11: COMPANHIA DE SANEAMENTO DE MINAS GERAIS COPASA MG | I11: 17.281.106/0001-03 | N11: 107 | P11: 99.06 | R11: 1964.62 | S11: 91 | T11: 1450.01.0005511/2026-51 | X11: =AA11 + ABS(Y11) + ABS(Z11) -> 1322.23 | Y11: -63.47 | Z11: 0 | AA11: 1258.76 | AB11: 62 | AC11: 10/03/2026 | AD11: 1450.01.0029372/2026-78 | AE11: TRUE | AF11: TRUE | AG11: =(AB11-S11)/S11 -> -0.31868132 | AH11: =(AA11-R11)/R11 -> -0.35928577 | AI11: =AL11 + ABS(AJ11) + ABS(AK11) -> 33810.05 | AJ11: -1622.88 | AK11: 0 | AL11: 32187.17 | AM11: 1104 | AN11: 46122 | AO11: 1450.01.0046622/2026-25 | AP11: TRUE | AQ11: TRUE | AR11: =(AM11-AB11)/AB11 -> 16.806452 | AS11: =(AL11-AA11)/AA11 -> 24.570538 | AT11: =AW11 + ABS(AU11) + ABS(AV11) -> 0 | BA11: FALSE | BB11: FALSE | BC11: =(AX11-AM11)/AM11 -> -1 | BD11: =(AW11-AL11)/AL11 -> -1 | BE11: =BH11 + ABS(BF11) + ABS(BG11) -> 0 | BL11: FALSE | BM11: FALSE | BN11: =(BI11-AZ11)/AZ11 -> #DIV/0! | BO11: =(BH11-AW11)/AW11 -> #DIV/0! | BP11: =BS11 + ABS(BQ11) + ABS(BR11) -> 0 | BW11: FALSE | BX11: FALSE | BY11: =(BT11-BI11)/BI11 -> #DIV/0! | BZ11: =(BS11-BH11)/BH11 -> #DIV/0! | CA11: =CD11 + ABS(CB11) + ABS(CC11) -> 0 | CH11: FALSE | CI11: FALSE | CJ11: =(CE11-BV11)/BV11 -> #DIV/0! | CK11: =(CD11-BS11)/BS11 -> #DIV/0! | CL11: =CO11 + ABS(CM11) + ABS(CN11) -> 0 | CS11: FALSE | CT11: FALSE | CU11: =(CP11-CE11)/CE11 -> #DIV/0! | CV11: =(CO11-CD11)/CD11 -> #DIV/0! | CW11: =CZ11 + ABS(CX11) + ABS(CY11) -> 0 | DD11: FALSE | DE11: FALSE | DF11: =(DA11-CR11)/CR11 -> #DIV/0! | DG11: =(CZ11-CO11)/CO11 -> #DIV/0! | DH11: =DK11 + ABS(DI11) + ABS(DJ11) -> 0 | DO11: FALSE | DP11: FALSE | DQ11: =(DL11-DA11)/DA11 -> #DIV/0! | DR11: =(DK11-CZ11)/CZ11 -> #DIV/0! | DS11: =DV11 + ABS(DT11) + ABS(DU11) -> 0 | DZ11: FALSE | EA11: FALSE | EB11: =(DW11-DN11)/DN11 -> #DIV/0! | EC11: =(DV11-DK11)/DK11 -> #DIV/0! | ED11: =EG11 + ABS(EE11) + ABS(EF11) -> 0 | EK11: FALSE | EL11: FALSE | EM11: =(EH11-DW11)/DW11 -> #DIV/0! | EN11: =(EG11-DV11)/DV11 -> #DIV/0! | EO11: =ER11 + ABS(EP11) + ABS(EQ11) -> 0 | EV11: FALSE | EW11: FALSE | EX11: =(ES11-EJ11)/EJ11 -> #DIV/0! | EY11: =(ER11-EG11)/EG11 -> #DIV/0!
C12: CASA DO ALBERGADO PRESIDENTE JOÃO PESSOA | D12: 1450022 | E12: 50 | F12: D17B0704493 | G12: 00027029697 | H12: COMPANHIA DE SANEAMENTO DE MINAS GERAIS COPASA MG | I12: 17.281.106/0001-03 | N12: 107 | P12: 245.29 | R12: 4865 | S12: 208 | T12: 1450.01.0005511/2026-51 | X12: =AA12 + ABS(Y12) + ABS(Z12) -> 5430.52 | Y12: -260.66 | Z12: 0 | AA12: 5169.86 | AB12: 218 | AC12: 10/03/2026 | AD12: 1450.01.0029372/2026-78 | AE12: TRUE | AF12: TRUE | AG12: =(AB12-S12)/S12 -> 0.048076923 | AH12: =(AA12-R12)/R12 -> 0.062663926 | AI12: =AL12 + ABS(AJ12) + ABS(AK12) -> 5591.41 | AJ12: -268.39 | AK12: 0 | AL12: 5323.02 | AM12: 215 | AN12: 46122 | AO12: 1450.01.0046622/2026-25 | AP12: TRUE | AQ12: TRUE | AR12: =(AM12-AB12)/AB12 -> -0.013761468 | AS12: =(AL12-AA12)/AA12 -> 0.02962556 | AT12: =AW12 + ABS(AU12) + ABS(AV12) -> 0 | BA12: FALSE | BB12: FALSE | BC12: =(AX12-AM12)/AM12 -> -1 | BD12: =(AW12-AL12)/AL12 -> -1 | BE12: =BH12 + ABS(BF12) + ABS(BG12) -> 0 | BL12: FALSE | BM12: FALSE | BN12: =(BI12-AZ12)/AZ12 -> #DIV/0! | BO12: =(BH12-AW12)/AW12 -> #DIV/0! | BP12: =BS12 + ABS(BQ12) + ABS(BR12) -> 0 | BW12: FALSE | BX12: FALSE | BY12: =(BT12-BI12)/BI12 -> #DIV/0! | BZ12: =(BS12-BH12)/BH12 -> #DIV/0! | CA12: =CD12 + ABS(CB12) + ABS(CC12) -> 0 | CH12: FALSE | CI12: FALSE | CJ12: =(CE12-BV12)/BV12 -> #DIV/0! | CK12: =(CD12-BS12)/BS12 -> #DIV/0! | CL12: =CO12 + ABS(CM12) + ABS(CN12) -> 0 | CS12: FALSE | CT12: FALSE | CU12: =(CP12-CE12)/CE12 -> #DIV/0! | CV12: =(CO12-CD12)/CD12 -> #DIV/0! | CW12: =CZ12 + ABS(CX12) + ABS(CY12) -> 0 | DD12: FALSE | DE12: FALSE | DF12: =(DA12-CR12)/CR12 -> #DIV/0! | DG12: =(CZ12-CO12)/CO12 -> #DIV/0! | DH12: =DK12 + ABS(DI12) + ABS(DJ12) -> 0 | DO12: FALSE | DP12: FALSE | DQ12: =(DL12-DA12)/DA12 -> #DIV/0! | DR12: =(DK12-CZ12)/CZ12 -> #DIV/0! | DS12: =DV12 + ABS(DT12) + ABS(DU12) -> 0 | DZ12: FALSE | EA12: FALSE | EB12: =(DW12-DN12)/DN12 -> #DIV/0! | EC12: =(DV12-DK12)/DK12 -> #DIV/0! | ED12: =EG12 + ABS(EE12) + ABS(EF12) -> 0 | EK12: FALSE | EL12: FALSE | EM12: =(EH12-DW12)/DW12 -> #DIV/0! | EN12: =(EG12-DV12)/DV12 -> #DIV/0! | EO12: =ER12 + ABS(EP12) + ABS(EQ12) -> 0 | EV12: FALSE | EW12: FALSE | EX12: =(ES12-EJ12)/EJ12 -> #DIV/0! | EY12: =(ER12-EG12)/EG12 -> #DIV/0!
C13: CENTRAL DE FLAGRANTES | D13: 1450022 | E13: 282 | F13: A19N0415854 | G13: 00000693537 | H13: COMPANHIA DE SANEAMENTO DE MINAS GERAIS COPASA MG | I13: 17.281.106/0001-03 | N13: 107 | P13: 45.95 | R13: 911.34 | S13: 48 | T13: 1450.01.0005511/2026-51 | X13: =AA13 + ABS(Y13) + ABS(Z13) -> 883.44 | Y13: -42.41 | Z13: 0 | AA13: 841.03 | AB13: 45 | AC13: 10/03/2026 | AD13: 1450.01.0029372/2026-78 | AE13: TRUE | AF13: TRUE | AG13: =(AB13-S13)/S13 -> -0.0625 | AH13: =(AA13-R13)/R13 -> -0.077150131 | AI13: =AL13 + ABS(AJ13) + ABS(AK13) -> 985.81 | AJ13: -47.32 | AK13: 0 | AL13: 938.49 | AM13: 47 | AN13: 46122 | AO13: 1450.01.0046622/2026-25 | AP13: TRUE | AQ13: TRUE | AR13: =(AM13-AB13)/AB13 -> 0.044444444 | AS13: =(AL13-AA13)/AA13 -> 0.11588172 | AT13: =AW13 + ABS(AU13) + ABS(AV13) -> 0 | BA13: FALSE | BB13: FALSE | BC13: =(AX13-AM13)/AM13 -> -1 | BD13: =(AW13-AL13)/AL13 -> -1 | BE13: =BH13 + ABS(BF13) + ABS(BG13) -> 0 | BL13: FALSE | BM13: FALSE | BN13: =(BI13-AZ13)/AZ13 -> #DIV/0! | BO13: =(BH13-AW13)/AW13 -> #DIV/0! | BP13: =BS13 + ABS(BQ13) + ABS(BR13) -> 0 | BW13: FALSE | BX13: FALSE | BY13: =(BT13-BI13)/BI13 -> #DIV/0! | BZ13: =(BS13-BH13)/BH13 -> #DIV/0! | CA13: =CD13 + ABS(CB13) + ABS(CC13) -> 0 | CH13: FALSE | CI13: FALSE | CJ13: =(CE13-BV13)/BV13 -> #DIV/0! | CK13: =(CD13-BS13)/BS13 -> #DIV/0! | CL13: =CO13 + ABS(CM13) + ABS(CN13) -> 0 | CS13: FALSE | CT13: FALSE | CU13: =(CP13-CE13)/CE13 -> #DIV/0! | CV13: =(CO13-CD13)/CD13 -> #DIV/0! | CW13: =CZ13 + ABS(CX13) + ABS(CY13) -> 0 | DD13: FALSE | DE13: FALSE | DF13: =(DA13-CR13)/CR13 -> #DIV/0! | DG13: =(CZ13-CO13)/CO13 -> #DIV/0! | DH13: =DK13 + ABS(DI13) + ABS(DJ13) -> 0 | DO13: FALSE | DP13: FALSE | DQ13: =(DL13-DA13)/DA13 -> #DIV/0! | DR13: =(DK13-CZ13)/CZ13 -> #DIV/0! | DS13: =DV13 + ABS(DT13) + ABS(DU13) -> 0 | DZ13: FALSE | EA13: FALSE | EB13: =(DW13-DN13)/DN13 -> #DIV/0! | EC13: =(DV13-DK13)/DK13 -> #DIV/0! | ED13: =EG13 + ABS(EE13) + ABS(EF13) -> 0 | EK13: FALSE | EL13: FALSE | EM13: =(EH13-DW13)/DW13 -> #DIV/0! | EN13: =(EG13-DV13)/DV13 -> #DIV/0! | EO13: =ER13 + ABS(EP13) + ABS(EQ13) -> 0 | EV13: FALSE | EW13: FALSE | EX13: =(ES13-EJ13)/EJ13 -> #DIV/0! | EY13: =(ER13-EG13)/EG13 -> #DIV/0!
C14: CERESP BETIM | D14: 1450022 | E14: 85 | F14: E17B0791102 G23C8001998 | G14: 00109188632 | H14: COMPANHIA DE SANEAMENTO DE MINAS GERAIS COPASA MG | I14: 17.281.106/0001-03 | N14: 107 | P14: 9263.7 | R14: 183730.14 | S14: 6418 | T14: 1450.01.0005511/2026-51 | X14: =AA14 + ABS(Y14) + ABS(Z14) -> 237196.39 | Y14: -11385.43 | Z14: 0 | AA14: 225810.96 | AB14: 7879 | AC14: 10/03/2026 | AD14: 1450.01.0029372/2026-78 | AE14: TRUE | AF14: TRUE | AG14: =(AB14-S14)/S14 -> 0.22764101 | AH14: =(AA14-R14)/R14 -> 0.22903602 | AI14: =AL14 + ABS(AJ14) + ABS(AK14) -> 232539.57 | AJ14: -11161.9 | AK14: 0 | AL14: 221377.67 | AM14: 7522 | AN14: 46122 | AO14: 1450.01.0046622/2026-25 | AP14: TRUE | AQ14: TRUE | AR14: =(AM14-AB14)/AB14 -> -0.045310319 | AS14: =(AL14-AA14)/AA14 -> -0.019632749 | AT14: =AW14 + ABS(AU14) + ABS(AV14) -> 0 | BA14: FALSE | BB14: FALSE | BC14: =(AX14-AM14)/AM14 -> -1 | BD14: =(AW14-AL14)/AL14 -> -1 | BE14: =BH14 + ABS(BF14) + ABS(BG14) -> 0 | BL14: FALSE | BM14: FALSE | BN14: =(BI14-AZ14)/AZ14 -> #DIV/0! | BO14: =(BH14-AW14)/AW14 -> #DIV/0! | BP14: =BS14 + ABS(BQ14) + ABS(BR14) -> 0 | BW14: FALSE | BX14: FALSE | BY14: =(BT14-BI14)/BI14 -> #DIV/0! | BZ14: =(BS14-BH14)/BH14 -> #DIV/0! | CA14: =CD14 + ABS(CB14) + ABS(CC14) -> 0 | CH14: FALSE | CI14: FALSE | CJ14: =(CE14-BV14)/BV14 -> #DIV/0! | CK14: =(CD14-BS14)/BS14 -> #DIV/0! | CL14: =CO14 + ABS(CM14) + ABS(CN14) -> 0 | CS14: FALSE | CT14: FALSE | CU14: =(CP14-CE14)/CE14 -> #DIV/0! | CV14: =(CO14-CD14)/CD14 -> #DIV/0! | CW14: =CZ14 + ABS(CX14) + ABS(CY14) -> 0 | DD14: FALSE | DE14: FALSE | DF14: =(DA14-CR14)/CR14 -> #DIV/0! | DG14: =(CZ14-CO14)/CO14 -> #DIV/0! | DH14: =DK14 + ABS(DI14) + ABS(DJ14) -> 0 | DO14: FALSE | DP14: FALSE | DQ14: =(DL14-DA14)/DA14 -> #DIV/0! | DR14: =(DK14-CZ14)/CZ14 -> #DIV/0! | DS14: =DV14 + ABS(DT14) + ABS(DU14) -> 0 | DZ14: FALSE | EA14: FALSE | EB14: =(DW14-DN14)/DN14 -> #DIV/0! | EC14: =(DV14-DK14)/DK14 -> #DIV/0! | ED14: =EG14 + ABS(EE14) + ABS(EF14) -> 0 | EK14: FALSE | EL14: FALSE | EM14: =(EH14-DW14)/DW14 -> #DIV/0! | EN14: =(EG14-DV14)/DV14 -> #DIV/0! | EO14: =ER14 + ABS(EP14) + ABS(EQ14) -> 0 | EV14: FALSE | EW14: FALSE | EX14: =(ES14-EJ14)/EJ14 -> #DIV/0! | EY14: =(ER14-EG14)/EG14 -> #DIV/0!
C15: CERESP CONTAGEM | D15: 1450022 | E15: 136 | F15: D17B0705014 | G15: 00002251426 | H15: COMPANHIA DE SANEAMENTO DE MINAS GERAIS COPASA MG | I15: 17.281.106/0001-03 | N15: 107 | P15: 284.5 | R15: 5642.68 | S15: 235 | T15: 1450.01.0005511/2026-51 | X15: =AA15 + ABS(Y15) + ABS(Z15) -> 16758.46 | Y15: -804.41 | Z15: 0 | AA15: 15954.05 | AB15: 593 | AC15: 10/03/2026 | AD15: 1450.01.0029372/2026-78 | AE15: TRUE | AF15: TRUE | AG15: =(AB15-S15)/S15 -> 1.5234043 | AH15: =(AA15-R15)/R15 -> 1.8273888 | AI15: =AL15 + ABS(AJ15) + ABS(AK15) -> 16160.55 | AJ15: -775.71 | AK15: 0 | AL15: 15384.84 | AM15: 553 | AN15: 46122 | AO15: 1450.01.0046622/2026-25 | AP15: TRUE | AQ15: TRUE | AR15: =(AM15-AB15)/AB15 -> -0.067453626 | AS15: =(AL15-AA15)/AA15 -> -0.035678088 | AT15: =AW15 + ABS(AU15) + ABS(AV15) -> 0 | BA15: FALSE | BB15: FALSE | BC15: =(AX15-AM15)/AM15 -> -1 | BD15: =(AW15-AL15)/AL15 -> -1 | BE15: =BH15 + ABS(BF15) + ABS(BG15) -> 0 | BL15: FALSE | BM15: FALSE | BN15: =(BI15-AZ15)/AZ15 -> #DIV/0! | BO15: =(BH15-AW15)/AW15 -> #DIV/0! | BP15: =BS15 + ABS(BQ15) + ABS(BR15) -> 0 | BW15: FALSE | BX15: FALSE | BY15: =(BT15-BI15)/BI15 -> #DIV/0! | BZ15: =(BS15-BH15)/BH15 -> #DIV/0! | CA15: =CD15 + ABS(CB15) + ABS(CC15) -> 0 | CH15: FALSE | CI15: FALSE | CJ15: =(CE15-BV15)/BV15 -> #DIV/0! | CK15: =(CD15-BS15)/BS15 -> #DIV/0! | CL15: =CO15 + ABS(CM15) + ABS(CN15) -> 0 | CS15: FALSE | CT15: FALSE | CU15: =(CP15-CE15)/CE15 -> #DIV/0! | CV15: =(CO15-CD15)/CD15 -> #DIV/0! | CW15: =CZ15 + ABS(CX15) + ABS(CY15) -> 0 | DD15: FALSE | DE15: FALSE | DF15: =(DA15-CR15)/CR15 -> #DIV/0! | DG15: =(CZ15-CO15)/CO15 -> #DIV/0! | DH15: =DK15 + ABS(DI15) + ABS(DJ15) -> 0 | DO15: FALSE | DP15: FALSE | DQ15: =(DL15-DA15)/DA15 -> #DIV/0! | DR15: =(DK15-CZ15)/CZ15 -> #DIV/0! | DS15: =DV15 + ABS(DT15) + ABS(DU15) -> 0 | DZ15: FALSE | EA15: FALSE | EB15: =(DW15-DN15)/DN15 -> #DIV/0! | EC15: =(DV15-DK15)/DK15 -> #DIV/0! | ED15: =EG15 + ABS(EE15) + ABS(EF15) -> 0 | EK15: FALSE | EL15: FALSE | EM15: =(EH15-DW15)/DW15 -> #DIV/0! | EN15: =(EG15-DV15)/DV15 -> #DIV/0! | EO15: =ER15 + ABS(EP15) + ABS(EQ15) -> 0 | EV15: FALSE | EW15: FALSE | EX15: =(ES15-EJ15)/EJ15 -> #DIV/0! | EY15: =(ER15-EG15)/EG15 -> #DIV/0!
C16: CERESP GAMELEIRA | D16: 1450022 | E16: 86 | F16: G23C8002161 G22C8100030 | G16: 00002027461 | H16: COMPANHIA DE SANEAMENTO DE MINAS GERAIS COPASA MG | I16: 17.281.106/0001-03 | N16: 107 | P16: 18235.64 | R16: 361673.59 | S16: 12596 | T16: 1450.01.0005511/2026-51 | X16: =AA16 + ABS(Y16) + ABS(Z16) -> 450100.83 | Y16: -21604.84 | Z16: 0 | AA16: 428495.99 | AB16: 14916 | AC16: 10/03/2026 | AD16: 1450.01.0029372/2026-78 | AE16: TRUE | AF16: TRUE | AG16: =(AB16-S16)/S16 -> 0.18418546 | AH16: =(AA16-R16)/R16 -> 0.18475886 | AI16: =AL16 + ABS(AJ16) + ABS(AK16) -> 262626.58 | AJ16: -12606.08 | AK16: 0 | AL16: 250020.5 | AM16: 8421 | AN16: 46122 | AO16: 1450.01.0046622/2026-25 | AP16: TRUE | AQ16: TRUE | AR16: =(AM16-AB16)/AB16 -> -0.43543846 | AS16: =(AL16-AA16)/AA16 -> -0.41651613 | AT16: =AW16 + ABS(AU16) + ABS(AV16) -> 0 | BA16: FALSE | BB16: FALSE | BC16: =(AX16-AM16)/AM16 -> -1 | BD16: =(AW16-AL16)/AL16 -> -1 | BE16: =BH16 + ABS(BF16) + ABS(BG16) -> 0 | BL16: FALSE | BM16: FALSE | BN16: =(BI16-AZ16)/AZ16 -> #DIV/0! | BO16: =(BH16-AW16)/AW16 -> #DIV/0! | BP16: =BS16 + ABS(BQ16) + ABS(BR16) -> 0 | BW16: FALSE | BX16: FALSE | BY16: =(BT16-BI16)/BI16 -> #DIV/0! | BZ16: =(BS16-BH16)/BH16 -> #DIV/0! | CA16: =CD16 + ABS(CB16) + ABS(CC16) -> 0 | CH16: FALSE | CI16: FALSE | CJ16: =(CE16-BV16)/BV16 -> #DIV/0! | CK16: =(CD16-BS16)/BS16 -> #DIV/0! | CL16: =CO16 + ABS(CM16) + ABS(CN16) -> 0 | CS16: FALSE | CT16: FALSE | CU16: =(CP16-CE16)/CE16 -> #DIV/0! | CV16: =(CO16-CD16)/CD16 -> #DIV/0! | CW16: =CZ16 + ABS(CX16) + ABS(CY16) -> 0 | DD16: FALSE | DE16: FALSE | DF16: =(DA16-CR16)/CR16 -> #DIV/0! | DG16: =(CZ16-CO16)/CO16 -> #DIV/0! | DH16: =DK16 + ABS(DI16) + ABS(DJ16) -> 0 | DO16: FALSE | DP16: FALSE | DQ16: =(DL16-DA16)/DA16 -> #DIV/0! | DR16: =(DK16-CZ16)/CZ16 -> #DIV/0! | DS16: =DV16 + ABS(DT16) + ABS(DU16) -> 0 | DZ16: FALSE | EA16: FALSE | EB16: =(DW16-DN16)/DN16 -> #DIV/0! | EC16: =(DV16-DK16)/DK16 -> #DIV/0! | ED16: =EG16 + ABS(EE16) + ABS(EF16) -> 0 | EK16: FALSE | EL16: FALSE | EM16: =(EH16-DW16)/DW16 -> #DIV/0! | EN16: =(EG16-DV16)/DV16 -> #DIV/0! | EO16: =ER16 + ABS(EP16) + ABS(EQ16) -> 0 | EV16: FALSE | EW16: FALSE | EX16: =(ES16-EJ16)/EJ16 -> #DIV/0! | EY16: =(ER16-EG16)/EG16 -> #DIV/0!
C17: CERESP IPATINGA (Santana do Paraiso) | D17: 1450022 | E17: 106 | F17: E18B0801588 | G17: 00105574660 | H17: COMPANHIA DE SANEAMENTO DE MINAS GERAIS COPASA MG | I17: 17.281.106/0001-03 | N17: 107 | P17: 7436.79 | R17: 147496.26 | S17: 5160 | T17: 1450.01.0005511/2026-51 | X17: =AA17 + ABS(Y17) + ABS(Z17) -> 177321.75 | Y17: -8511.44 | Z17: 0 | AA17: 168810.31 | AB17: 5900 | AC17: 10/03/2026 | AD17: 1450.01.0029372/2026-78 | AE17: TRUE | AF17: TRUE | AG17: =(AB17-S17)/S17 -> 0.14341085 | AH17: =(AA17-R17)/R17 -> 0.1445057 | AI17: =AL17 + ABS(AJ17) + ABS(AK17) -> 150467.34 | AJ17: -7222.43 | AK17: 0 | AL17: 143244.91 | AM17: 4897 | AN17: 46122 | AO17: 1450.01.0046622/2026-25 | AP17: TRUE | AQ17: TRUE | AR17: =(AM17-AB17)/AB17 -> -0.17 | AS17: =(AL17-AA17)/AA17 -> -0.15144454 | AT17: =AW17 + ABS(AU17) + ABS(AV17) -> 0 | BA17: FALSE | BB17: FALSE | BC17: =(AX17-AM17)/AM17 -> -1 | BD17: =(AW17-AL17)/AL17 -> -1 | BE17: =BH17 + ABS(BF17) + ABS(BG17) -> 0 | BL17: FALSE | BM17: FALSE | BN17: =(BI17-AZ17)/AZ17 -> #DIV/0! | BO17: =(BH17-AW17)/AW17 -> #DIV/0! | BP17: =BS17 + ABS(BQ17) + ABS(BR17) -> 0 | BW17: FALSE | BX17: FALSE | BY17: =(BT17-BI17)/BI17 -> #DIV/0! | BZ17: =(BS17-BH17)/BH17 -> #DIV/0! | CA17: =CD17 + ABS(CB17) + ABS(CC17) -> 0 | CH17: FALSE | CI17: FALSE | CJ17: =(CE17-BV17)/BV17 -> #DIV/0! | CK17: =(CD17-BS17)/BS17 -> #DIV/0! | CL17: =CO17 + ABS(CM17) + ABS(CN17) -> 0 | CS17: FALSE | CT17: FALSE | CU17: =(CP17-CE17)/CE17 -> #DIV/0! | CV17: =(CO17-CD17)/CD17 -> #DIV/0! | CW17: =CZ17 + ABS(CX17) + ABS(CY17) -> 0 | DD17: FALSE | DE17: FALSE | DF17: =(DA17-CR17)/CR17 -> #DIV/0! | DG17: =(CZ17-CO17)/CO17 -> #DIV/0! | DH17: =DK17 + ABS(DI17) + ABS(DJ17) -> 0 | DO17: FALSE | DP17: FALSE | DQ17: =(DL17-DA17)/DA17 -> #DIV/0! | DR17: =(DK17-CZ17)/CZ17 -> #DIV/0! | DS17: =DV17 + ABS(DT17) + ABS(DU17) -> 0 | DZ17: FALSE | EA17: FALSE | EB17: =(DW17-DN17)/DN17 -> #DIV/0! | EC17: =(DV17-DK17)/DK17 -> #DIV/0! | ED17: =EG17 + ABS(EE17) + ABS(EF17) -> 0 | EK17: FALSE | EL17: FALSE | EM17: =(EH17-DW17)/DW17 -> #DIV/0! | EN17: =(EG17-DV17)/DV17 -> #DIV/0! | EO17: =ER17 + ABS(EP17) + ABS(EQ17) -> 0 | EV17: FALSE | EW17: FALSE | EX17: =(ES17-EJ17)/EJ17 -> #DIV/0! | EY17: =(ER17-EG17)/EG17 -> #DIV/0!
C18: COMPLEXO PENITENCIÁRIO ESTEVÃO PINTO | D18: 1450022 | E18: 27 | F18: D17B7045870 | G18: 00119083850 | H18: COMPANHIA DE SANEAMENTO DE MINAS GERAIS COPASA MG | I18: 17.281.106/0001-03 | N18: 107 | P18: 2927.58 | R18: 58063.7 | S18: 2055 | T18: 1450.01.0005511/2026-51 | X18: =AA18 + ABS(Y18) + ABS(Z18) -> 33748.06 | Y18: -1619.91 | Z18: 0 | AA18: 32128.15 | AB18: 1151 | AC18: 10/03/2026 | AD18: 1450.01.0029372/2026-78 | AE18: TRUE | AF18: TRUE | AG18: =(AB18-S18)/S18 -> -0.43990268 | AH18: =(AA18-R18)/R18 -> -0.44667408 | AI18: =AL18 + ABS(AJ18) + ABS(AK18) -> 32032.5 | AJ18: -1537.56 | AK18: 0 | AL18: 30494.94 | AM18: 1048 | AN18: 46122 | AO18: 1450.01.0046622/2026-25 | AP18: TRUE | AQ18: TRUE | AR18: =(AM18-AB18)/AB18 -> -0.089487402 | AS18: =(AL18-AA18)/AA18 -> -0.050834237 | AT18: =AW18 + ABS(AU18) + ABS(AV18) -> 0 | BA18: FALSE | BB18: FALSE | BC18: =(AX18-AM18)/AM18 -> -1 | BD18: =(AW18-AL18)/AL18 -> -1 | BE18: =BH18 + ABS(BF18) + ABS(BG18) -> 0 | BL18: FALSE | BM18: FALSE | BN18: =(BI18-AZ18)/AZ18 -> #DIV/0! | BO18: =(BH18-AW18)/AW18 -> #DIV/0! | BP18: =BS18 + ABS(BQ18) + ABS(BR18) -> 0 | BW18: FALSE | BX18: FALSE | BY18: =(BT18-BI18)/BI18 -> #DIV/0! | BZ18: =(BS18-BH18)/BH18 -> #DIV/0! | CA18: =CD18 + ABS(CB18) + ABS(CC18) -> 0 | CH18: FALSE | CI18: FALSE | CJ18: =(CE18-BV18)/BV18 -> #DIV/0! | CK18: =(CD18-BS18)/BS18 -> #DIV/0! | CL18: =CO18 + ABS(CM18) + ABS(CN18) -> 0 | CS18: FALSE | CT18: FALSE | CU18: =(CP18-CE18)/CE18 -> #DIV/0! | CV18: =(CO18-CD18)/CD18 -> #DIV/0! | CW18: =CZ18 + ABS(CX18) + ABS(CY18) -> 0 | DD18: FALSE | DE18: FALSE | DF18: =(DA18-CR18)/CR18 -> #DIV/0! | DG18: =(CZ18-CO18)/CO18 -> #DIV/0! | DH18: =DK18 + ABS(DI18) + ABS(DJ18) -> 0 | DO18: FALSE | DP18: FALSE | DQ18: =(DL18-DA18)/DA18 -> #DIV/0! | DR18: =(DK18-CZ18)/CZ18 -> #DIV/0! | DS18: =DV18 + ABS(DT18) + ABS(DU18) -> 0 | DZ18: FALSE | EA18: FALSE | EB18: =(DW18-DN18)/DN18 -> #DIV/0! | EC18: =(DV18-DK18)/DK18 -> #DIV/0! | ED18: =EG18 + ABS(EE18) + ABS(EF18) -> 0 | EK18: FALSE | EL18: FALSE | EM18: =(EH18-DW18)/DW18 -> #DIV/0! | EN18: =(EG18-DV18)/DV18 -> #DIV/0! | EO18: =ER18 + ABS(EP18) + ABS(EQ18) -> 0 | EV18: FALSE | EW18: FALSE | EX18: =(ES18-EJ18)/EJ18 -> #DIV/0! | EY18: =(ER18-EG18)/EG18 -> #DIV/0!
C19: COMPLEXO PENITENCIÁRIO ESTEVÃO PINTO | D19: 1450022 | E19: 27 | F19: F18B0901260 | G19: 00011368802 | H19: COMPANHIA DE SANEAMENTO DE MINAS GERAIS COPASA MG | I19: 17.281.106/0001-03 | N19: 107 | P19: 4854.7 | R19: 96284.96 | S19: 3382 | T19: 1450.01.0005511/2026-51 | X19: =AA19 + ABS(Y19) + ABS(Z19) -> 101097.07 | Y19: -4852.66 | Z19: 0 | AA19: 96244.41 | AB19: 3370 | AC19: 10/03/2026 | AD19: 1450.01.0029372/2026-78 | AE19: TRUE | AF19: TRUE | AG19: =(AB19-S19)/S19 -> -0.0035481963 | AH19: =(AA19-R19)/R19 -> -0.00042114573 | AI19: =AL19 + ABS(AJ19) + ABS(AK19) -> 101928.38 | AJ19: -4892.56 | AK19: 0 | AL19: 97035.82 | AM19: 3250 | AN19: 46122 | AO19: 1450.01.0046622/2026-25 | AP19: TRUE | AQ19: TRUE | AR19: =(AM19-AB19)/AB19 -> -0.035608309 | AS19: =(AL19-AA19)/AA19 -> 0.0082229191 | AT19: =AW19 + ABS(AU19) + ABS(AV19) -> 0 | BA19: FALSE | BB19: FALSE | BC19: =(AX19-AM19)/AM19 -> -1 | BD19: =(AW19-AL19)/AL19 -> -1 | BE19: =BH19 + ABS(BF19) + ABS(BG19) -> 0 | BL19: FALSE | BM19: FALSE | BN19: =(BI19-AZ19)/AZ19 -> #DIV/0! | BO19: =(BH19-AW19)/AW19 -> #DIV/0! | BP19: =BS19 + ABS(BQ19) + ABS(BR19) -> 0 | BW19: FALSE | BX19: FALSE | BY19: =(BT19-BI19)/BI19 -> #DIV/0! | BZ19: =(BS19-BH19)/BH19 -> #DIV/0! | CA19: =CD19 + ABS(CB19) + ABS(CC19) -> 0 | CH19: FALSE | CI19: FALSE | CJ19: =(CE19-BV19)/BV19 -> #DIV/0! | CK19: =(CD19-BS19)/BS19 -> #DIV/0! | CL19: =CO19 + ABS(CM19) + ABS(CN19) -> 0 | CS19: FALSE | CT19: FALSE | CU19: =(CP19-CE19)/CE19 -> #DIV/0! | CV19: =(CO19-CD19)/CD19 -> #DIV/0! | CW19: =CZ19 + ABS(CX19) + ABS(CY19) -> 0 | DD19: FALSE | DE19: FALSE | DF19: =(DA19-CR19)/CR19 -> #DIV/0! | DG19: =(CZ19-CO19)/CO19 -> #DIV/0! | DH19: =DK19 + ABS(DI19) + ABS(DJ19) -> 0 | DO19: FALSE | DP19: FALSE | DQ19: =(DL19-DA19)/DA19 -> #DIV/0! | DR19: =(DK19-CZ19)/CZ19 -> #DIV/0! | DS19: =DV19 + ABS(DT19) + ABS(DU19) -> 0 | DZ19: FALSE | EA19: FALSE | EB19: =(DW19-DN19)/DN19 -> #DIV/0! | EC19: =(DV19-DK19)/DK19 -> #DIV/0! | ED19: =EG19 + ABS(EE19) + ABS(EF19) -> 0 | EK19: FALSE | EL19: FALSE | EM19: =(EH19-DW19)/DW19 -> #DIV/0! | EN19: =(EG19-DV19)/DV19 -> #DIV/0! | EO19: =ER19 + ABS(EP19) + ABS(EQ19) -> 0 | EV19: FALSE | EW19: FALSE | EX19: =(ES19-EJ19)/EJ19 -> #DIV/0! | EY19: =(ER19-EG19)/EG19 -> #DIV/0!
C20: COMPLEXO PENIT. NELSON HUNGRIA | D20: 1450022 | E20: 36 | F20: K22D2510787 | G20: 00017213169 | H20: COMPANHIA DE SANEAMENTO DE MINAS GERAIS COPASA MG | I20: 17.281.106/0001-03 | N20: 107 | P20: 38164.73 | R20: 756933.86 | S20: 26319 | T20: 1450.01.0005511/2026-51 | X20: =AA20 + ABS(Y20) + ABS(Z20) -> 1021755.1 | Y20: -49044.24 | Z20: 0 | AA20: 972710.81 | AB20: 33757 | AC20: 10/03/2026 | AD20: 1450.01.0029372/2026-78 | AE20: TRUE | AF20: TRUE | AG20: =(AB20-S20)/S20 -> 0.28260952 | AH20: =(AA20-R20)/R20 -> 0.28506711 | AI20: =AL20 + ABS(AJ20) + ABS(AK20) -> 766256.7 | AJ20: -36780.32 | AK20: 0 | AL20: 729476.38 | AM20: 24179 | AN20: 46122 | AO20: 1450.01.0046622/2026-25 | AP20: TRUE | AQ20: TRUE | AR20: =(AM20-AB20)/AB20 -> -0.28373374 | AS20: =(AL20-AA20)/AA20 -> -0.25005832 | AT20: =AW20 + ABS(AU20) + ABS(AV20) -> 0 | BA20: FALSE | BB20: FALSE | BC20: =(AX20-AM20)/AM20 -> -1 | BD20: =(AW20-AL20)/AL20 -> -1 | BE20: =BH20 + ABS(BF20) + ABS(BG20) -> 0 | BL20: FALSE | BM20: FALSE | BN20: =(BI20-AZ20)/AZ20 -> #DIV/0! | BO20: =(BH20-AW20)/AW20 -> #DIV/0! | BP20: =BS20 + ABS(BQ20) + ABS(BR20) -> 0 | BW20: FALSE | BX20: FALSE | BY20: =(BT20-BI20)/BI20 -> #DIV/0! | BZ20: =(BS20-BH20)/BH20 -> #DIV/0! | CA20: =CD20 + ABS(CB20) + ABS(CC20) -> 0 | CH20: FALSE | CI20: FALSE | CJ20: =(CE20-BV20)/BV20 -> #DIV/0! | CK20: =(CD20-BS20)/BS20 -> #DIV/0! | CL20: =CO20 + ABS(CM20) + ABS(CN20) -> 0 | CS20: FALSE | CT20: FALSE | CU20: =(CP20-CE20)/CE20 -> #DIV/0! | CV20: =(CO20-CD20)/CD20 -> #DIV/0! | CW20: =CZ20 + ABS(CX20) + ABS(CY20) -> 0 | DD20: FALSE | DE20: FALSE | DF20: =(DA20-CR20)/CR20 -> #DIV/0! | DG20: =(CZ20-CO20)/CO20 -> #DIV/0! | DH20: =DK20 + ABS(DI20) + ABS(DJ20) -> 0 | DO20: FALSE | DP20: FALSE | DQ20: =(DL20-DA20)/DA20 -> #DIV/0! | DR20: =(DK20-CZ20)/CZ20 -> #DIV/0! | DS20: =DV20 + ABS(DT20) + ABS(DU20) -> 0 | DZ20: FALSE | EA20: FALSE | EB20: =(DW20-DN20)/DN20 -> #DIV/0! | EC20: =(DV20-DK20)/DK20 -> #DIV/0! | ED20: =EG20 + ABS(EE20) + ABS(EF20) -> 0 | EK20: FALSE | EL20: FALSE | EM20: =(EH20-DW20)/DW20 -> #DIV/0! | EN20: =(EG20-DV20)/DV20 -> #DIV/0! | EO20: =ER20 + ABS(EP20) + ABS(EQ20) -> 0 | EV20: FALSE | EW20: FALSE | EX20: =(ES20-EJ20)/EJ20 -> #DIV/0! | EY20: =(ER20-EG20)/EG20 -> #DIV/0!
C21: COMPLEXO PENIT. NOSSA SENH. DO CARMO | D21: 1450022 | E21: 38 | F21: C18D0704419 | G21: 00114881669 | H21: COMPANHIA DE SANEAMENTO DE MINAS GERAIS COPASA MG | I21: 17.281.106/0001-03 | N21: 107 | P21: 1836.95 | R21: 36432.82 | S21: 1304 | T21: 1450.01.0005511/2026-51 | X21: =AA21 + ABS(Y21) + ABS(Z21) -> 50002.75 | Y21: -2400.13 | Z21: 0 | AA21: 47602.62 | AB21: 1673 | AC21: 10/03/2026 | AD21: 1450.01.0029372/2026-78 | AE21: TRUE | AF21: TRUE | AG21: =(AB21-S21)/S21 -> 0.28297546 | AH21: =(AA21-R21)/R21 -> 0.3065862 | AI21: =AL21 + ABS(AJ21) + ABS(AK21) -> 33841.79 | AJ21: -1624.41 | AK21: 0 | AL21: 32217.38 | AM21: 1105 | AN21: 46122 | AO21: 1450.01.0046622/2026-25 | AP21: TRUE | AQ21: TRUE | AR21: =(AM21-AB21)/AB21 -> -0.33950986 | AS21: =(AL21-AA21)/AA21 -> -0.32320154 | AT21: =AW21 + ABS(AU21) + ABS(AV21) -> 0 | BA21: FALSE | BB21: FALSE | BC21: =(AX21-AM21)/AM21 -> -1 | BD21: =(AW21-AL21)/AL21 -> -1 | BE21: =BH21 + ABS(BF21) + ABS(BG21) -> 0 | BL21: FALSE | BM21: FALSE | BN21: =(BI21-AZ21)/AZ21 -> #DIV/0! | BO21: =(BH21-AW21)/AW21 -> #DIV/0! | BP21: =BS21 + ABS(BQ21) + ABS(BR21) -> 0 | BW21: FALSE | BX21: FALSE | BY21: =(BT21-BI21)/BI21 -> #DIV/0! | BZ21: =(BS21-BH21)/BH21 -> #DIV/0! | CA21: =CD21 + ABS(CB21) + ABS(CC21) -> 0 | CH21: FALSE | CI21: FALSE | CJ21: =(CE21-BV21)/BV21 -> #DIV/0! | CK21: =(CD21-BS21)/BS21 -> #DIV/0! | CL21: =CO21 + ABS(CM21) + ABS(CN21) -> 0 | CS21: FALSE | CT21: FALSE | CU21: =(CP21-CE21)/CE21 -> #DIV/0! | CV21: =(CO21-CD21)/CD21 -> #DIV/0! | CW21: =CZ21 + ABS(CX21) + ABS(CY21) -> 0 | DD21: FALSE | DE21: FALSE | DF21: =(DA21-CR21)/CR21 -> #DIV/0! | DG21: =(CZ21-CO21)/CO21 -> #DIV/0! | DH21: =DK21 + ABS(DI21) + ABS(DJ21) -> 0 | DO21: FALSE | DP21: FALSE | DQ21: =(DL21-DA21)/DA21 -> #DIV/0! | DR21: =(DK21-CZ21)/CZ21 -> #DIV/0! | DS21: =DV21 + ABS(DT21) + ABS(DU21) -> 0 | DZ21: FALSE | EA21: FALSE | EB21: =(DW21-DN21)/DN21 -> #DIV/0! | EC21: =(DV21-DK21)/DK21 -> #DIV/0! | ED21: =EG21 + ABS(EE21) + ABS(EF21) -> 0 | EK21: FALSE | EL21: FALSE | EM21: =(EH21-DW21)/DW21 -> #DIV/0! | EN21: =(EG21-DV21)/DV21 -> #DIV/0! | EO21: =ER21 + ABS(EP21) + ABS(EQ21) -> 0 | EV21: FALSE | EW21: FALSE | EX21: =(ES21-EJ21)/EJ21 -> #DIV/0! | EY21: =(ER21-EG21)/EG21 -> #DIV/0!
... C30: PENITENCIÁRIA JOSÉ MARIA ALKIMIM | D30: 1450022 | E30: 35 | F30: Y24G1242371 | G30: 00106360655 | H30: COMPANHIA DE SANEAMENTO DE MINAS GERAIS COPASA MG | I30: 17.281.106/0001-03 | N30: 107 | P30: 7.61 | R30: 150.83 | S30: 10 | T30: 1450.01.0005511/2026-51 | X30: =AA30 + ABS(Y30) + ABS(Z30) -> 158.44 | Y30: -7.61 | Z30: 0 | AA30: 150.83 | AB30: 10 | AC30: 10/03/2026 | AD30: 1450.01.0029372/2026-78 | AE30: TRUE | AF30: TRUE | AG30: =(AB30-S30)/S30 -> 0 | AH30: =(AA30-R30)/R30 -> 0 | AI30: =AL30 + ABS(AJ30) + ABS(AK30) -> 160.33 | AJ30: -7.7 | AK30: 0 | AL30: 152.63 | AM30: 9 | AN30: 46122 | AO30: 1450.01.0046622/2026-25 | AP30: TRUE | AQ30: TRUE | AR30: =(AM30-AB30)/AB30 -> -0.1 | AS30: =(AL30-AA30)/AA30 -> 0.011933965 | AT30: =AW30 + ABS(AU30) + ABS(AV30) -> 0 | BA30: FALSE | BB30: FALSE | BC30: =(AX30-AM30)/AM30 -> -1 | BD30: =(AW30-AL30)/AL30 -> -1 | BE30: =BH30 + ABS(BF30) + ABS(BG30) -> 0 | BL30: FALSE | BM30: FALSE | BN30: =(BI30-AZ30)/AZ30 -> #DIV/0! | BO30: =(BH30-AW30)/AW30 -> #DIV/0! | BP30: =BS30 + ABS(BQ30) + ABS(BR30) -> 0 | BW30: FALSE | BX30: FALSE | BY30: =(BT30-BI30)/BI30 -> #DIV/0! | BZ30: =(BS30-BH30)/BH30 -> #DIV/0! | CA30: =CD30 + ABS(CB30) + ABS(CC30) -> 0 | CH30: FALSE | CI30: FALSE | CJ30: =(CE30-BV30)/BV30 -> #DIV/0! | CK30: =(CD30-BS30)/BS30 -> #DIV/0! | CL30: =CO30 + ABS(CM30) + ABS(CN30) -> 0 | CS30: FALSE | CT30: FALSE | CU30: =(CP30-CE30)/CE30 -> #DIV/0! | CV30: =(CO30-CD30)/CD30 -> #DIV/0! | CW30: =CZ30 + ABS(CX30) + ABS(CY30) -> 0 | DD30: FALSE | DE30: FALSE | DF30: =(DA30-CR30)/CR30 -> #DIV/0! | DG30: =(CZ30-CO30)/CO30 -> #DIV/0! | DH30: =DK30 + ABS(DI30) + ABS(DJ30) -> 0 | DO30: FALSE | DP30: FALSE | DQ30: =(DL30-DA30)/DA30 -> #DIV/0! | DR30: =(DK30-CZ30)/CZ30 -> #DIV/0! | DS30: =DV30 + ABS(DT30) + ABS(DU30) -> 0 | DZ30: FALSE | EA30: FALSE | EB30: =(DW30-DN30)/DN30 -> #DIV/0! | EC30: =(DV30-DK30)/DK30 -> #DIV/0! | ED30: =EG30 + ABS(EE30) + ABS(EF30) -> 0 | EK30: FALSE | EL30: FALSE | EM30: =(EH30-DW30)/DW30 -> #DIV/0! | EN30: =(EG30-DV30)/DV30 -> #DIV/0! | EO30: =ER30 + ABS(EP30) + ABS(EQ30) -> 0 | EV30: FALSE | EW30: FALSE | EX30: =(ES30-EJ30)/EJ30 -> #DIV/0! | EY30: =(ER30-EG30)/EG30 -> #DIV/0!
C31: PENITENCIÁRIA JOSÉ MARIA ALKIMIM | D31: 1450022 | E31: 35 | F31: Y23G1222172 | G31: 00106360779 | H31: COMPANHIA DE SANEAMENTO DE MINAS GERAIS COPASA MG | I31: 17.281.106/0001-03 | N31: 107 | P31: 2.6 | R31: 51.52 | T31: 1450.01.0005511/2026-51 | X31: =AA31 + ABS(Y31) + ABS(Z31) -> 242.67 | Y31: -11.65 | Z31: 0 | AA31: 231.02 | AB31: 15 | AC31: 10/03/2026 | AD31: 1450.01.0029372/2026-78 | AE31: TRUE | AF31: TRUE | AG31: 0 | AH31: =(AA31-R31)/R31 -> 3.4840839 | AI31: =AL31 + ABS(AJ31) + ABS(AK31) -> 618.48 | AJ31: -29.69 | AK31: 0 | AL31: 588.79 | AM31: 32 | AN31: 46122 | AO31: 1450.01.0046622/2026-25 | AP31: TRUE | AQ31: TRUE | AR31: =(AM31-AB31)/AB31 -> 1.1333333 | AS31: =(AL31-AA31)/AA31 -> 1.5486538 | AT31: =AW31 + ABS(AU31) + ABS(AV31) -> 0 | BA31: FALSE | BB31: FALSE | BC31: =(AX31-AM31)/AM31 -> -1 | BD31: =(AW31-AL31)/AL31 -> -1 | BE31: =BH31 + ABS(BF31) + ABS(BG31) -> 0 | BL31: FALSE | BM31: FALSE | BN31: =(BI31-AZ31)/AZ31 -> #DIV/0! | BO31: =(BH31-AW31)/AW31 -> #DIV/0! | BP31: =BS31 + ABS(BQ31) + ABS(BR31) -> 0 | BW31: FALSE | BX31: FALSE | BY31: =(BT31-BI31)/BI31 -> #DIV/0! | BZ31: =(BS31-BH31)/BH31 -> #DIV/0! | CA31: =CD31 + ABS(CB31) + ABS(CC31) -> 0 | CH31: FALSE | CI31: FALSE | CJ31: =(CE31-BV31)/BV31 -> #DIV/0! | CK31: =(CD31-BS31)/BS31 -> #DIV/0! | CL31: =CO31 + ABS(CM31) + ABS(CN31) -> 0 | CS31: FALSE | CT31: FALSE | CU31: =(CP31-CE31)/CE31 -> #DIV/0! | CV31: =(CO31-CD31)/CD31 -> #DIV/0! | CW31: =CZ31 + ABS(CX31) + ABS(CY31) -> 0 | DD31: FALSE | DE31: FALSE | DF31: =(DA31-CR31)/CR31 -> #DIV/0! | DG31: =(CZ31-CO31)/CO31 -> #DIV/0! | DH31: =DK31 + ABS(DI31) + ABS(DJ31) -> 0 | DO31: FALSE | DP31: FALSE | DQ31: =(DL31-DA31)/DA31 -> #DIV/0! | DR31: =(DK31-CZ31)/CZ31 -> #DIV/0! | DS31: =DV31 + ABS(DT31) + ABS(DU31) -> 0 | DZ31: FALSE | EA31: FALSE | EB31: =(DW31-DN31)/DN31 -> #DIV/0! | EC31: =(DV31-DK31)/DK31 -> #DIV/0! | ED31: =EG31 + ABS(EE31) + ABS(EF31) -> 0 | EK31: FALSE | EL31: FALSE | EM31: =(EH31-DW31)/DW31 -> #DIV/0! | EN31: =(EG31-DV31)/DV31 -> #DIV/0! | EO31: =ER31 + ABS(EP31) + ABS(EQ31) -> 0 | EV31: FALSE | EW31: FALSE | EX31: =(ES31-EJ31)/EJ31 -> #DIV/0! | EY31: =(ER31-EG31)/EG31 -> #DIV/0!
C32: PENITENCIÁRIA JOSÉ MARIA ALKIMIM | D32: 1450022 | E32: 35 | F32: Y24F0430859 | G32: 00106359029 | H32: COMPANHIA DE SANEAMENTO DE MINAS GERAIS COPASA MG | I32: 17.281.106/0001-03 | N32: 107 | P32: 15.69 | R32: 311.2 | S32: 20 | T32: 1450.01.0005511/2026-51 | X32: =AA32 + ABS(Y32) + ABS(Z32) -> 293.2 | Y32: -14.07 | Z32: 0 | AA32: 279.13 | AB32: 18 | AC32: 10/03/2026 | AD32: 1450.01.0029372/2026-78 | AE32: TRUE | AF32: TRUE | AG32: =(AB32-S32)/S32 -> -0.1 | AH32: =(AA32-R32)/R32 -> -0.1030527 | AI32: =AL32 + ABS(AJ32) + ABS(AK32) -> 226.75 | AJ32: -10.88 | AK32: 0 | AL32: 215.87 | AM32: 13 | AN32: 46122 | AO32: 1450.01.0046622/2026-25 | AP32: TRUE | AQ32: TRUE | AR32: =(AM32-AB32)/AB32 -> -0.27777778 | AS32: =(AL32-AA32)/AA32 -> -0.22663275 | AT32: =AW32 + ABS(AU32) + ABS(AV32) -> 0 | BA32: FALSE | BB32: FALSE | BC32: =(AX32-AM32)/AM32 -> -1 | BD32: =(AW32-AL32)/AL32 -> -1 | BE32: =BH32 + ABS(BF32) + ABS(BG32) -> 0 | BL32: FALSE | BM32: FALSE | BN32: =(BI32-AZ32)/AZ32 -> #DIV/0! | BO32: =(BH32-AW32)/AW32 -> #DIV/0! | BP32: =BS32 + ABS(BQ32) + ABS(BR32) -> 0 | BW32: FALSE | BX32: FALSE | BY32: =(BT32-BI32)/BI32 -> #DIV/0! | BZ32: =(BS32-BH32)/BH32 -> #DIV/0! | CA32: =CD32 + ABS(CB32) + ABS(CC32) -> 0 | CH32: FALSE | CI32: FALSE | CJ32: =(CE32-BV32)/BV32 -> #DIV/0! | CK32: =(CD32-BS32)/BS32 -> #DIV/0! | CL32: =CO32 + ABS(CM32) + ABS(CN32) -> 0 | CS32: FALSE | CT32: FALSE | CU32: =(CP32-CE32)/CE32 -> #DIV/0! | CV32: =(CO32-CD32)/CD32 -> #DIV/0! | CW32: =CZ32 + ABS(CX32) + ABS(CY32) -> 0 | DD32: FALSE | DE32: FALSE | DF32: =(DA32-CR32)/CR32 -> #DIV/0! | DG32: =(CZ32-CO32)/CO32 -> #DIV/0! | DH32: =DK32 + ABS(DI32) + ABS(DJ32) -> 0 | DO32: FALSE | DP32: FALSE | DQ32: =(DL32-DA32)/DA32 -> #DIV/0! | DR32: =(DK32-CZ32)/CZ32 -> #DIV/0! | DS32: =DV32 + ABS(DT32) + ABS(DU32) -> 0 | DZ32: FALSE | EA32: FALSE | EB32: =(DW32-DN32)/DN32 -> #DIV/0! | EC32: =(DV32-DK32)/DK32 -> #DIV/0! | ED32: =EG32 + ABS(EE32) + ABS(EF32) -> 0 | EK32: FALSE | EL32: FALSE | EM32: =(EH32-DW32)/DW32 -> #DIV/0! | EN32: =(EG32-DV32)/DV32 -> #DIV/0! | EO32: =ER32 + ABS(EP32) + ABS(EQ32) -> 0 | EV32: FALSE | EW32: FALSE | EX32: =(ES32-EJ32)/EJ32 -> #DIV/0! | EY32: =(ER32-EG32)/EG32 -> #DIV/0!
C33: PENITENCIÁRIA JOSÉ MARIA ALKIMIM | D33: 1450022 | E33: 35 | F33: A24H0025317 | G33: 00106357140 | H33: COMPANHIA DE SANEAMENTO DE MINAS GERAIS COPASA MG | I33: 17.281.106/0001-03 | N33: 107 | P33: 24.86 | R33: 493.08 | S33: 29 | T33: 1450.01.0005511/2026-51 | X33: =AA33 + ABS(Y33) + ABS(Z33) -> 1111.67 | Y33: -53.36 | Z33: 0 | AA33: 1058.31 | AB33: 54 | AC33: 10/03/2026 | AD33: 1450.01.0029372/2026-78 | AE33: TRUE | AF33: TRUE | AG33: =(AB33-S33)/S33 -> 0.86206897 | AH33: =(AA33-R33)/R33 -> 1.1463251 | AI33: =AL33 + ABS(AJ33) + ABS(AK33) -> 931.83 | AJ33: -44.73 | AK33: 0 | AL33: 887.1 | AM33: 45 | AN33: 46122 | AO33: 1450.01.0046622/2026-25 | AP33: TRUE | AQ33: TRUE | AR33: =(AM33-AB33)/AB33 -> -0.16666667 | AS33: =(AL33-AA33)/AA33 -> -0.1617768 | AT33: =AW33 + ABS(AU33) + ABS(AV33) -> 0 | BA33: FALSE | BB33: FALSE | BC33: =(AX33-AM33)/AM33 -> -1 | BD33: =(AW33-AL33)/AL33 -> -1 | BE33: =BH33 + ABS(BF33) + ABS(BG33) -> 0 | BL33: FALSE | BM33: FALSE | BN33: =(BI33-AZ33)/AZ33 -> #DIV/0! | BO33: =(BH33-AW33)/AW33 -> #DIV/0! | BP33: =BS33 + ABS(BQ33) + ABS(BR33) -> 0 | BW33: FALSE | BX33: FALSE | BY33: =(BT33-BI33)/BI33 -> #DIV/0! | BZ33: =(BS33-BH33)/BH33 -> #DIV/0! | CA33: =CD33 + ABS(CB33) + ABS(CC33) -> 0 | CH33: FALSE | CI33: FALSE | CJ33: =(CE33-BV33)/BV33 -> #DIV/0! | CK33: =(CD33-BS33)/BS33 -> #DIV/0! | CL33: =CO33 + ABS(CM33) + ABS(CN33) -> 0 | CS33: FALSE | CT33: FALSE | CU33: =(CP33-CE33)/CE33 -> #DIV/0! | CV33: =(CO33-CD33)/CD33 -> #DIV/0! | CW33: =CZ33 + ABS(CX33) + ABS(CY33) -> 0 | DD33: FALSE | DE33: FALSE | DF33: =(DA33-CR33)/CR33 -> #DIV/0! | DG33: =(CZ33-CO33)/CO33 -> #DIV/0! | DH33: =DK33 + ABS(DI33) + ABS(DJ33) -> 0 | DO33: FALSE | DP33: FALSE | DQ33: =(DL33-DA33)/DA33 -> #DIV/0! | DR33: =(DK33-CZ33)/CZ33 -> #DIV/0! | DS33: =DV33 + ABS(DT33) + ABS(DU33) -> 0 | DZ33: FALSE | EA33: FALSE | EB33: =(DW33-DN33)/DN33 -> #DIV/0! | EC33: =(DV33-DK33)/DK33 -> #DIV/0! | ED33: =EG33 + ABS(EE33) + ABS(EF33) -> 0 | EK33: FALSE | EL33: FALSE | EM33: =(EH33-DW33)/DW33 -> #DIV/0! | EN33: =(EG33-DV33)/DV33 -> #DIV/0! | EO33: =ER33 + ABS(EP33) + ABS(EQ33) -> 0 | EV33: FALSE | EW33: FALSE | EX33: =(ES33-EJ33)/EJ33 -> #DIV/0! | EY33: =(ER33-EG33)/EG33 -> #DIV/0!
C34: PENITENCIÁRIA JOSÉ MARIA ALKIMIM | D34: 1450022 | E34: 35 | F34: Y24S1242222 | G34: 00106356950 | H34: COMPANHIA DE SANEAMENTO DE MINAS GERAIS COPASA MG | I34: 17.281.106/0001-03 | N34: 107 | P34: 30.97 | R34: 614.34 | S34: 35 | T34: 1450.01.0005511/2026-51 | X34: =AA34 + ABS(Y34) + ABS(Z34) -> 276.36 | Y34: -13.27 | Z34: 0 | AA34: 263.09 | AB34: 17 | AC34: 10/03/2026 | AD34: 1450.01.0029372/2026-78 | AE34: TRUE | AF34: TRUE | AG34: =(AB34-S34)/S34 -> -0.51428571 | AH34: =(AA34-R34)/R34 -> -0.5717518 | AI34: =AL34 + ABS(AJ34) + ABS(AK34) -> 262.21 | AJ34: -12.59 | AK34: 0 | AL34: 249.62 | AM34: 15 | AN34: 46122 | AO34: 1450.01.0046622/2026-25 | AP34: TRUE | AQ34: TRUE | AR34: =(AM34-AB34)/AB34 -> -0.11764706 | AS34: =(AL34-AA34)/AA34 -> -0.051199209 | AT34: =AW34 + ABS(AU34) + ABS(AV34) -> 0 | BA34: FALSE | BB34: FALSE | BC34: =(AX34-AM34)/AM34 -> -1 | BD34: =(AW34-AL34)/AL34 -> -1 | BE34: =BH34 + ABS(BF34) + ABS(BG34) -> 0 | BL34: FALSE | BM34: FALSE | BN34: =(BI34-AZ34)/AZ34 -> #DIV/0! | BO34: =(BH34-AW34)/AW34 -> #DIV/0! | BP34: =BS34 + ABS(BQ34) + ABS(BR34) -> 0 | BW34: FALSE | BX34: FALSE | BY34: =(BT34-BI34)/BI34 -> #DIV/0! | BZ34: =(BS34-BH34)/BH34 -> #DIV/0! | CA34: =CD34 + ABS(CB34) + ABS(CC34) -> 0 | CH34: FALSE | CI34: FALSE | CJ34: =(CE34-BV34)/BV34 -> #DIV/0! | CK34: =(CD34-BS34)/BS34 -> #DIV/0! | CL34: =CO34 + ABS(CM34) + ABS(CN34) -> 0 | CS34: FALSE | CT34: FALSE | CU34: =(CP34-CE34)/CE34 -> #DIV/0! | CV34: =(CO34-CD34)/CD34 -> #DIV/0! | CW34: =CZ34 + ABS(CX34) + ABS(CY34) -> 0 | DD34: FALSE | DE34: FALSE | DF34: =(DA34-CR34)/CR34 -> #DIV/0! | DG34: =(CZ34-CO34)/CO34 -> #DIV/0! | DH34: =DK34 + ABS(DI34) + ABS(DJ34) -> 0 | DO34: FALSE | DP34: FALSE | DQ34: =(DL34-DA34)/DA34 -> #DIV/0! | DR34: =(DK34-CZ34)/CZ34 -> #DIV/0! | DS34: =DV34 + ABS(DT34) + ABS(DU34) -> 0 | DZ34: FALSE | EA34: FALSE | EB34: =(DW34-DN34)/DN34 -> #DIV/0! | EC34: =(DV34-DK34)/DK34 -> #DIV/0! | ED34: =EG34 + ABS(EE34) + ABS(EF34) -> 0 | EK34: FALSE | EL34: FALSE | EM34: =(EH34-DW34)/DW34 -> #DIV/0! | EN34: =(EG34-DV34)/DV34 -> #DIV/0! | EO34: =ER34 + ABS(EP34) + ABS(EQ34) -> 0 | EV34: FALSE | EW34: FALSE | EX34: =(ES34-EJ34)/EJ34 -> #DIV/0! | EY34: =(ER34-EG34)/EG34 -> #DIV/0!
C35: PENITENCIÁRIA JOSÉ MARIA ALKIMIM | D35: 1450022 | E35: 35 | F35: Y20G0674247 | G35: 00106359878 | H35: COMPANHIA DE SANEAMENTO DE MINAS GERAIS COPASA MG | I35: 17.281.106/0001-03 | N35: 107 | P35: 9.22 | R35: 182.91 | S35: 12 | T35: 1450.01.0005511/2026-51 | X35: =AA35 + ABS(Y35) + ABS(Z35) -> 242.67 | Y35: -11.65 | Z35: 0 | AA35: 231.02 | AB35: 15 | AC35: 10/03/2026 | AD35: 1450.01.0029372/2026-78 | AE35: TRUE | AF35: TRUE | AG35: =(AB35-S35)/S35 -> 0.25 | AH35: =(AA35-R35)/R35 -> 0.26302553 | AI35: =AL35 + ABS(AJ35) + ABS(AK35) -> 279.94 | AJ35: -13.44 | AK35: 0 | AL35: 266.5 | AM35: 16 | AN35: 46122 | AO35: 1450.01.0046622/2026-25 | AP35: TRUE | AQ35: TRUE | AR35: =(AM35-AB35)/AB35 -> 0.066666667 | AS35: =(AL35-AA35)/AA35 -> 0.15357978 | AT35: =AW35 + ABS(AU35) + ABS(AV35) -> 0 | BA35: FALSE | BB35: FALSE | BC35: =(AX35-AM35)/AM35 -> -1 | BD35: =(AW35-AL35)/AL35 -> -1 | BE35: =BH35 + ABS(BF35) + ABS(BG35) -> 0 | BL35: FALSE | BM35: FALSE | BN35: =(BI35-AZ35)/AZ35 -> #DIV/0! | BO35: =(BH35-AW35)/AW35 -> #DIV/0! | BP35: =BS35 + ABS(BQ35) + ABS(BR35) -> 0 | BW35: FALSE | BX35: FALSE | BY35: =(BT35-BI35)/BI35 -> #DIV/0! | BZ35: =(BS35-BH35)/BH35 -> #DIV/0! | CA35: =CD35 + ABS(CB35) + ABS(CC35) -> 0 | CH35: FALSE | CI35: FALSE | CJ35: =(CE35-BV35)/BV35 -> #DIV/0! | CK35: =(CD35-BS35)/BS35 -> #DIV/0! | CL35: =CO35 + ABS(CM35) + ABS(CN35) -> 0 | CS35: FALSE | CT35: FALSE | CU35: =(CP35-CE35)/CE35 -> #DIV/0! | CV35: =(CO35-CD35)/CD35 -> #DIV/0! | CW35: =CZ35 + ABS(CX35) + ABS(CY35) -> 0 | DD35: FALSE | DE35: FALSE | DF35: =(DA35-CR35)/CR35 -> #DIV/0! | DG35: =(CZ35-CO35)/CO35 -> #DIV/0! | DH35: =DK35 + ABS(DI35) + ABS(DJ35) -> 0 | DO35: FALSE | DP35: FALSE | DQ35: =(DL35-DA35)/DA35 -> #DIV/0! | DR35: =(DK35-CZ35)/CZ35 -> #DIV/0! | DS35: =DV35 + ABS(DT35) + ABS(DU35) -> 0 | DZ35: FALSE | EA35: FALSE | EB35: =(DW35-DN35)/DN35 -> #DIV/0! | EC35: =(DV35-DK35)/DK35 -> #DIV/0! | ED35: =EG35 + ABS(EE35) + ABS(EF35) -> 0 | EK35: FALSE | EL35: FALSE | EM35: =(EH35-DW35)/DW35 -> #DIV/0! | EN35: =(EG35-DV35)/DV35 -> #DIV/0! | EO35: =ER35 + ABS(EP35) + ABS(EQ35) -> 0 | EV35: FALSE | EW35: FALSE | EX35: =(ES35-EJ35)/EJ35 -> #DIV/0! | EY35: =(ER35-EG35)/EG35 -> #DIV/0!
C36: PENITENCIÁRIA JOSÉ MARIA ALKIMIM | D36: 1450022 | E36: 35 | F36: Y21S0634297 | G36: 00106360744 | H36: COMPANHIA DE SANEAMENTO DE MINAS GERAIS COPASA MG | I36: 17.281.106/0001-03 | N36: 107 | P36: 4.2 | R36: 83.28 | S36: 4 | T36: 1450.01.0005511/2026-51 | X36: =AA36 + ABS(Y36) + ABS(Z36) -> 242.67 | Y36: -11.65 | Z36: 0 | AA36: 231.02 | AB36: 15 | AC36: 10/03/2026 | AD36: 1450.01.0029372/2026-78 | AE36: TRUE | AF36: TRUE | AG36: =(AB36-S36)/S36 -> 2.75 | AH36: =(AA36-R36)/R36 -> 1.7740154 | AI36: =AL36 + ABS(AJ36) + ABS(AK36) -> 191.29 | AJ36: -9.18 | AK36: 0 | AL36: 182.11 | AM36: 11 | AN36: 46122 | AO36: 1450.01.0046622/2026-25 | AP36: TRUE | AQ36: TRUE | AR36: =(AM36-AB36)/AB36 -> -0.26666667 | AS36: =(AL36-AA36)/AA36 -> -0.21171327 | AT36: =AW36 + ABS(AU36) + ABS(AV36) -> 0 | BA36: FALSE | BB36: FALSE | BC36: =(AX36-AM36)/AM36 -> -1 | BD36: =(AW36-AL36)/AL36 -> -1 | BE36: =BH36 + ABS(BF36) + ABS(BG36) -> 0 | BL36: FALSE | BM36: FALSE | BN36: =(BI36-AZ36)/AZ36 -> #DIV/0! | BO36: =(BH36-AW36)/AW36 -> #DIV/0! | BP36: =BS36 + ABS(BQ36) + ABS(BR36) -> 0 | BW36: FALSE | BX36: FALSE | BY36: =(BT36-BI36)/BI36 -> #DIV/0! | BZ36: =(BS36-BH36)/BH36 -> #DIV/0! | CA36: =CD36 + ABS(CB36) + ABS(CC36) -> 0 | CH36: FALSE | CI36: FALSE | CJ36: =(CE36-BV36)/BV36 -> #DIV/0! | CK36: =(CD36-BS36)/BS36 -> #DIV/0! | CL36: =CO36 + ABS(CM36) + ABS(CN36) -> 0 | CS36: FALSE | CT36: FALSE | CU36: =(CP36-CE36)/CE36 -> #DIV/0! | CV36: =(CO36-CD36)/CD36 -> #DIV/0! | CW36: =CZ36 + ABS(CX36) + ABS(CY36) -> 0 | DD36: FALSE | DE36: FALSE | DF36: =(DA36-CR36)/CR36 -> #DIV/0! | DG36: =(CZ36-CO36)/CO36 -> #DIV/0! | DH36: =DK36 + ABS(DI36) + ABS(DJ36) -> 0 | DO36: FALSE | DP36: FALSE | DQ36: =(DL36-DA36)/DA36 -> #DIV/0! | DR36: =(DK36-CZ36)/CZ36 -> #DIV/0! | DS36: =DV36 + ABS(DT36) + ABS(DU36) -> 0 | DZ36: FALSE | EA36: FALSE | EB36: =(DW36-DN36)/DN36 -> #DIV/0! | EC36: =(DV36-DK36)/DK36 -> #DIV/0! | ED36: =EG36 + ABS(EE36) + ABS(EF36) -> 0 | EK36: FALSE | EL36: FALSE | EM36: =(EH36-DW36)/DW36 -> #DIV/0! | EN36: =(EG36-DV36)/DV36 -> #DIV/0! | EO36: =ER36 + ABS(EP36) + ABS(EQ36) -> 0 | EV36: FALSE | EW36: FALSE | EX36: =(ES36-EJ36)/EJ36 -> #DIV/0! | EY36: =(ER36-EG36)/EG36 -> #DIV/0!
C37: PENITENCIÁRIA JOSÉ MARIA ALKIMIM | D37: 1450022 | E37: 35 | F37: Y23G1129610 | G37: 00106360884 | H37: COMPANHIA DE SANEAMENTO DE MINAS GERAIS COPASA MG | I37: 17.281.106/0001-03 | N37: 107 | P37: 3 | R37: 59.46 | S37: 1 | T37: 1450.01.0005511/2026-51 | X37: =AA37 + ABS(Y37) + ABS(Z37) -> 54.12 | Y37: -2.6 | Z37: 0 | AA37: 51.52 | AB37: 0 | AC37: 10/03/2026 | AD37: 1450.01.0029372/2026-78 | AE37: TRUE | AF37: TRUE | AG37: =(AB37-S37)/S37 -> -1 | AH37: =(AA37-R37)/R37 -> -0.13353515 | AI37: =AL37 + ABS(AJ37) + ABS(AK37) -> 63.39 | AJ37: -3.04 | AK37: 0 | AL37: 60.35 | AM37: 0 | AN37: 46122 | AO37: 1450.01.0046622/2026-25 | AP37: TRUE | AQ37: TRUE | AR37: 0 | AS37: =(AL37-AA37)/AA37 -> 0.17138975 | AT37: =AW37 + ABS(AU37) + ABS(AV37) -> 0 | BA37: FALSE | BB37: FALSE | BC37: =(AX37-AM37)/AM37 -> #DIV/0! | BD37: =(AW37-AL37)/AL37 -> -1 | BE37: =BH37 + ABS(BF37) + ABS(BG37) -> 0 | BL37: FALSE | BM37: FALSE | BN37: =(BI37-AZ37)/AZ37 -> #DIV/0! | BO37: =(BH37-AW37)/AW37 -> #DIV/0! | BP37: =BS37 + ABS(BQ37) + ABS(BR37) -> 0 | BW37: FALSE | BX37: FALSE | BY37: =(BT37-BI37)/BI37 -> #DIV/0! | BZ37: =(BS37-BH37)/BH37 -> #DIV/0! | CA37: =CD37 + ABS(CB37) + ABS(CC37) -> 0 | CH37: FALSE | CI37: FALSE | CJ37: =(CE37-BV37)/BV37 -> #DIV/0! | CK37: =(CD37-BS37)/BS37 -> #DIV/0! | CL37: =CO37 + ABS(CM37) + ABS(CN37) -> 0 | CS37: FALSE | CT37: FALSE | CU37: =(CP37-CE37)/CE37 -> #DIV/0! | CV37: =(CO37-CD37)/CD37 -> #DIV/0! | CW37: =CZ37 + ABS(CX37) + ABS(CY37) -> 0 | DD37: FALSE | DE37: FALSE | DF37: =(DA37-CR37)/CR37 -> #DIV/0! | DG37: =(CZ37-CO37)/CO37 -> #DIV/0! | DH37: =DK37 + ABS(DI37) + ABS(DJ37) -> 0 | DO37: FALSE | DP37: FALSE | DQ37: =(DL37-DA37)/DA37 -> #DIV/0! | DR37: =(DK37-CZ37)/CZ37 -> #DIV/0! | DS37: =DV37 + ABS(DT37) + ABS(DU37) -> 0 | DZ37: FALSE | EA37: FALSE | EB37: =(DW37-DN37)/DN37 -> #DIV/0! | EC37: =(DV37-DK37)/DK37 -> #DIV/0! | ED37: =EG37 + ABS(EE37) + ABS(EF37) -> 0 | EK37: FALSE | EL37: FALSE | EM37: =(EH37-DW37)/DW37 -> #DIV/0! | EN37: =(EG37-DV37)/DV37 -> #DIV/0! | EO37: =ER37 + ABS(EP37) + ABS(EQ37) -> 0 | EV37: FALSE | EW37: FALSE | EX37: =(ES37-EJ37)/EJ37 -> #DIV/0! | EY37: =(ER37-EG37)/EG37 -> #DIV/0!
C38: PENITENCIÁRIA JOSÉ MARIA ALKIMIM | D38: 1450022 | E38: 35 | F38: A24H0001971 | G38: 00106359614 | H38: COMPANHIA DE SANEAMENTO DE MINAS GERAIS COPASA MG | I38: 17.281.106/0001-03 | N38: 107 | P38: 27.92 | R38: 553.71 | S38: 32 | T38: 1450.01.0005511/2026-51 | X38: =AA38 + ABS(Y38) + ABS(Z38) -> 242.67 | Y38: -11.65 | Z38: 0 | AA38: 231.02 | AB38: 15 | AC38: 10/03/2026 | AD38: 1450.01.0029372/2026-78 | AE38: TRUE | AF38: TRUE | AG38: =(AB38-S38)/S38 -> -0.53125 | AH38: =(AA38-R38)/R38 -> -0.58277799 | AI38: =AL38 + ABS(AJ38) + ABS(AK38) -> 147.11 | AJ38: -7.06 | AK38: 0 | AL38: 140.05 | AM38: 8 | AN38: 46122 | AO38: 1450.01.0046622/2026-25 | AP38: TRUE | AQ38: TRUE | AR38: =(AM38-AB38)/AB38 -> -0.46666667 | AS38: =(AL38-AA38)/AA38 -> -0.39377543 | AT38: =AW38 + ABS(AU38) + ABS(AV38) -> 0 | BA38: FALSE | BB38: FALSE | BC38: =(AX38-AM38)/AM38 -> -1 | BD38: =(AW38-AL38)/AL38 -> -1 | BE38: =BH38 + ABS(BF38) + ABS(BG38) -> 0 | BL38: FALSE | BM38: FALSE | BN38: =(BI38-AZ38)/AZ38 -> #DIV/0! | BO38: =(BH38-AW38)/AW38 -> #DIV/0! | BP38: =BS38 + ABS(BQ38) + ABS(BR38) -> 0 | BW38: FALSE | BX38: FALSE | BY38: =(BT38-BI38)/BI38 -> #DIV/0! | BZ38: =(BS38-BH38)/BH38 -> #DIV/0! | CA38: =CD38 + ABS(CB38) + ABS(CC38) -> 0 | CH38: FALSE | CI38: FALSE | CJ38: =(CE38-BV38)/BV38 -> #DIV/0! | CK38: =(CD38-BS38)/BS38 -> #DIV/0! | CL38: =CO38 + ABS(CM38) + ABS(CN38) -> 0 | CS38: FALSE | CT38: FALSE | CU38: =(CP38-CE38)/CE38 -> #DIV/0! | CV38: =(CO38-CD38)/CD38 -> #DIV/0! | CW38: =CZ38 + ABS(CX38) + ABS(CY38) -> 0 | DD38: FALSE | DE38: FALSE | DF38: =(DA38-CR38)/CR38 -> #DIV/0! | DG38: =(CZ38-CO38)/CO38 -> #DIV/0! | DH38: =DK38 + ABS(DI38) + ABS(DJ38) -> 0 | DO38: FALSE | DP38: FALSE | DQ38: =(DL38-DA38)/DA38 -> #DIV/0! | DR38: =(DK38-CZ38)/CZ38 -> #DIV/0! | DS38: =DV38 + ABS(DT38) + ABS(DU38) -> 0 | DZ38: FALSE | EA38: FALSE | EB38: =(DW38-DN38)/DN38 -> #DIV/0! | EC38: =(DV38-DK38)/DK38 -> #DIV/0! | ED38: =EG38 + ABS(EE38) + ABS(EF38) -> 0 | EK38: FALSE | EL38: FALSE | EM38: =(EH38-DW38)/DW38 -> #DIV/0! | EN38: =(EG38-DV38)/DV38 -> #DIV/0! | EO38: =ER38 + ABS(EP38) + ABS(EQ38) -> 0 | EV38: FALSE | EW38: FALSE | EX38: =(ES38-EJ38)/EJ38 -> #DIV/0! | EY38: =(ER38-EG38)/EG38 -> #DIV/0!
C39: PENITENCIÁRIA JOSÉ MARIA ALKIMIM | D39: 1450022 | E39: 35 | F39: F17B0700287 | G39: 00022143432 | H39: COMPANHIA DE SANEAMENTO DE MINAS GERAIS COPASA MG | I39: 17.281.106/0001-03 | N39: 107 | P39: 13428.73 | R39: 266336.45 | S39: 9286 | T39: 1450.01.0005511/2026-51 | X39: =AA39 + ABS(Y39) + ABS(Z39) -> 287631.48 | Y39: -13806.31 | Z39: 0 | AA39: 273825.17 | AB39: 9546 | AC39: 10/03/2026 | AD39: 1450.01.0029372/2026-78 | AE39: TRUE | AF39: TRUE | AG39: =(AB39-S39)/S39 -> 0.027999138 | AH39: =(AA39-R39)/R39 -> 0.028117518 | AI39: =AL39 + ABS(AJ39) + ABS(AK39) -> 543713.54 | AJ39: -26098.25 | AK39: 0 | AL39: 517615.29 | AM39: 17168 | AN39: 46122 | AO39: 1450.01.0046622/2026-25 | AP39: TRUE | AQ39: TRUE | AR39: =(AM39-AB39)/AB39 -> 0.79844961 | AS39: =(AL39-AA39)/AA39 -> 0.89031304 | AT39: =AW39 + ABS(AU39) + ABS(AV39) -> 0 | BA39: FALSE | BB39: FALSE | BC39: =(AX39-AM39)/AM39 -> -1 | BD39: =(AW39-AL39)/AL39 -> -1 | BE39: =BH39 + ABS(BF39) + ABS(BG39) -> 0 | BL39: FALSE | BM39: FALSE | BN39: =(BI39-AZ39)/AZ39 -> #DIV/0! | BO39: =(BH39-AW39)/AW39 -> #DIV/0! | BP39: =BS39 + ABS(BQ39) + ABS(BR39) -> 0 | BW39: FALSE | BX39: FALSE | BY39: =(BT39-BI39)/BI39 -> #DIV/0! | BZ39: =(BS39-BH39)/BH39 -> #DIV/0! | CA39: =CD39 + ABS(CB39) + ABS(CC39) -> 0 | CH39: FALSE | CI39: FALSE | CJ39: =(CE39-BV39)/BV39 -> #DIV/0! | CK39: =(CD39-BS39)/BS39 -> #DIV/0! | CL39: =CO39 + ABS(CM39) + ABS(CN39) -> 0 | CS39: FALSE | CT39: FALSE | CU39: =(CP39-CE39)/CE39 -> #DIV/0! | CV39: =(CO39-CD39)/CD39 -> #DIV/0! | CW39: =CZ39 + ABS(CX39) + ABS(CY39) -> 0 | DD39: FALSE | DE39: FALSE | DF39: =(DA39-CR39)/CR39 -> #DIV/0! | DG39: =(CZ39-CO39)/CO39 -> #DIV/0! | DH39: =DK39 + ABS(DI39) + ABS(DJ39) -> 0 | DO39: FALSE | DP39: FALSE | DQ39: =(DL39-DA39)/DA39 -> #DIV/0! | DR39: =(DK39-CZ39)/CZ39 -> #DIV/0! | DS39: =DV39 + ABS(DT39) + ABS(DU39) -> 0 | DZ39: FALSE | EA39: FALSE | EB39: =(DW39-DN39)/DN39 -> #DIV/0! | EC39: =(DV39-DK39)/DK39 -> #DIV/0! | ED39: =EG39 + ABS(EE39) + ABS(EF39) -> 0 | EK39: FALSE | EL39: FALSE | EM39: =(EH39-DW39)/DW39 -> #DIV/0! | EN39: =(EG39-DV39)/DV39 -> #DIV/0! | EO39: =ER39 + ABS(EP39) + ABS(EQ39) -> 0 | EV39: FALSE | EW39: FALSE | EX39: =(ES39-EJ39)/EJ39 -> #DIV/0! | EY39: =(ER39-EG39)/EG39 -> #DIV/0!
C40: PENITENCIÁRIA JOSÉ MARIA ALKIMIM | D40: 1450022 | E40: 35 | F40: Y22G1203219 | G40: 00106358782 | H40: COMPANHIA DE SANEAMENTO DE MINAS GERAIS COPASA MG | I40: 17.281.106/0001-03 | N40: 107 | P40: 5.2 | R40: 103.15 | S40: 6 | T40: 1450.01.0005511/2026-51 | X40: =AA40 + ABS(Y40) + ABS(Z40) -> 95.82 | Y40: -4.6 | Z40: 0 | AA40: 91.22 | AB40: 5 | AC40: 10/03/2026 | AD40: 1450.01.0029372/2026-78 | AE40: TRUE | AF40: TRUE | AG40: =(AB40-S40)/S40 -> -0.16666667 | AH40: =(AA40-R40)/R40 -> -0.11565681 | AI40: =AL40 + ABS(AJ40) + ABS(AK40) -> 120.67 | AJ40: -5.79 | AK40: 0 | AL40: 114.88 | AM40: 6 | AN40: 46122 | AO40: 1450.01.0046622/2026-25 | AP40: TRUE | AQ40: TRUE | AR40: =(AM40-AB40)/AB40 -> 0.2 | AS40: =(AL40-AA40)/AA40 -> 0.25937294 | AT40: =AW40 + ABS(AU40) + ABS(AV40) -> 0 | BA40: FALSE | BB40: FALSE | BC40: =(AX40-AM40)/AM40 -> -1 | BD40: =(AW40-AL40)/AL40 -> -1 | BE40: =BH40 + ABS(BF40) + ABS(BG40) -> 0 | BL40: FALSE | BM40: FALSE | BN40: =(BI40-AZ40)/AZ40 -> #DIV/0! | BO40: =(BH40-AW40)/AW40 -> #DIV/0! | BP40: =BS40 + ABS(BQ40) + ABS(BR40) -> 0 | BW40: FALSE | BX40: FALSE | BY40: =(BT40-BI40)/BI40 -> #DIV/0! | BZ40: =(BS40-BH40)/BH40 -> #DIV/0! | CA40: =CD40 + ABS(CB40) + ABS(CC40) -> 0 | CH40: FALSE | CI40: FALSE | CJ40: =(CE40-BV40)/BV40 -> #DIV/0! | CK40: =(CD40-BS40)/BS40 -> #DIV/0! | CL40: =CO40 + ABS(CM40) + ABS(CN40) -> 0 | CS40: FALSE | CT40: FALSE | CU40: =(CP40-CE40)/CE40 -> #DIV/0! | CV40: =(CO40-CD40)/CD40 -> #DIV/0! | CW40: =CZ40 + ABS(CX40) + ABS(CY40) -> 0 | DD40: FALSE | DE40: FALSE | DF40: =(DA40-CR40)/CR40 -> #DIV/0! | DG40: =(CZ40-CO40)/CO40 -> #DIV/0! | DH40: =DK40 + ABS(DI40) + ABS(DJ40) -> 0 | DO40: FALSE | DP40: FALSE | DQ40: =(DL40-DA40)/DA40 -> #DIV/0! | DR40: =(DK40-CZ40)/CZ40 -> #DIV/0! | DS40: =DV40 + ABS(DT40) + ABS(DU40) -> 0 | DZ40: FALSE | EA40: FALSE | EB40: =(DW40-DN40)/DN40 -> #DIV/0! | EC40: =(DV40-DK40)/DK40 -> #DIV/0! | ED40: =EG40 + ABS(EE40) + ABS(EF40) -> 0 | EK40: FALSE | EL40: FALSE | EM40: =(EH40-DW40)/DW40 -> #DIV/0! | EN40: =(EG40-DV40)/DV40 -> #DIV/0! | EO40: =ER40 + ABS(EP40) + ABS(EQ40) -> 0 | EV40: FALSE | EW40: FALSE | EX40: =(ES40-EJ40)/EJ40 -> #DIV/0! | EY40: =(ER40-EG40)/EG40 -> #DIV/0!
C41: PENITENCIÁRIA PROF. JASON SOARES ALBERGARIA | D41: 1450022 | E41: 39 | F41: F24G0800119 | G41: 00108465675 | H41: COMPANHIA DE SANEAMENTO DE MINAS GERAIS COPASA MG | I41: 17.281.106/0001-03 | N41: 107 | P41: 4797.91 | R41: 95158.47 | S41: 5788 | T41: 1450.01.0005511/2026-51 | X41: =AA41 + ABS(Y41) + ABS(Z41) -> 152708.53 | Y41: -7330.01 | Z41: 0 | AA41: 145378.52 | AB41: 8822 | AC41: 10/03/2026 | AD41: 1450.01.0029372/2026-78 | AE41: TRUE | AF41: TRUE | AG41: =(AB41-S41)/S41 -> 0.52418798 | AH41: =(AA41-R41)/R41 -> 0.52775176 | AI41: =AL41 + ABS(AJ41) + ABS(AK41) -> 155936.18 | AJ41: -7484.94 | AK41: 0 | AL41: 148451.24 | AM41: 8840 | AN41: 46122 | AO41: 1450.01.0046622/2026-25 | AP41: TRUE | AQ41: TRUE | AR41: =(AM41-AB41)/AB41 -> 0.0020403537 | AS41: =(AL41-AA41)/AA41 -> 0.021135997 | AT41: =AW41 + ABS(AU41) + ABS(AV41) -> 0 | BA41: FALSE | BB41: FALSE | BC41: =(AX41-AM41)/AM41 -> -1 | BD41: =(AW41-AL41)/AL41 -> -1 | BE41: =BH41 + ABS(BF41) + ABS(BG41) -> 0 | BL41: FALSE | BM41: FALSE | BN41: =(BI41-AZ41)/AZ41 -> #DIV/0! | BO41: =(BH41-AW41)/AW41 -> #DIV/0! | BP41: =BS41 + ABS(BQ41) + ABS(BR41) -> 0 | BW41: FALSE | BX41: FALSE | BY41: =(BT41-BI41)/BI41 -> #DIV/0! | BZ41: =(BS41-BH41)/BH41 -> #DIV/0! | CA41: =CD41 + ABS(CB41) + ABS(CC41) -> 0 | CH41: FALSE | CI41: FALSE | CJ41: =(CE41-BV41)/BV41 -> #DIV/0! | CK41: =(CD41-BS41)/BS41 -> #DIV/0! | CL41: =CO41 + ABS(CM41) + ABS(CN41) -> 0 | CS41: FALSE | CT41: FALSE | CU41: =(CP41-CE41)/CE41 -> #DIV/0! | CV41: =(CO41-CD41)/CD41 -> #DIV/0! | CW41: =CZ41 + ABS(CX41) + ABS(CY41) -> 0 | DD41: FALSE | DE41: FALSE | DF41: =(DA41-CR41)/CR41 -> #DIV/0! | DG41: =(CZ41-CO41)/CO41 -> #DIV/0! | DH41: =DK41 + ABS(DI41) + ABS(DJ41) -> 0 | DO41: FALSE | DP41: FALSE | DQ41: =(DL41-DA41)/DA41 -> #DIV/0! | DR41: =(DK41-CZ41)/CZ41 -> #DIV/0! | DS41: =DV41 + ABS(DT41) + ABS(DU41) -> 0 | DZ41: FALSE | EA41: FALSE | EB41: =(DW41-DN41)/DN41 -> #DIV/0! | EC41: =(DV41-DK41)/DK41 -> #DIV/0! | ED41: =EG41 + ABS(EE41) + ABS(EF41) -> 0 | EK41: FALSE | EL41: FALSE | EM41: =(EH41-DW41)/DW41 -> #DIV/0! | EN41: =(EG41-DV41)/DV41 -> #DIV/0! | EO41: =ER41 + ABS(EP41) + ABS(EQ41) -> 0 | EV41: FALSE | EW41: FALSE | EX41: =(ES41-EJ41)/EJ41 -> #DIV/0! | EY41: =(ER41-EG41)/EG41 -> #DIV/0!
C42: PRESÍDIO ALVORADA (MONTES CLAROS) | D42: 1450022 | E42: 97 | F42: E18B0801569 | G42: 00013109235 | H42: COMPANHIA DE SANEAMENTO DE MINAS GERAIS COPASA MG | I42: 17.281.106/0001-03 | N42: 107 | P42: 3543.33 | R42: 70276.06 | S42: 2479 | T42: 1450.01.0005511/2026-51 | X42: =AA42 + ABS(Y42) + ABS(Z42) -> 83358.99 | Y42: -4001.23 | Z42: 0 | AA42: 79357.76 | AB42: 2763 | AC42: 10/03/2026 | AD42: 1450.01.0029372/2026-78 | AE42: TRUE | AF42: TRUE | AG42: =(AB42-S42)/S42 -> 0.11456232 | AH42: =(AA42-R42)/R42 -> 0.12922893 | AI42: =AL42 + ABS(AJ42) + ABS(AK42) -> 73804.97 | AJ42: -3542.64 | AK42: 0 | AL42: 70262.33 | AM42: 2364 | AN42: 46122 | AO42: 1450.01.0046622/2026-25 | AP42: TRUE | AQ42: TRUE | AR42: =(AM42-AB42)/AB42 -> -0.14440825 | AS42: =(AL42-AA42)/AA42 -> -0.11461299 | AT42: =AW42 + ABS(AU42) + ABS(AV42) -> 0 | BA42: FALSE | BB42: FALSE | BC42: =(AX42-AM42)/AM42 -> -1 | BD42: =(AW42-AL42)/AL42 -> -1 | BE42: =BH42 + ABS(BF42) + ABS(BG42) -> 0 | BL42: FALSE | BM42: FALSE | BN42: =(BI42-AZ42)/AZ42 -> #DIV/0! | BO42: =(BH42-AW42)/AW42 -> #DIV/0! | BP42: =BS42 + ABS(BQ42) + ABS(BR42) -> 0 | BW42: FALSE | BX42: FALSE | BY42: =(BT42-BI42)/BI42 -> #DIV/0! | BZ42: =(BS42-BH42)/BH42 -> #DIV/0! | CA42: =CD42 + ABS(CB42) + ABS(CC42) -> 0 | CH42: FALSE | CI42: FALSE | CJ42: =(CE42-BV42)/BV42 -> #DIV/0! | CK42: =(CD42-BS42)/BS42 -> #DIV/0! | CL42: =CO42 + ABS(CM42) + ABS(CN42) -> 0 | CS42: FALSE | CT42: FALSE | CU42: =(CP42-CE42)/CE42 -> #DIV/0! | CV42: =(CO42-CD42)/CD42 -> #DIV/0! | CW42: =CZ42 + ABS(CX42) + ABS(CY42) -> 0 | DD42: FALSE | DE42: FALSE | DF42: =(DA42-CR42)/CR42 -> #DIV/0! | DG42: =(CZ42-CO42)/CO42 -> #DIV/0! | DH42: =DK42 + ABS(DI42) + ABS(DJ42) -> 0 | DO42: FALSE | DP42: FALSE | DQ42: =(DL42-DA42)/DA42 -> #DIV/0! | DR42: =(DK42-CZ42)/CZ42 -> #DIV/0! | DS42: =DV42 + ABS(DT42) + ABS(DU42) -> 0 | DZ42: FALSE | EA42: FALSE | EB42: =(DW42-DN42)/DN42 -> #DIV/0! | EC42: =(DV42-DK42)/DK42 -> #DIV/0! | ED42: =EG42 + ABS(EE42) + ABS(EF42) -> 0 | EK42: FALSE | EL42: FALSE | EM42: =(EH42-DW42)/DW42 -> #DIV/0! | EN42: =(EG42-DV42)/DV42 -> #DIV/0! | EO42: =ER42 + ABS(EP42) + ABS(EQ42) -> 0 | EV42: FALSE | EW42: FALSE | EX42: =(ES42-EJ42)/EJ42 -> #DIV/0! | EY42: =(ER42-EG42)/EG42 -> #DIV/0!
C43: PRESÍDIO ANTÔNIO DUTRA LADEIRA | D43: 1450022 | E43: 26 | F43: K23C8002911 | G43: 00111760429 | H43: COMPANHIA DE SANEAMENTO DE MINAS GERAIS COPASA MG | I43: 17.281.106/0001-03 | N43: 107 | P43: 70494.5 | R43: 1398140.9 | S43: 48581 | T43: 1450.01.0005511/2026-51 | X43: =AA43 + ABS(Y43) + ABS(Z43) -> 862627.76 | Y43: -41406.13 | Z43: 0 | AA43: 821221.63 | AB43: 28551 | AC43: 10/03/2026 | AD43: 1450.01.0029372/2026-78 | AE43: TRUE | AF43: TRUE | AG43: =(AB43-S43)/S43 -> -0.41230111 | AH43: =(AA43-R43)/R43 -> -0.41263314 | AI43: =AL43 + ABS(AJ43) + ABS(AK43) -> 830939.87 | AJ43: -39885.11 | AK43: 0 | AL43: 791054.76 | AM43: 26603 | AN43: 46122 | AO43: 1450.01.0046622/2026-25 | AP43: TRUE | AQ43: TRUE | AR43: =(AM43-AB43)/AB43 -> -0.068228784 | AS43: =(AL43-AA43)/AA43 -> -0.03673414 | AT43: =AW43 + ABS(AU43) + ABS(AV43) -> 0 | BA43: FALSE | BB43: FALSE | BC43: =(AX43-AM43)/AM43 -> -1 | BD43: =(AW43-AL43)/AL43 -> -1 | BE43: =BH43 + ABS(BF43) + ABS(BG43) -> 0 | BL43: FALSE | BM43: FALSE | BN43: =(BI43-AZ43)/AZ43 -> #DIV/0! | BO43: =(BH43-AW43)/AW43 -> #DIV/0! | BP43: =BS43 + ABS(BQ43) + ABS(BR43) -> 0 | BW43: FALSE | BX43: FALSE | BY43: =(BT43-BI43)/BI43 -> #DIV/0! | BZ43: =(BS43-BH43)/BH43 -> #DIV/0! | CA43: =CD43 + ABS(CB43) + ABS(CC43) -> 0 | CH43: FALSE | CI43: FALSE | CJ43: =(CE43-BV43)/BV43 -> #DIV/0! | CK43: =(CD43-BS43)/BS43 -> #DIV/0! | CL43: =CO43 + ABS(CM43) + ABS(CN43) -> 0 | CS43: FALSE | CT43: FALSE | CU43: =(CP43-CE43)/CE43 -> #DIV/0! | CV43: =(CO43-CD43)/CD43 -> #DIV/0! | CW43: =CZ43 + ABS(CX43) + ABS(CY43) -> 0 | DD43: FALSE | DE43: FALSE | DF43: =(DA43-CR43)/CR43 -> #DIV/0! | DG43: =(CZ43-CO43)/CO43 -> #DIV/0! | DH43: =DK43 + ABS(DI43) + ABS(DJ43) -> 0 | DO43: FALSE | DP43: FALSE | DQ43: =(DL43-DA43)/DA43 -> #DIV/0! | DR43: =(DK43-CZ43)/CZ43 -> #DIV/0! | DS43: =DV43 + ABS(DT43) + ABS(DU43) -> 0 | DZ43: FALSE | EA43: FALSE | EB43: =(DW43-DN43)/DN43 -> #DIV/0! | EC43: =(DV43-DK43)/DK43 -> #DIV/0! | ED43: =EG43 + ABS(EE43) + ABS(EF43) -> 0 | EK43: FALSE | EL43: FALSE | EM43: =(EH43-DW43)/DW43 -> #DIV/0! | EN43: =(EG43-DV43)/DV43 -> #DIV/0! | EO43: =ER43 + ABS(EP43) + ABS(EQ43) -> 0 | EV43: FALSE | EW43: FALSE | EX43: =(ES43-EJ43)/EJ43 -> #DIV/0! | EY43: =(ER43-EG43)/EG43 -> #DIV/0!
C44: PRESÍDIO DE ABAETÉ | D44: 1450022 | E44: 157 | F44: Y24S0051535 | G44: 00111979056 | H44: COMPANHIA DE SANEAMENTO DE MINAS GERAIS COPASA MG | I44: 17.281.106/0001-03 | N44: 107 | P44: 416.66 | R44: 8263.72 | S44: 326 | T44: 1450.01.0005511/2026-51 | X44: =AA44 + ABS(Y44) + ABS(Z44) -> 10465.43 | Y44: -502.34 | Z44: 0 | AA44: 9963.09 | AB44: 385 | AC44: 10/03/2026 | AD44: 1450.01.0029372/2026-78 | AE44: TRUE | AF44: TRUE | AG44: =(AB44-S44)/S44 -> 0.1809816 | AH44: =(AA44-R44)/R44 -> 0.20564225 | AI44: =AL44 + ABS(AJ44) + ABS(AK44) -> 8610.23 | AJ44: -413.29 | AK44: 0 | AL44: 8196.94 | AM44: 311 | AN44: 46122 | AO44: 1450.01.0046622/2026-25 | AP44: TRUE | AQ44: TRUE | AR44: =(AM44-AB44)/AB44 -> -0.19220779 | AS44: =(AL44-AA44)/AA44 -> -0.1772693 | AT44: =AW44 + ABS(AU44) + ABS(AV44) -> 0 | BA44: FALSE | BB44: FALSE | BC44: =(AX44-AM44)/AM44 -> -1 | BD44: =(AW44-AL44)/AL44 -> -1 | BE44: =BH44 + ABS(BF44) + ABS(BG44) -> 0 | BL44: FALSE | BM44: FALSE | BN44: =(BI44-AZ44)/AZ44 -> #DIV/0! | BO44: =(BH44-AW44)/AW44 -> #DIV/0! | BP44: =BS44 + ABS(BQ44) + ABS(BR44) -> 0 | BW44: FALSE | BX44: FALSE | BY44: =(BT44-BI44)/BI44 -> #DIV/0! | BZ44: =(BS44-BH44)/BH44 -> #DIV/0! | CA44: =CD44 + ABS(CB44) + ABS(CC44) -> 0 | CH44: FALSE | CI44: FALSE | CJ44: =(CE44-BV44)/BV44 -> #DIV/0! | CK44: =(CD44-BS44)/BS44 -> #DIV/0! | CL44: =CO44 + ABS(CM44) + ABS(CN44) -> 0 | CS44: FALSE | CT44: FALSE | CU44: =(CP44-CE44)/CE44 -> #DIV/0! | CV44: =(CO44-CD44)/CD44 -> #DIV/0! | CW44: =CZ44 + ABS(CX44) + ABS(CY44) -> 0 | DD44: FALSE | DE44: FALSE | DF44: =(DA44-CR44)/CR44 -> #DIV/0! | DG44: =(CZ44-CO44)/CO44 -> #DIV/0! | DH44: =DK44 + ABS(DI44) + ABS(DJ44) -> 0 | DO44: FALSE | DP44: FALSE | DQ44: =(DL44-DA44)/DA44 -> #DIV/0! | DR44: =(DK44-CZ44)/CZ44 -> #DIV/0! | DS44: =DV44 + ABS(DT44) + ABS(DU44) -> 0 | DZ44: FALSE | EA44: FALSE | EB44: =(DW44-DN44)/DN44 -> #DIV/0! | EC44: =(DV44-DK44)/DK44 -> #DIV/0! | ED44: =EG44 + ABS(EE44) + ABS(EF44) -> 0 | EK44: FALSE | EL44: FALSE | EM44: =(EH44-DW44)/DW44 -> #DIV/0! | EN44: =(EG44-DV44)/DV44 -> #DIV/0! | EO44: =ER44 + ABS(EP44) + ABS(EQ44) -> 0 | EV44: FALSE | EW44: FALSE | EX44: =(ES44-EJ44)/EJ44 -> #DIV/0! | EY44: =(ER44-EG44)/EG44 -> #DIV/0!
C45: PRESÍDIO DE ABAETÉ | D45: 1450022 | E45: 157 | F45: A19N0094674 | G45: 00006940773 | H45: COMPANHIA DE SANEAMENTO DE MINAS GERAIS COPASA MG | I45: 17.281.106/0001-03 | N45: 107 | P45: 540.1 | R45: 10711.96 | S45: 411 | T45: 1450.01.0005511/2026-51 | X45: =AA45 + ABS(Y45) + ABS(Z45) -> 10949.51 | Y45: -525.58 | Z45: 0 | AA45: 10423.93 | AB45: 401 | AC45: 10/03/2026 | AD45: 1450.01.0029372/2026-78 | AE45: TRUE | AF45: TRUE | AG45: =(AB45-S45)/S45 -> -0.0243309 | AH45: =(AA45-R45)/R45 -> -0.026888637 | AI45: =AL45 + ABS(AJ45) + ABS(AK45) -> 11457.8 | AJ45: -549.97 | AK45: 0 | AL45: 10907.83 | AM45: 401 | AN45: 46122 | AO45: 1450.01.0046622/2026-25 | AP45: TRUE | AQ45: TRUE | AR45: =(AM45-AB45)/AB45 -> 0 | AS45: =(AL45-AA45)/AA45 -> 0.046422031 | AT45: =AW45 + ABS(AU45) + ABS(AV45) -> 0 | BA45: FALSE | BB45: FALSE | BC45: =(AX45-AM45)/AM45 -> -1 | BD45: =(AW45-AL45)/AL45 -> -1 | BE45: =BH45 + ABS(BF45) + ABS(BG45) -> 0 | BL45: FALSE | BM45: FALSE | BN45: =(BI45-AZ45)/AZ45 -> #DIV/0! | BO45: =(BH45-AW45)/AW45 -> #DIV/0! | BP45: =BS45 + ABS(BQ45) + ABS(BR45) -> 0 | BW45: FALSE | BX45: FALSE | BY45: =(BT45-BI45)/BI45 -> #DIV/0! | BZ45: =(BS45-BH45)/BH45 -> #DIV/0! | CA45: =CD45 + ABS(CB45) + ABS(CC45) -> 0 | CH45: FALSE | CI45: FALSE | CJ45: =(CE45-BV45)/BV45 -> #DIV/0! | CK45: =(CD45-BS45)/BS45 -> #DIV/0! | CL45: =CO45 + ABS(CM45) + ABS(CN45) -> 0 | CS45: FALSE | CT45: FALSE | CU45: =(CP45-CE45)/CE45 -> #DIV/0! | CV45: =(CO45-CD45)/CD45 -> #DIV/0! | CW45: =CZ45 + ABS(CX45) + ABS(CY45) -> 0 | DD45: FALSE | DE45: FALSE | DF45: =(DA45-CR45)/CR45 -> #DIV/0! | DG45: =(CZ45-CO45)/CO45 -> #DIV/0! | DH45: =DK45 + ABS(DI45) + ABS(DJ45) -> 0 | DO45: FALSE | DP45: FALSE | DQ45: =(DL45-DA45)/DA45 -> #DIV/0! | DR45: =(DK45-CZ45)/CZ45 -> #DIV/0! | DS45: =DV45 + ABS(DT45) + ABS(DU45) -> 0 | DZ45: FALSE | EA45: FALSE | EB45: =(DW45-DN45)/DN45 -> #DIV/0! | EC45: =(DV45-DK45)/DK45 -> #DIV/0! | ED45: =EG45 + ABS(EE45) + ABS(EF45) -> 0 | EK45: FALSE | EL45: FALSE | EM45: =(EH45-DW45)/DW45 -> #DIV/0! | EN45: =(EG45-DV45)/DV45 -> #DIV/0! | EO45: =ER45 + ABS(EP45) + ABS(EQ45) -> 0 | EV45: FALSE | EW45: FALSE | EX45: =(ES45-EJ45)/EJ45 -> #DIV/0! | EY45: =(ER45-EG45)/EG45 -> #DIV/0!
C46: PRESÍDIO DE ABAETÉ | D46: 1450022 | E46: 157 | F46: B13L0009944 | G46: 00155533452 | H46: COMPANHIA DE SANEAMENTO DE MINAS GERAIS COPASA MG | I46: 17.281.106/0001-03 | N46: 107 | P46: 797.15 | R46: 15810.04 | S46: 588 | T46: 1450.01.0005511/2026-51 | X46: =AA46 + ABS(Y46) + ABS(Z46) -> 16728.21 | Y46: -802.95 | Z46: 0 | AA46: 15925.26 | AB46: 592 | AC46: 10/03/2026 | AD46: 1450.01.0029372/2026-78 | AE46: TRUE | AF46: TRUE | AG46: =(AB46-S46)/S46 -> 0.0068027211 | AH46: =(AA46-R46)/R46 -> 0.0072877741 | AI46: =AL46 + ABS(AJ46) + ABS(AK46) -> 17690.79 | AJ46: -849.16 | AK46: 0 | AL46: 16841.63 | AM46: 598 | AN46: 46122 | AO46: 1450.01.0046622/2026-25 | AP46: TRUE | AQ46: TRUE | AR46: =(AM46-AB46)/AB46 -> 0.010135135 | AS46: =(AL46-AA46)/AA46 -> 0.057541918 | AT46: =AW46 + ABS(AU46) + ABS(AV46) -> 0 | BA46: FALSE | BB46: FALSE | BC46: =(AX46-AM46)/AM46 -> -1 | BD46: =(AW46-AL46)/AL46 -> -1 | BE46: =BH46 + ABS(BF46) + ABS(BG46) -> 0 | BL46: FALSE | BM46: FALSE | BN46: =(BI46-AZ46)/AZ46 -> #DIV/0! | BO46: =(BH46-AW46)/AW46 -> #DIV/0! | BP46: =BS46 + ABS(BQ46) + ABS(BR46) -> 0 | BW46: FALSE | BX46: FALSE | BY46: =(BT46-BI46)/BI46 -> #DIV/0! | BZ46: =(BS46-BH46)/BH46 -> #DIV/0! | CA46: =CD46 + ABS(CB46) + ABS(CC46) -> 0 | CH46: FALSE | CI46: FALSE | CJ46: =(CE46-BV46)/BV46 -> #DIV/0! | CK46: =(CD46-BS46)/BS46 -> #DIV/0! | CL46: =CO46 + ABS(CM46) + ABS(CN46) -> 0 | CS46: FALSE | CT46: FALSE | CU46: =(CP46-CE46)/CE46 -> #DIV/0! | CV46: =(CO46-CD46)/CD46 -> #DIV/0! | CW46: =CZ46 + ABS(CX46) + ABS(CY46) -> 0 | DD46: FALSE | DE46: FALSE | DF46: =(DA46-CR46)/CR46 -> #DIV/0! | DG46: =(CZ46-CO46)/CO46 -> #DIV/0! | DH46: =DK46 + ABS(DI46) + ABS(DJ46) -> 0 | DO46: FALSE | DP46: FALSE | DQ46: =(DL46-DA46)/DA46 -> #DIV/0! | DR46: =(DK46-CZ46)/CZ46 -> #DIV/0! | DS46: =DV46 + ABS(DT46) + ABS(DU46) -> 0 | DZ46: FALSE | EA46: FALSE | EB46: =(DW46-DN46)/DN46 -> #DIV/0! | EC46: =(DV46-DK46)/DK46 -> #DIV/0! | ED46: =EG46 + ABS(EE46) + ABS(EF46) -> 0 | EK46: FALSE | EL46: FALSE | EM46: =(EH46-DW46)/DW46 -> #DIV/0! | EN46: =(EG46-DV46)/DV46 -> #DIV/0! | EO46: =ER46 + ABS(EP46) + ABS(EQ46) -> 0 | EV46: FALSE | EW46: FALSE | EX46: =(ES46-EJ46)/EJ46 -> #DIV/0! | EY46: =(ER46-EG46)/EG46 -> #DIV/0!
C47: PRESÍDIO DE AÇUCENA | D47: 1450022 | E47: 315 | F47: B18F0008947 | G47: 00118649205 | H47: COMPANHIA DE SANEAMENTO DE MINAS GERAIS COPASA MG | I47: 17.281.106/0001-03 | N47: 107 | P47: 1362.79 | R47: 27028.69 | S47: 1672 | T47: 1450.01.0005511/2026-51 | X47: =AA47 + ABS(Y47) + ABS(Z47) -> 29243.45 | Y47: -1403.69 | Z47: 0 | AA47: 27839.76 | AB47: 1721 | AC47: 10/03/2026 | AD47: 1450.01.0029372/2026-78 | AE47: TRUE | AF47: TRUE | AG47: =(AB47-S47)/S47 -> 0.02930622 | AH47: =(AA47-R47)/R47 -> 0.030007744 | AI47: =AL47 + ABS(AJ47) + ABS(AK47) -> 26399.39 | AJ47: -1267.17 | AK47: 0 | AL47: 25132.22 | AM47: 1486 | AN47: 46122 | AO47: 1450.01.0046622/2026-25 | AP47: TRUE | AQ47: TRUE | AR47: =(AM47-AB47)/AB47 -> -0.13654852 | AS47: =(AL47-AA47)/AA47 -> -0.09725443 | AT47: =AW47 + ABS(AU47) + ABS(AV47) -> 0 | BA47: FALSE | BB47: FALSE | BC47: =(AX47-AM47)/AM47 -> -1 | BD47: =(AW47-AL47)/AL47 -> -1 | BE47: =BH47 + ABS(BF47) + ABS(BG47) -> 0 | BL47: FALSE | BM47: FALSE | BN47: =(BI47-AZ47)/AZ47 -> #DIV/0! | BO47: =(BH47-AW47)/AW47 -> #DIV/0! | BP47: =BS47 + ABS(BQ47) + ABS(BR47) -> 0 | BW47: FALSE | BX47: FALSE | BY47: =(BT47-BI47)/BI47 -> #DIV/0! | BZ47: =(BS47-BH47)/BH47 -> #DIV/0! | CA47: =CD47 + ABS(CB47) + ABS(CC47) -> 0 | CH47: FALSE | CI47: FALSE | CJ47: =(CE47-BV47)/BV47 -> #DIV/0! | CK47: =(CD47-BS47)/BS47 -> #DIV/0! | CL47: =CO47 + ABS(CM47) + ABS(CN47) -> 0 | CS47: FALSE | CT47: FALSE | CU47: =(CP47-CE47)/CE47 -> #DIV/0! | CV47: =(CO47-CD47)/CD47 -> #DIV/0! | CW47: =CZ47 + ABS(CX47) + ABS(CY47) -> 0 | DD47: FALSE | DE47: FALSE | DF47: =(DA47-CR47)/CR47 -> #DIV/0! | DG47: =(CZ47-CO47)/CO47 -> #DIV/0! | DH47: =DK47 + ABS(DI47) + ABS(DJ47) -> 0 | DO47: FALSE | DP47: FALSE | DQ47: =(DL47-DA47)/DA47 -> #DIV/0! | DR47: =(DK47-CZ47)/CZ47 -> #DIV/0! | DS47: =DV47 + ABS(DT47) + ABS(DU47) -> 0 | DZ47: FALSE | EA47: FALSE | EB47: =(DW47-DN47)/DN47 -> #DIV/0! | EC47: =(DV47-DK47)/DK47 -> #DIV/0! | ED47: =EG47 + ABS(EE47) + ABS(EF47) -> 0 | EK47: FALSE | EL47: FALSE | EM47: =(EH47-DW47)/DW47 -> #DIV/0! | EN47: =(EG47-DV47)/DV47 -> #DIV/0! | EO47: =ER47 + ABS(EP47) + ABS(EQ47) -> 0 | EV47: FALSE | EW47: FALSE | EX47: =(ES47-EJ47)/EJ47 -> #DIV/0! | EY47: =(ER47-EG47)/EG47 -> #DIV/0!
C48: PRESÍDIO DE ÁGUAS FORMOSAS | D48: 1450022 | E48: 236 | F48: B23G0004605 | G48: 00008245703 | H48: COMPANHIA DE SANEAMENTO DE MINAS GERAIS COPASA MG | I48: 17.281.106/0001-03 | N48: 107 | P48: 206.07 | R48: 4087.03 | S48: 286 | T48: 1450.01.0005511/2026-51 | X48: =AA48 + ABS(Y48) + ABS(Z48) -> 4971.2 | Y48: -238.62 | Z48: 0 | AA48: 4732.58 | AB48: 325 | AC48: 10/03/2026 | AD48: 1450.01.0029372/2026-78 | AE48: TRUE | AF48: TRUE | AG48: =(AB48-S48)/S48 -> 0.13636364 | AH48: =(AA48-R48)/R48 -> 0.15795088 | AI48: =AL48 + ABS(AJ48) + ABS(AK48) -> 4090.77 | AJ48: -196.36 | AK48: 0 | AL48: 3894.41 | AM48: 268 | AN48: 46122 | AO48: 1450.01.0046622/2026-25 | AP48: TRUE | AQ48: TRUE | AR48: =(AM48-AB48)/AB48 -> -0.17538462 | AS48: =(AL48-AA48)/AA48 -> -0.17710636 | AT48: =AW48 + ABS(AU48) + ABS(AV48) -> 0 | BA48: FALSE | BB48: FALSE | BC48: =(AX48-AM48)/AM48 -> -1 | BD48: =(AW48-AL48)/AL48 -> -1 | BE48: =BH48 + ABS(BF48) + ABS(BG48) -> 0 | BL48: FALSE | BM48: FALSE | BN48: =(BI48-AZ48)/AZ48 -> #DIV/0! | BO48: =(BH48-AW48)/AW48 -> #DIV/0! | BP48: =BS48 + ABS(BQ48) + ABS(BR48) -> 0 | BW48: FALSE | BX48: FALSE | BY48: =(BT48-BI48)/BI48 -> #DIV/0! | BZ48: =(BS48-BH48)/BH48 -> #DIV/0! | CA48: =CD48 + ABS(CB48) + ABS(CC48) -> 0 | CH48: FALSE | CI48: FALSE | CJ48: =(CE48-BV48)/BV48 -> #DIV/0! | CK48: =(CD48-BS48)/BS48 -> #DIV/0! | CL48: =CO48 + ABS(CM48) + ABS(CN48) -> 0 | CS48: FALSE | CT48: FALSE | CU48: =(CP48-CE48)/CE48 -> #DIV/0! | CV48: =(CO48-CD48)/CD48 -> #DIV/0! | CW48: =CZ48 + ABS(CX48) + ABS(CY48) -> 0 | DD48: FALSE | DE48: FALSE | DF48: =(DA48-CR48)/CR48 -> #DIV/0! | DG48: =(CZ48-CO48)/CO48 -> #DIV/0! | DH48: =DK48 + ABS(DI48) + ABS(DJ48) -> 0 | DO48: FALSE | DP48: FALSE | DQ48: =(DL48-DA48)/DA48 -> #DIV/0! | DR48: =(DK48-CZ48)/CZ48 -> #DIV/0! | DS48: =DV48 + ABS(DT48) + ABS(DU48) -> 0 | DZ48: FALSE | EA48: FALSE | EB48: =(DW48-DN48)/DN48 -> #DIV/0! | EC48: =(DV48-DK48)/DK48 -> #DIV/0! | ED48: =EG48 + ABS(EE48) + ABS(EF48) -> 0 | EK48: FALSE | EL48: FALSE | EM48: =(EH48-DW48)/DW48 -> #DIV/0! | EN48: =(EG48-DV48)/DV48 -> #DIV/0! | EO48: =ER48 + ABS(EP48) + ABS(EQ48) -> 0 | EV48: FALSE | EW48: FALSE | EX48: =(ES48-EJ48)/EJ48 -> #DIV/0! | EY48: =(ER48-EG48)/EG48 -> #DIV/0!
C49: PRESÍDIO DE ALEM PARAIBA | D49: 1450022 | E49: 346 | F49: B22G0013224 | G49: 00010364137 | H49: COMPANHIA DE SANEAMENTO DE MINAS GERAIS COPASA MG | I49: 17.281.106/0001-03 | N49: 107 | P49: 1121.6 | R49: 22245.04 | S49: 1383 | T49: 1450.01.0005511/2026-51 | X49: =AA49 + ABS(Y49) + ABS(Z49) -> 26687.56 | Y49: -1281 | Z49: 0 | AA49: 25406.56 | AB49: 1574 | AC49: 10/03/2026 | AD49: 1450.01.0029372/2026-78 | AE49: TRUE | AF49: TRUE | AG49: =(AB49-S49)/S49 -> 0.13810557 | AH49: =(AA49-R49)/R49 -> 0.14212247 | AI49: =AL49 + ABS(AJ49) + ABS(AK49) -> 24462.5 | AJ49: -1174.2 | AK49: 0 | AL49: 23288.3 | AM49: 1393 | AN49: 46122 | AO49: 1450.01.0046622/2026-25 | AP49: TRUE | AQ49: TRUE | AR49: =(AM49-AB49)/AB49 -> -0.11499365 | AS49: =(AL49-AA49)/AA49 -> -0.08337453 | AT49: =AW49 + ABS(AU49) + ABS(AV49) -> 0 | BA49: FALSE | BB49: FALSE | BC49: =(AX49-AM49)/AM49 -> -1 | BD49: =(AW49-AL49)/AL49 -> -1 | BE49: =BH49 + ABS(BF49) + ABS(BG49) -> 0 | BL49: FALSE | BM49: FALSE | BN49: =(BI49-AZ49)/AZ49 -> #DIV/0! | BO49: =(BH49-AW49)/AW49 -> #DIV/0! | BP49: =BS49 + ABS(BQ49) + ABS(BR49) -> 0 | BW49: FALSE | BX49: FALSE | BY49: =(BT49-BI49)/BI49 -> #DIV/0! | BZ49: =(BS49-BH49)/BH49 -> #DIV/0! | CA49: =CD49 + ABS(CB49) + ABS(CC49) -> 0 | CH49: FALSE | CI49: FALSE | CJ49: =(CE49-BV49)/BV49 -> #DIV/0! | CK49: =(CD49-BS49)/BS49 -> #DIV/0! | CL49: =CO49 + ABS(CM49) + ABS(CN49) -> 0 | CS49: FALSE | CT49: FALSE | CU49: =(CP49-CE49)/CE49 -> #DIV/0! | CV49: =(CO49-CD49)/CD49 -> #DIV/0! | CW49: =CZ49 + ABS(CX49) + ABS(CY49) -> 0 | DD49: FALSE | DE49: FALSE | DF49: =(DA49-CR49)/CR49 -> #DIV/0! | DG49: =(CZ49-CO49)/CO49 -> #DIV/0! | DH49: =DK49 + ABS(DI49) + ABS(DJ49) -> 0 | DO49: FALSE | DP49: FALSE | DQ49: =(DL49-DA49)/DA49 -> #DIV/0! | DR49: =(DK49-CZ49)/CZ49 -> #DIV/0! | DS49: =DV49 + ABS(DT49) + ABS(DU49) -> 0 | DZ49: FALSE | EA49: FALSE | EB49: =(DW49-DN49)/DN49 -> #DIV/0! | EC49: =(DV49-DK49)/DK49 -> #DIV/0! | ED49: =EG49 + ABS(EE49) + ABS(EF49) -> 0 | EK49: FALSE | EL49: FALSE | EM49: =(EH49-DW49)/DW49 -> #DIV/0! | EN49: =(EG49-DV49)/DV49 -> #DIV/0! | EO49: =ER49 + ABS(EP49) + ABS(EQ49) -> 0 | EV49: FALSE | EW49: FALSE | EX49: =(ES49-EJ49)/EJ49 -> #DIV/0! | EY49: =(ER49-EG49)/EG49 -> #DIV/0!
... C56: PRESÍDIO DE ANDRELANDIA | D56: 1450022 | E56: 361 | F56: B18F0007902 | G56: 00025065459 | H56: COMPANHIA DE SANEAMENTO DE MINAS GERAIS COPASA MG | I56: 17.281.106/0001-03 | N56: 107 | P56: 6.7 | R56: 132.8 | S56: 15 | T56: 1450.01.0005511/2026-51 | X56: =AA56 + ABS(Y56) + ABS(Z56) -> 2132.41 | Y56: -102.36 | Z56: 0 | AA56: 2030.05 | AB56: 155 | AC56: 10/03/2026 | AD56: 1450.01.0029372/2026-78 | AE56: TRUE | AF56: TRUE | AG56: =(AB56-S56)/S56 -> 9.3333333 | AH56: =(AA56-R56)/R56 -> 14.286521 | AI56: =AL56 + ABS(AJ56) + ABS(AK56) -> 453.73 | AJ56: -21.78 | AK56: 0 | AL56: 431.95 | AM56: 40 | AN56: 46122 | AO56: 1450.01.0046622/2026-25 | AP56: TRUE | AQ56: TRUE | AR56: =(AM56-AB56)/AB56 -> -0.74193548 | AS56: =(AL56-AA56)/AA56 -> -0.78722199 | AT56: =AW56 + ABS(AU56) + ABS(AV56) -> 0 | BA56: FALSE | BB56: FALSE | BC56: =(AX56-AM56)/AM56 -> -1 | BD56: =(AW56-AL56)/AL56 -> -1 | BE56: =BH56 + ABS(BF56) + ABS(BG56) -> 0 | BL56: FALSE | BM56: FALSE | BN56: =(BI56-AZ56)/AZ56 -> #DIV/0! | BO56: =(BH56-AW56)/AW56 -> #DIV/0! | BP56: =BS56 + ABS(BQ56) + ABS(BR56) -> 0 | BW56: FALSE | BX56: FALSE | BY56: =(BT56-BI56)/BI56 -> #DIV/0! | BZ56: =(BS56-BH56)/BH56 -> #DIV/0! | CA56: =CD56 + ABS(CB56) + ABS(CC56) -> 0 | CH56: FALSE | CI56: FALSE | CJ56: =(CE56-BV56)/BV56 -> #DIV/0! | CK56: =(CD56-BS56)/BS56 -> #DIV/0! | CL56: =CO56 + ABS(CM56) + ABS(CN56) -> 0 | CS56: FALSE | CT56: FALSE | CU56: =(CP56-CE56)/CE56 -> #DIV/0! | CV56: =(CO56-CD56)/CD56 -> #DIV/0! | CW56: =CZ56 + ABS(CX56) + ABS(CY56) -> 0 | DD56: FALSE | DE56: FALSE | DF56: =(DA56-CR56)/CR56 -> #DIV/0! | DG56: =(CZ56-CO56)/CO56 -> #DIV/0! | DH56: =DK56 + ABS(DI56) + ABS(DJ56) -> 0 | DO56: FALSE | DP56: FALSE | DQ56: =(DL56-DA56)/DA56 -> #DIV/0! | DR56: =(DK56-CZ56)/CZ56 -> #DIV/0! | DS56: =DV56 + ABS(DT56) + ABS(DU56) -> 0 | DZ56: FALSE | EA56: FALSE | EB56: =(DW56-DN56)/DN56 -> #DIV/0! | EC56: =(DV56-DK56)/DK56 -> #DIV/0! | ED56: =EG56 + ABS(EE56) + ABS(EF56) -> 0 | EK56: FALSE | EL56: FALSE | EM56: =(EH56-DW56)/DW56 -> #DIV/0! | EN56: =(EG56-DV56)/DV56 -> #DIV/0! | EO56: =ER56 + ABS(EP56) + ABS(EQ56) -> 0 | EV56: FALSE | EW56: FALSE | EX56: =(ES56-EJ56)/EJ56 -> #DIV/0! | EY56: =(ER56-EG56)/EG56 -> #DIV/0!
C57: PRESÍDIO DE ARAÇUAÍ | D57: 1450022 | E57: 54 | F57: Y22G1053067 | G57: 00007342659 | H57: COMPANHIA DE SANEAMENTO DE MINAS GERAIS COPASA MG | I57: 17.281.106/0001-03 | N57: 107 | P57: 2.6 | R57: 51.52 | T57: 1450.01.0005511/2026-51 | X57: =AA57 + ABS(Y57) + ABS(Z57) -> 55.86 | Y57: -2.68 | Z57: 0 | AA57: 53.18 | AB57: 0 | AC57: 10/03/2026 | AD57: 1450.01.0029372/2026-78 | AE57: TRUE | AF57: TRUE | AG57: 0 | AH57: =(AA57-R57)/R57 -> 0.032220497 | AI57: =AL57 + ABS(AJ57) + ABS(AK57) -> 63.39 | AJ57: -3.04 | AK57: 0 | AL57: 60.35 | AM57: 0 | AN57: 46122 | AO57: 1450.01.0046622/2026-25 | AP57: TRUE | AQ57: TRUE | AR57: 0 | AS57: =(AL57-AA57)/AA57 -> 0.13482512 | AT57: =AW57 + ABS(AU57) + ABS(AV57) -> 0 | BA57: FALSE | BB57: FALSE | BC57: =(AX57-AM57)/AM57 -> #DIV/0! | BD57: =(AW57-AL57)/AL57 -> -1 | BE57: =BH57 + ABS(BF57) + ABS(BG57) -> 0 | BL57: FALSE | BM57: FALSE | BN57: =(BI57-AZ57)/AZ57 -> #DIV/0! | BO57: =(BH57-AW57)/AW57 -> #DIV/0! | BP57: =BS57 + ABS(BQ57) + ABS(BR57) -> 0 | BW57: FALSE | BX57: FALSE | BY57: =(BT57-BI57)/BI57 -> #DIV/0! | BZ57: =(BS57-BH57)/BH57 -> #DIV/0! | CA57: =CD57 + ABS(CB57) + ABS(CC57) -> 0 | CH57: FALSE | CI57: FALSE | CJ57: =(CE57-BV57)/BV57 -> #DIV/0! | CK57: =(CD57-BS57)/BS57 -> #DIV/0! | CL57: =CO57 + ABS(CM57) + ABS(CN57) -> 0 | CS57: FALSE | CT57: FALSE | CU57: =(CP57-CE57)/CE57 -> #DIV/0! | CV57: =(CO57-CD57)/CD57 -> #DIV/0! | CW57: =CZ57 + ABS(CX57) + ABS(CY57) -> 0 | DD57: FALSE | DE57: FALSE | DF57: =(DA57-CR57)/CR57 -> #DIV/0! | DG57: =(CZ57-CO57)/CO57 -> #DIV/0! | DH57: =DK57 + ABS(DI57) + ABS(DJ57) -> 0 | DO57: FALSE | DP57: FALSE | DQ57: =(DL57-DA57)/DA57 -> #DIV/0! | DR57: =(DK57-CZ57)/CZ57 -> #DIV/0! | DS57: =DV57 + ABS(DT57) + ABS(DU57) -> 0 | DZ57: FALSE | EA57: FALSE | EB57: =(DW57-DN57)/DN57 -> #DIV/0! | EC57: =(DV57-DK57)/DK57 -> #DIV/0! | ED57: =EG57 + ABS(EE57) + ABS(EF57) -> 0 | EK57: FALSE | EL57: FALSE | EM57: =(EH57-DW57)/DW57 -> #DIV/0! | EN57: =(EG57-DV57)/DV57 -> #DIV/0! | EO57: =ER57 + ABS(EP57) + ABS(EQ57) -> 0 | EV57: FALSE | EW57: FALSE | EX57: =(ES57-EJ57)/EJ57 -> #DIV/0! | EY57: =(ER57-EG57)/EG57 -> #DIV/0!
C58: PRESÍDIO DE ARAÇUAÍ | D58: 1450022 | E58: 54 | F58: E18B0809922 | G58: 00027653439 | H58: COMPANHIA DE SANEAMENTO DE MINAS GERAIS COPASA MG | I58: 17.281.106/0001-03 | N58: 107 | P58: 2086.73 | R58: 41386.9 | S58: 1476 | T58: 1450.01.0005511/2026-51 | X58: =AA58 + ABS(Y58) + ABS(Z58) -> 45433.23 | Y58: -2180.8 | Z58: 0 | AA58: 43252.43 | AB58: 1536 | AC58: 10/03/2026 | AD58: 1450.01.0029372/2026-78 | AE58: TRUE | AF58: TRUE | AG58: =(AB58-S58)/S58 -> 0.040650407 | AH58: =(AA58-R58)/R58 -> 0.045075374 | AI58: =AL58 + ABS(AJ58) + ABS(AK58) -> 46030.72 | AJ58: -2209.47 | AK58: 0 | AL58: 43821.25 | AM58: 1489 | AN58: 46122 | AO58: 1450.01.0046622/2026-25 | AP58: TRUE | AQ58: TRUE | AR58: =(AM58-AB58)/AB58 -> -0.030598958 | AS58: =(AL58-AA58)/AA58 -> 0.013151169 | AT58: =AW58 + ABS(AU58) + ABS(AV58) -> 0 | BA58: FALSE | BB58: FALSE | BC58: =(AX58-AM58)/AM58 -> -1 | BD58: =(AW58-AL58)/AL58 -> -1 | BE58: =BH58 + ABS(BF58) + ABS(BG58) -> 0 | BL58: FALSE | BM58: FALSE | BN58: =(BI58-AZ58)/AZ58 -> #DIV/0! | BO58: =(BH58-AW58)/AW58 -> #DIV/0! | BP58: =BS58 + ABS(BQ58) + ABS(BR58) -> 0 | BW58: FALSE | BX58: FALSE | BY58: =(BT58-BI58)/BI58 -> #DIV/0! | BZ58: =(BS58-BH58)/BH58 -> #DIV/0! | CA58: =CD58 + ABS(CB58) + ABS(CC58) -> 0 | CH58: FALSE | CI58: FALSE | CJ58: =(CE58-BV58)/BV58 -> #DIV/0! | CK58: =(CD58-BS58)/BS58 -> #DIV/0! | CL58: =CO58 + ABS(CM58) + ABS(CN58) -> 0 | CS58: FALSE | CT58: FALSE | CU58: =(CP58-CE58)/CE58 -> #DIV/0! | CV58: =(CO58-CD58)/CD58 -> #DIV/0! | CW58: =CZ58 + ABS(CX58) + ABS(CY58) -> 0 | DD58: FALSE | DE58: FALSE | DF58: =(DA58-CR58)/CR58 -> #DIV/0! | DG58: =(CZ58-CO58)/CO58 -> #DIV/0! | DH58: =DK58 + ABS(DI58) + ABS(DJ58) -> 0 | DO58: FALSE | DP58: FALSE | DQ58: =(DL58-DA58)/DA58 -> #DIV/0! | DR58: =(DK58-CZ58)/CZ58 -> #DIV/0! | DS58: =DV58 + ABS(DT58) + ABS(DU58) -> 0 | DZ58: FALSE | EA58: FALSE | EB58: =(DW58-DN58)/DN58 -> #DIV/0! | EC58: =(DV58-DK58)/DK58 -> #DIV/0! | ED58: =EG58 + ABS(EE58) + ABS(EF58) -> 0 | EK58: FALSE | EL58: FALSE | EM58: =(EH58-DW58)/DW58 -> #DIV/0! | EN58: =(EG58-DV58)/DV58 -> #DIV/0! | EO58: =ER58 + ABS(EP58) + ABS(EQ58) -> 0 | EV58: FALSE | EW58: FALSE | EX58: =(ES58-EJ58)/EJ58 -> #DIV/0! | EY58: =(ER58-EG58)/EG58 -> #DIV/0!
C59: PRESÍDIO DE ARAXÁ | D59: 1450022 | E59: 84 | F59: B18F0008530 | G59: 00114422567 | H59: COMPANHIA DE SANEAMENTO DE MINAS GERAIS COPASA MG | I59: 17.281.106/0001-03 | N59: 107 | P59: 975.77 | R59: 19352.79 | S59: 711 | T59: 1450.01.0005511/2026-51 | X59: =AA59 + ABS(Y59) + ABS(Z59) -> 24778.94 | Y59: -1189.39 | Z59: 0 | AA59: 23589.55 | AB59: 852 | AC59: 10/03/2026 | AD59: 1450.01.0029372/2026-78 | AE59: TRUE | AF59: TRUE | AG59: =(AB59-S59)/S59 -> 0.19831224 | AH59: =(AA59-R59)/R59 -> 0.21892244 | AI59: =AL59 + ABS(AJ59) + ABS(AK59) -> 21049.76 | AJ59: -1010.39 | AK59: 0 | AL59: 20039.37 | AM59: 702 | AN59: 46122 | AO59: 1450.01.0046622/2026-25 | AP59: TRUE | AQ59: TRUE | AR59: =(AM59-AB59)/AB59 -> -0.17605634 | AS59: =(AL59-AA59)/AA59 -> -0.150498 | AT59: =AW59 + ABS(AU59) + ABS(AV59) -> 0 | BA59: FALSE | BB59: FALSE | BC59: =(AX59-AM59)/AM59 -> -1 | BD59: =(AW59-AL59)/AL59 -> -1 | BE59: =BH59 + ABS(BF59) + ABS(BG59) -> 0 | BL59: FALSE | BM59: FALSE | BN59: =(BI59-AZ59)/AZ59 -> #DIV/0! | BO59: =(BH59-AW59)/AW59 -> #DIV/0! | BP59: =BS59 + ABS(BQ59) + ABS(BR59) -> 0 | BW59: FALSE | BX59: FALSE | BY59: =(BT59-BI59)/BI59 -> #DIV/0! | BZ59: =(BS59-BH59)/BH59 -> #DIV/0! | CA59: =CD59 + ABS(CB59) + ABS(CC59) -> 0 | CH59: FALSE | CI59: FALSE | CJ59: =(CE59-BV59)/BV59 -> #DIV/0! | CK59: =(CD59-BS59)/BS59 -> #DIV/0! | CL59: =CO59 + ABS(CM59) + ABS(CN59) -> 0 | CS59: FALSE | CT59: FALSE | CU59: =(CP59-CE59)/CE59 -> #DIV/0! | CV59: =(CO59-CD59)/CD59 -> #DIV/0! | CW59: =CZ59 + ABS(CX59) + ABS(CY59) -> 0 | DD59: FALSE | DE59: FALSE | DF59: =(DA59-CR59)/CR59 -> #DIV/0! | DG59: =(CZ59-CO59)/CO59 -> #DIV/0! | DH59: =DK59 + ABS(DI59) + ABS(DJ59) -> 0 | DO59: FALSE | DP59: FALSE | DQ59: =(DL59-DA59)/DA59 -> #DIV/0! | DR59: =(DK59-CZ59)/CZ59 -> #DIV/0! | DS59: =DV59 + ABS(DT59) + ABS(DU59) -> 0 | DZ59: FALSE | EA59: FALSE | EB59: =(DW59-DN59)/DN59 -> #DIV/0! | EC59: =(DV59-DK59)/DK59 -> #DIV/0! | ED59: =EG59 + ABS(EE59) + ABS(EF59) -> 0 | EK59: FALSE | EL59: FALSE | EM59: =(EH59-DW59)/DW59 -> #DIV/0! | EN59: =(EG59-DV59)/DV59 -> #DIV/0! | EO59: =ER59 + ABS(EP59) + ABS(EQ59) -> 0 | EV59: FALSE | EW59: FALSE | EX59: =(ES59-EJ59)/EJ59 -> #DIV/0! | EY59: =(ER59-EG59)/EG59 -> #DIV/0!
C60: PRESÍDIO DE ARAXÁ | D60: 1450022 | E60: 84 | F60: E18B0801557 | G60: 00115998519 | H60: COMPANHIA DE SANEAMENTO DE MINAS GERAIS COPASA MG | I60: 17.281.106/0001-03 | N60: 107 | P60: 1799.19 | R60: 35683.95 | S60: 1278 | T60: 1450.01.0005511/2026-51 | X60: =AA60 + ABS(Y60) + ABS(Z60) -> 89001.21 | Y60: -4272.06 | Z60: 0 | AA60: 84729.15 | AB60: 2959 | AC60: 10/03/2026 | AD60: 1450.01.0029372/2026-78 | AE60: TRUE | AF60: TRUE | AG60: =(AB60-S60)/S60 -> 1.3153365 | AH60: =(AA60-R60)/R60 -> 1.374433 | AI60: =AL60 + ABS(AJ60) + ABS(AK60) -> 35905.02 | AJ60: -1723.44 | AK60: 0 | AL60: 34181.58 | AM60: 1170 | AN60: 46122 | AO60: 1450.01.0046622/2026-25 | AP60: TRUE | AQ60: TRUE | AR60: =(AM60-AB60)/AB60 -> -0.60459615 | AS60: =(AL60-AA60)/AA60 -> -0.59657827 | AT60: =AW60 + ABS(AU60) + ABS(AV60) -> 0 | BA60: FALSE | BB60: FALSE | BC60: =(AX60-AM60)/AM60 -> -1 | BD60: =(AW60-AL60)/AL60 -> -1 | BE60: =BH60 + ABS(BF60) + ABS(BG60) -> 0 | BL60: FALSE | BM60: FALSE | BN60: =(BI60-AZ60)/AZ60 -> #DIV/0! | BO60: =(BH60-AW60)/AW60 -> #DIV/0! | BP60: =BS60 + ABS(BQ60) + ABS(BR60) -> 0 | BW60: FALSE | BX60: FALSE | BY60: =(BT60-BI60)/BI60 -> #DIV/0! | BZ60: =(BS60-BH60)/BH60 -> #DIV/0! | CA60: =CD60 + ABS(CB60) + ABS(CC60) -> 0 | CH60: FALSE | CI60: FALSE | CJ60: =(CE60-BV60)/BV60 -> #DIV/0! | CK60: =(CD60-BS60)/BS60 -> #DIV/0! | CL60: =CO60 + ABS(CM60) + ABS(CN60) -> 0 | CS60: FALSE | CT60: FALSE | CU60: =(CP60-CE60)/CE60 -> #DIV/0! | CV60: =(CO60-CD60)/CD60 -> #DIV/0! | CW60: =CZ60 + ABS(CX60) + ABS(CY60) -> 0 | DD60: FALSE | DE60: FALSE | DF60: =(DA60-CR60)/CR60 -> #DIV/0! | DG60: =(CZ60-CO60)/CO60 -> #DIV/0! | DH60: =DK60 + ABS(DI60) + ABS(DJ60) -> 0 | DO60: FALSE | DP60: FALSE | DQ60: =(DL60-DA60)/DA60 -> #DIV/0! | DR60: =(DK60-CZ60)/CZ60 -> #DIV/0! | DS60: =DV60 + ABS(DT60) + ABS(DU60) -> 0 | DZ60: FALSE | EA60: FALSE | EB60: =(DW60-DN60)/DN60 -> #DIV/0! | EC60: =(DV60-DK60)/DK60 -> #DIV/0! | ED60: =EG60 + ABS(EE60) + ABS(EF60) -> 0 | EK60: FALSE | EL60: FALSE | EM60: =(EH60-DW60)/DW60 -> #DIV/0! | EN60: =(EG60-DV60)/DV60 -> #DIV/0! | EO60: =ER60 + ABS(EP60) + ABS(EQ60) -> 0 | EV60: FALSE | EW60: FALSE | EX60: =(ES60-EJ60)/EJ60 -> #DIV/0! | EY60: =(ER60-EG60)/EG60 -> #DIV/0!
C61: PRESÍDIO DE ARAXÁ | D61: 1450022 | E61: 84 | F61: D18B7041530 | G61: 00114922667 | H61: COMPANHIA DE SANEAMENTO DE MINAS GERAIS COPASA MG | I61: 17.281.106/0001-03 | N61: 107 | P61: 965.6 | R61: 19151.17 | S61: 704 | T61: 1450.01.0005511/2026-51 | X61: =AA61 + ABS(Y61) + ABS(Z61) -> 25815.28 | Y61: -1239.13 | Z61: 0 | AA61: 24576.15 | AB61: 886 | AC61: 10/03/2026 | AD61: 1450.01.0029372/2026-78 | AE61: TRUE | AF61: TRUE | AG61: =(AB61-S61)/S61 -> 0.25852273 | AH61: =(AA61-R61)/R61 -> 0.28327147 | AI61: =AL61 + ABS(AJ61) + ABS(AK61) -> 22160.73 | AJ61: -1063.72 | AK61: 0 | AL61: 21097.01 | AM61: 737 | AN61: 46122 | AO61: 1450.01.0046622/2026-25 | AP61: TRUE | AQ61: TRUE | AR61: =(AM61-AB61)/AB61 -> -0.16817156 | AS61: =(AL61-AA61)/AA61 -> -0.1415657 | AT61: =AW61 + ABS(AU61) + ABS(AV61) -> 0 | BA61: FALSE | BB61: FALSE | BC61: =(AX61-AM61)/AM61 -> -1 | BD61: =(AW61-AL61)/AL61 -> -1 | BE61: =BH61 + ABS(BF61) + ABS(BG61) -> 0 | BL61: FALSE | BM61: FALSE | BN61: =(BI61-AZ61)/AZ61 -> #DIV/0! | BO61: =(BH61-AW61)/AW61 -> #DIV/0! | BP61: =BS61 + ABS(BQ61) + ABS(BR61) -> 0 | BW61: FALSE | BX61: FALSE | BY61: =(BT61-BI61)/BI61 -> #DIV/0! | BZ61: =(BS61-BH61)/BH61 -> #DIV/0! | CA61: =CD61 + ABS(CB61) + ABS(CC61) -> 0 | CH61: FALSE | CI61: FALSE | CJ61: =(CE61-BV61)/BV61 -> #DIV/0! | CK61: =(CD61-BS61)/BS61 -> #DIV/0! | CL61: =CO61 + ABS(CM61) + ABS(CN61) -> 0 | CS61: FALSE | CT61: FALSE | CU61: =(CP61-CE61)/CE61 -> #DIV/0! | CV61: =(CO61-CD61)/CD61 -> #DIV/0! | CW61: =CZ61 + ABS(CX61) + ABS(CY61) -> 0 | DD61: FALSE | DE61: FALSE | DF61: =(DA61-CR61)/CR61 -> #DIV/0! | DG61: =(CZ61-CO61)/CO61 -> #DIV/0! | DH61: =DK61 + ABS(DI61) + ABS(DJ61) -> 0 | DO61: FALSE | DP61: FALSE | DQ61: =(DL61-DA61)/DA61 -> #DIV/0! | DR61: =(DK61-CZ61)/CZ61 -> #DIV/0! | DS61: =DV61 + ABS(DT61) + ABS(DU61) -> 0 | DZ61: FALSE | EA61: FALSE | EB61: =(DW61-DN61)/DN61 -> #DIV/0! | EC61: =(DV61-DK61)/DK61 -> #DIV/0! | ED61: =EG61 + ABS(EE61) + ABS(EF61) -> 0 | EK61: FALSE | EL61: FALSE | EM61: =(EH61-DW61)/DW61 -> #DIV/0! | EN61: =(EG61-DV61)/DV61 -> #DIV/0! | EO61: =ER61 + ABS(EP61) + ABS(EQ61) -> 0 | EV61: FALSE | EW61: FALSE | EX61: =(ES61-EJ61)/EJ61 -> #DIV/0! | EY61: =(ER61-EG61)/EG61 -> #DIV/0!
C62: PRESÍDIO DE BAMBUI | D62: 1450022 | E62: 344 | F62: B19F0007087 B18F0008532 | G62: 00018913504 | H62: COMPANHIA DE SANEAMENTO DE MINAS GERAIS COPASA MG | I62: 17.281.106/0001-03 | N62: 107 | P62: 16.05 | R62: 318.25 | S62: 32 | T62: 1450.01.0005511/2026-51 | X62: =AA62 + ABS(Y62) + ABS(Z62) -> 55.1 | Y62: -2.64 | Z62: 0 | AA62: 52.46 | AB62: 5 | AC62: 10/03/2026 | AD62: 1450.01.0029372/2026-78 | AE62: TRUE | AF62: TRUE | AG62: =(AB62-S62)/S62 -> -0.84375 | AH62: =(AA62-R62)/R62 -> -0.83516104 | AI62: =AL62 + ABS(AJ62) + ABS(AK62) -> 33.49 | AJ62: -1.61 | AK62: 0 | AL62: 31.88 | AM62: 0 | AN62: 46122 | AO62: 1450.01.0046622/2026-25 | AP62: TRUE | AQ62: TRUE | AR62: =(AM62-AB62)/AB62 -> -1 | AS62: =(AL62-AA62)/AA62 -> -0.39229889 | AT62: =AW62 + ABS(AU62) + ABS(AV62) -> 0 | BA62: FALSE | BB62: FALSE | BC62: =(AX62-AM62)/AM62 -> #DIV/0! | BD62: =(AW62-AL62)/AL62 -> -1 | BE62: =BH62 + ABS(BF62) + ABS(BG62) -> 0 | BL62: FALSE | BM62: FALSE | BN62: =(BI62-AZ62)/AZ62 -> #DIV/0! | BO62: =(BH62-AW62)/AW62 -> #DIV/0! | BP62: =BS62 + ABS(BQ62) + ABS(BR62) -> 0 | BW62: FALSE | BX62: FALSE | BY62: =(BT62-BI62)/BI62 -> #DIV/0! | BZ62: =(BS62-BH62)/BH62 -> #DIV/0! | CA62: =CD62 + ABS(CB62) + ABS(CC62) -> 0 | CH62: FALSE | CI62: FALSE | CJ62: =(CE62-BV62)/BV62 -> #DIV/0! | CK62: =(CD62-BS62)/BS62 -> #DIV/0! | CL62: =CO62 + ABS(CM62) + ABS(CN62) -> 0 | CS62: FALSE | CT62: FALSE | CU62: =(CP62-CE62)/CE62 -> #DIV/0! | CV62: =(CO62-CD62)/CD62 -> #DIV/0! | CW62: =CZ62 + ABS(CX62) + ABS(CY62) -> 0 | DD62: FALSE | DE62: FALSE | DF62: =(DA62-CR62)/CR62 -> #DIV/0! | DG62: =(CZ62-CO62)/CO62 -> #DIV/0! | DH62: =DK62 + ABS(DI62) + ABS(DJ62) -> 0 | DO62: FALSE | DP62: FALSE | DQ62: =(DL62-DA62)/DA62 -> #DIV/0! | DR62: =(DK62-CZ62)/CZ62 -> #DIV/0! | DS62: =DV62 + ABS(DT62) + ABS(DU62) -> 0 | DZ62: FALSE | EA62: FALSE | EB62: =(DW62-DN62)/DN62 -> #DIV/0! | EC62: =(DV62-DK62)/DK62 -> #DIV/0! | ED62: =EG62 + ABS(EE62) + ABS(EF62) -> 0 | EK62: FALSE | EL62: FALSE | EM62: =(EH62-DW62)/DW62 -> #DIV/0! | EN62: =(EG62-DV62)/DV62 -> #DIV/0! | EO62: =ER62 + ABS(EP62) + ABS(EQ62) -> 0 | EV62: FALSE | EW62: FALSE | EX62: =(ES62-EJ62)/EJ62 -> #DIV/0! | EY62: =(ER62-EG62)/EG62 -> #DIV/0!
C63: PRESÍDIO DE BARÃO DE COCAIS | D63: 1450022 | E63: 204 | F63: G23C8002547 | G63: 00116568348 | H63: COMPANHIA DE SANEAMENTO DE MINAS GERAIS COPASA MG | I63: 17.281.106/0001-03 | N63: 107 | P63: 1869.38 | R63: 37076.01 | S63: 2279 | T63: 1450.01.0005511/2026-51 | X63: =AA63 + ABS(Y63) + ABS(Z63) -> 33838.25 | Y63: -1624.24 | Z63: 0 | AA63: 32214.01 | AB63: 1960 | AC63: 10/03/2026 | AD63: 1450.01.0029372/2026-78 | AE63: TRUE | AF63: TRUE | AG63: =(AB63-S63)/S63 -> -0.13997367 | AH63: =(AA63-R63)/R63 -> -0.13113601 | AI63: =AL63 + ABS(AJ63) + ABS(AK63) -> 38475.6 | AJ63: -1846.83 | AK63: 0 | AL63: 36628.77 | AM63: 2148 | AN63: 46122 | AO63: 1450.01.0046622/2026-25 | AP63: TRUE | AQ63: TRUE | AR63: =(AM63-AB63)/AB63 -> 0.095918367 | AS63: =(AL63-AA63)/AA63 -> 0.13704472 | AT63: =AW63 + ABS(AU63) + ABS(AV63) -> 0 | BA63: FALSE | BB63: FALSE | BC63: =(AX63-AM63)/AM63 -> -1 | BD63: =(AW63-AL63)/AL63 -> -1 | BE63: =BH63 + ABS(BF63) + ABS(BG63) -> 0 | BL63: FALSE | BM63: FALSE | BN63: =(BI63-AZ63)/AZ63 -> #DIV/0! | BO63: =(BH63-AW63)/AW63 -> #DIV/0! | BP63: =BS63 + ABS(BQ63) + ABS(BR63) -> 0 | BW63: FALSE | BX63: FALSE | BY63: =(BT63-BI63)/BI63 -> #DIV/0! | BZ63: =(BS63-BH63)/BH63 -> #DIV/0! | CA63: =CD63 + ABS(CB63) + ABS(CC63) -> 0 | CH63: FALSE | CI63: FALSE | CJ63: =(CE63-BV63)/BV63 -> #DIV/0! | CK63: =(CD63-BS63)/BS63 -> #DIV/0! | CL63: =CO63 + ABS(CM63) + ABS(CN63) -> 0 | CS63: FALSE | CT63: FALSE | CU63: =(CP63-CE63)/CE63 -> #DIV/0! | CV63: =(CO63-CD63)/CD63 -> #DIV/0! | CW63: =CZ63 + ABS(CX63) + ABS(CY63) -> 0 | DD63: FALSE | DE63: FALSE | DF63: =(DA63-CR63)/CR63 -> #DIV/0! | DG63: =(CZ63-CO63)/CO63 -> #DIV/0! | DH63: =DK63 + ABS(DI63) + ABS(DJ63) -> 0 | DO63: FALSE | DP63: FALSE | DQ63: =(DL63-DA63)/DA63 -> #DIV/0! | DR63: =(DK63-CZ63)/CZ63 -> #DIV/0! | DS63: =DV63 + ABS(DT63) + ABS(DU63) -> 0 | DZ63: FALSE | EA63: FALSE | EB63: =(DW63-DN63)/DN63 -> #DIV/0! | EC63: =(DV63-DK63)/DK63 -> #DIV/0! | ED63: =EG63 + ABS(EE63) + ABS(EF63) -> 0 | EK63: FALSE | EL63: FALSE | EM63: =(EH63-DW63)/DW63 -> #DIV/0! | EN63: =(EG63-DV63)/DV63 -> #DIV/0! | EO63: =ER63 + ABS(EP63) + ABS(EQ63) -> 0 | EV63: FALSE | EW63: FALSE | EX63: =(ES63-EJ63)/EJ63 -> #DIV/0! | EY63: =(ER63-EG63)/EG63 -> #DIV/0!
C64: PRESÍDIO DE BICAS | D64: 1450022 | E64: 316 | F64: B18F0008417 D17B7000910 | G64: 00025269488 | H64: COMPANHIA DE SANEAMENTO DE MINAS GERAIS COPASA MG | I64: 17.281.106/0001-03 | N64: 107 | P64: 1149.14 | R64: 22791.27 | S64: 1416 | T64: 1450.01.0005511/2026-51 | X64: =AA64 + ABS(Y64) + ABS(Z64) -> 22602.85 | Y64: -1084.94 | Z64: 0 | AA64: 21517.91 | AB64: 1337 | AC64: 10/03/2026 | AD64: 1450.01.0029372/2026-78 | AE64: TRUE | AF64: TRUE | AG64: =(AB64-S64)/S64 -> -0.05579096 | AH64: =(AA64-R64)/R64 -> -0.055870515 | AI64: =AL64 + ABS(AJ64) + ABS(AK64) -> 19430.95 | AJ64: -932.69 | AK64: 0 | AL64: 18498.26 | AM64: 1104 | AN64: 46122 | AO64: 1450.01.0046622/2026-25 | AP64: TRUE | AQ64: TRUE | AR64: =(AM64-AB64)/AB64 -> -0.17427076 | AS64: =(AL64-AA64)/AA64 -> -0.14033194 | AT64: =AW64 + ABS(AU64) + ABS(AV64) -> 0 | BA64: FALSE | BB64: FALSE | BC64: =(AX64-AM64)/AM64 -> -1 | BD64: =(AW64-AL64)/AL64 -> -1 | BE64: =BH64 + ABS(BF64) + ABS(BG64) -> 0 | BL64: FALSE | BM64: FALSE | BN64: =(BI64-AZ64)/AZ64 -> #DIV/0! | BO64: =(BH64-AW64)/AW64 -> #DIV/0! | BP64: =BS64 + ABS(BQ64) + ABS(BR64) -> 0 | BW64: FALSE | BX64: FALSE | BY64: =(BT64-BI64)/BI64 -> #DIV/0! | BZ64: =(BS64-BH64)/BH64 -> #DIV/0! | CA64: =CD64 + ABS(CB64) + ABS(CC64) -> 0 | CH64: FALSE | CI64: FALSE | CJ64: =(CE64-BV64)/BV64 -> #DIV/0! | CK64: =(CD64-BS64)/BS64 -> #DIV/0! | CL64: =CO64 + ABS(CM64) + ABS(CN64) -> 0 | CS64: FALSE | CT64: FALSE | CU64: =(CP64-CE64)/CE64 -> #DIV/0! | CV64: =(CO64-CD64)/CD64 -> #DIV/0! | CW64: =CZ64 + ABS(CX64) + ABS(CY64) -> 0 | DD64: FALSE | DE64: FALSE | DF64: =(DA64-CR64)/CR64 -> #DIV/0! | DG64: =(CZ64-CO64)/CO64 -> #DIV/0! | DH64: =DK64 + ABS(DI64) + ABS(DJ64) -> 0 | DO64: FALSE | DP64: FALSE | DQ64: =(DL64-DA64)/DA64 -> #DIV/0! | DR64: =(DK64-CZ64)/CZ64 -> #DIV/0! | DS64: =DV64 + ABS(DT64) + ABS(DU64) -> 0 | DZ64: FALSE | EA64: FALSE | EB64: =(DW64-DN64)/DN64 -> #DIV/0! | EC64: =(DV64-DK64)/DK64 -> #DIV/0! | ED64: =EG64 + ABS(EE64) + ABS(EF64) -> 0 | EK64: FALSE | EL64: FALSE | EM64: =(EH64-DW64)/DW64 -> #DIV/0! | EN64: =(EG64-DV64)/DV64 -> #DIV/0! | EO64: =ER64 + ABS(EP64) + ABS(EQ64) -> 0 | EV64: FALSE | EW64: FALSE | EX64: =(ES64-EJ64)/EJ64 -> #DIV/0! | EY64: =(ER64-EG64)/EG64 -> #DIV/0!
C65: PRESÍDIO DE BOM DESPACHO | D65: 1450022 | E65: 242 | F65: D17B0704000 | G65: 00102529183 | H65: COMPANHIA DE SANEAMENTO DE MINAS GERAIS COPASA MG | I65: 17.281.106/0001-03 | N65: 107 | P65: 1452.11 | R65: 28800.08 | S65: 1039 | T65: 1450.01.0005511/2026-51 | X65: =AA65 + ABS(Y65) + ABS(Z65) -> 35538.77 | Y65: -1705.86 | Z65: 0 | AA65: 33832.91 | AB65: 1210 | AC65: 10/03/2026 | AD65: 1450.01.0029372/2026-78 | AE65: TRUE | AF65: TRUE | AG65: =(AB65-S65)/S65 -> 0.16458133 | AH65: =(AA65-R65)/R65 -> 0.17475056 | AI65: =AL65 + ABS(AJ65) + ABS(AK65) -> 32032.5 | AJ65: -1537.56 | AK65: 0 | AL65: 30494.94 | AM65: 1048 | AN65: 46122 | AO65: 1450.01.0046622/2026-25 | AP65: TRUE | AQ65: TRUE | AR65: =(AM65-AB65)/AB65 -> -0.1338843 | AS65: =(AL65-AA65)/AA65 -> -0.098660446 | AT65: =AW65 + ABS(AU65) + ABS(AV65) -> 0 | BA65: FALSE | BB65: FALSE | BC65: =(AX65-AM65)/AM65 -> -1 | BD65: =(AW65-AL65)/AL65 -> -1 | BE65: =BH65 + ABS(BF65) + ABS(BG65) -> 0 | BL65: FALSE | BM65: FALSE | BN65: =(BI65-AZ65)/AZ65 -> #DIV/0! | BO65: =(BH65-AW65)/AW65 -> #DIV/0! | BP65: =BS65 + ABS(BQ65) + ABS(BR65) -> 0 | BW65: FALSE | BX65: FALSE | BY65: =(BT65-BI65)/BI65 -> #DIV/0! | BZ65: =(BS65-BH65)/BH65 -> #DIV/0! | CA65: =CD65 + ABS(CB65) + ABS(CC65) -> 0 | CH65: FALSE | CI65: FALSE | CJ65: =(CE65-BV65)/BV65 -> #DIV/0! | CK65: =(CD65-BS65)/BS65 -> #DIV/0! | CL65: =CO65 + ABS(CM65) + ABS(CN65) -> 0 | CS65: FALSE | CT65: FALSE | CU65: =(CP65-CE65)/CE65 -> #DIV/0! | CV65: =(CO65-CD65)/CD65 -> #DIV/0! | CW65: =CZ65 + ABS(CX65) + ABS(CY65) -> 0 | DD65: FALSE | DE65: FALSE | DF65: =(DA65-CR65)/CR65 -> #DIV/0! | DG65: =(CZ65-CO65)/CO65 -> #DIV/0! | DH65: =DK65 + ABS(DI65) + ABS(DJ65) -> 0 | DO65: FALSE | DP65: FALSE | DQ65: =(DL65-DA65)/DA65 -> #DIV/0! | DR65: =(DK65-CZ65)/CZ65 -> #DIV/0! | DS65: =DV65 + ABS(DT65) + ABS(DU65) -> 0 | DZ65: FALSE | EA65: FALSE | EB65: =(DW65-DN65)/DN65 -> #DIV/0! | EC65: =(DV65-DK65)/DK65 -> #DIV/0! | ED65: =EG65 + ABS(EE65) + ABS(EF65) -> 0 | EK65: FALSE | EL65: FALSE | EM65: =(EH65-DW65)/DW65 -> #DIV/0! | EN65: =(EG65-DV65)/DV65 -> #DIV/0! | EO65: =ER65 + ABS(EP65) + ABS(EQ65) -> 0 | EV65: FALSE | EW65: FALSE | EX65: =(ES65-EJ65)/EJ65 -> #DIV/0! | EY65: =(ER65-EG65)/EG65 -> #DIV/0!
C66: PRESÍDIO DE BOTELHOS | D66: 1450022 | E66: 66 | F66: A19N0095536 | G66: 00027250237 | H66: COMPANHIA DE SANEAMENTO DE MINAS GERAIS COPASA MG | I66: 17.281.106/0001-03 | N66: 107 | P66: 1.49 | R66: 29.61 | T66: 1450.01.0005511/2026-51 | X66: =AA66 + ABS(Y66) + ABS(Z66) -> 31.28 | Y66: -1.5 | Z66: 0 | AA66: 29.78 | AB66: 0 | AC66: 10/03/2026 | AD66: 1450.01.0029372/2026-78 | AE66: TRUE | AF66: TRUE | AG66: 0 | AH66: =(AA66-R66)/R66 -> 0.0057413036 | AI66: =AL66 + ABS(AJ66) + ABS(AK66) -> 36.43 | AJ66: -1.75 | AK66: 0 | AL66: 34.68 | AM66: 0 | AN66: 46122 | AO66: 1450.01.0046622/2026-25 | AP66: TRUE | AQ66: TRUE | AR66: 0 | AS66: =(AL66-AA66)/AA66 -> 0.16453996 | AT66: =AW66 + ABS(AU66) + ABS(AV66) -> 0 | BA66: FALSE | BB66: FALSE | BC66: =(AX66-AM66)/AM66 -> #DIV/0! | BD66: =(AW66-AL66)/AL66 -> -1 | BE66: =BH66 + ABS(BF66) + ABS(BG66) -> 0 | BL66: FALSE | BM66: FALSE | BN66: =(BI66-AZ66)/AZ66 -> #DIV/0! | BO66: =(BH66-AW66)/AW66 -> #DIV/0! | BP66: =BS66 + ABS(BQ66) + ABS(BR66) -> 0 | BW66: FALSE | BX66: FALSE | BY66: =(BT66-BI66)/BI66 -> #DIV/0! | BZ66: =(BS66-BH66)/BH66 -> #DIV/0! | CA66: =CD66 + ABS(CB66) + ABS(CC66) -> 0 | CH66: FALSE | CI66: FALSE | CJ66: =(CE66-BV66)/BV66 -> #DIV/0! | CK66: =(CD66-BS66)/BS66 -> #DIV/0! | CL66: =CO66 + ABS(CM66) + ABS(CN66) -> 0 | CS66: FALSE | CT66: FALSE | CU66: =(CP66-CE66)/CE66 -> #DIV/0! | CV66: =(CO66-CD66)/CD66 -> #DIV/0! | CW66: =CZ66 + ABS(CX66) + ABS(CY66) -> 0 | DD66: FALSE | DE66: FALSE | DF66: =(DA66-CR66)/CR66 -> #DIV/0! | DG66: =(CZ66-CO66)/CO66 -> #DIV/0! | DH66: =DK66 + ABS(DI66) + ABS(DJ66) -> 0 | DO66: FALSE | DP66: FALSE | DQ66: =(DL66-DA66)/DA66 -> #DIV/0! | DR66: =(DK66-CZ66)/CZ66 -> #DIV/0! | DS66: =DV66 + ABS(DT66) + ABS(DU66) -> 0 | DZ66: FALSE | EA66: FALSE | EB66: =(DW66-DN66)/DN66 -> #DIV/0! | EC66: =(DV66-DK66)/DK66 -> #DIV/0! | ED66: =EG66 + ABS(EE66) + ABS(EF66) -> 0 | EK66: FALSE | EL66: FALSE | EM66: =(EH66-DW66)/DW66 -> #DIV/0! | EN66: =(EG66-DV66)/DV66 -> #DIV/0! | EO66: =ER66 + ABS(EP66) + ABS(EQ66) -> 0 | EV66: FALSE | EW66: FALSE | EX66: =(ES66-EJ66)/EJ66 -> #DIV/0! | EY66: =(ER66-EG66)/EG66 -> #DIV/0!
C67: PRESÍDIO DE BOTELHOS | D67: 1450022 | E67: 66 | F67: B18F0007758 | G67: 00004919572 | H67: COMPANHIA DE SANEAMENTO DE MINAS GERAIS COPASA MG | I67: 17.281.106/0001-03 | N67: 107 | P67: 1.49 | R67: 29.61 | T67: 1450.01.0005511/2026-51 | X67: =AA67 + ABS(Y67) + ABS(Z67) -> 31.28 | Y67: -1.5 | Z67: 0 | AA67: 29.78 | AB67: 0 | AC67: 10/03/2026 | AD67: 1450.01.0029372/2026-78 | AE67: TRUE | AF67: TRUE | AG67: 0 | AH67: =(AA67-R67)/R67 -> 0.0057413036 | AI67: =AL67 + ABS(AJ67) + ABS(AK67) -> 36.43 | AJ67: -1.75 | AK67: 0 | AL67: 34.68 | AM67: 0 | AN67: 46122 | AO67: 1450.01.0046622/2026-25 | AP67: TRUE | AQ67: TRUE | AR67: 0 | AS67: =(AL67-AA67)/AA67 -> 0.16453996 | AT67: =AW67 + ABS(AU67) + ABS(AV67) -> 0 | BA67: FALSE | BB67: FALSE | BC67: =(AX67-AM67)/AM67 -> #DIV/0! | BD67: =(AW67-AL67)/AL67 -> -1 | BE67: =BH67 + ABS(BF67) + ABS(BG67) -> 0 | BL67: FALSE | BM67: FALSE | BN67: =(BI67-AZ67)/AZ67 -> #DIV/0! | BO67: =(BH67-AW67)/AW67 -> #DIV/0! | BP67: =BS67 + ABS(BQ67) + ABS(BR67) -> 0 | BW67: FALSE | BX67: FALSE | BY67: =(BT67-BI67)/BI67 -> #DIV/0! | BZ67: =(BS67-BH67)/BH67 -> #DIV/0! | CA67: =CD67 + ABS(CB67) + ABS(CC67) -> 0 | CH67: FALSE | CI67: FALSE | CJ67: =(CE67-BV67)/BV67 -> #DIV/0! | CK67: =(CD67-BS67)/BS67 -> #DIV/0! | CL67: =CO67 + ABS(CM67) + ABS(CN67) -> 0 | CS67: FALSE | CT67: FALSE | CU67: =(CP67-CE67)/CE67 -> #DIV/0! | CV67: =(CO67-CD67)/CD67 -> #DIV/0! | CW67: =CZ67 + ABS(CX67) + ABS(CY67) -> 0 | DD67: FALSE | DE67: FALSE | DF67: =(DA67-CR67)/CR67 -> #DIV/0! | DG67: =(CZ67-CO67)/CO67 -> #DIV/0! | DH67: =DK67 + ABS(DI67) + ABS(DJ67) -> 0 | DO67: FALSE | DP67: FALSE | DQ67: =(DL67-DA67)/DA67 -> #DIV/0! | DR67: =(DK67-CZ67)/CZ67 -> #DIV/0! | DS67: =DV67 + ABS(DT67) + ABS(DU67) -> 0 | DZ67: FALSE | EA67: FALSE | EB67: =(DW67-DN67)/DN67 -> #DIV/0! | EC67: =(DV67-DK67)/DK67 -> #DIV/0! | ED67: =EG67 + ABS(EE67) + ABS(EF67) -> 0 | EK67: FALSE | EL67: FALSE | EM67: =(EH67-DW67)/DW67 -> #DIV/0! | EN67: =(EG67-DV67)/DV67 -> #DIV/0! | EO67: =ER67 + ABS(EP67) + ABS(EQ67) -> 0 | EV67: FALSE | EW67: FALSE | EX67: =(ES67-EJ67)/EJ67 -> #DIV/0! | EY67: =(ER67-EG67)/EG67 -> #DIV/0!
C68: PRESÍDIO DE BRUMADINHO | D68: 1450022 | E68: 191 | F68: A14Z0109737 | G68: 00011669012 | H68: COMPANHIA DE SANEAMENTO DE MINAS GERAIS COPASA MG | I68: 17.281.106/0001-03 | N68: 107 | P68: 10.84 | R68: 214.98 | S68: 14 | T68: 1450.01.0005511/2026-51 | X68: =AA68 + ABS(Y68) + ABS(Z68) -> 133.39 | Y68: -6.4 | Z68: 0 | AA68: 126.99 | AB68: 8 | AC68: 10/03/2026 | AD68: 1450.01.0029372/2026-78 | AE68: TRUE | AF68: TRUE | AG68: =(AB68-S68)/S68 -> -0.42857143 | AH68: =(AA68-R68)/R68 -> -0.40929389 | AI68: =AL68 + ABS(AJ68) + ABS(AK68) -> 130.74 | AJ68: -6.28 | AK68: 0 | AL68: 124.46 | AM68: 7 | AN68: 46122 | AO68: 1450.01.0046622/2026-25 | AP68: TRUE | AQ68: TRUE | AR68: =(AM68-AB68)/AB68 -> -0.125 | AS68: =(AL68-AA68)/AA68 -> -0.019922829 | AT68: =AW68 + ABS(AU68) + ABS(AV68) -> 0 | BA68: FALSE | BB68: FALSE | BC68: =(AX68-AM68)/AM68 -> -1 | BD68: =(AW68-AL68)/AL68 -> -1 | BE68: =BH68 + ABS(BF68) + ABS(BG68) -> 0 | BL68: FALSE | BM68: FALSE | BN68: =(BI68-AZ68)/AZ68 -> #DIV/0! | BO68: =(BH68-AW68)/AW68 -> #DIV/0! | BP68: =BS68 + ABS(BQ68) + ABS(BR68) -> 0 | BW68: FALSE | BX68: FALSE | BY68: =(BT68-BI68)/BI68 -> #DIV/0! | BZ68: =(BS68-BH68)/BH68 -> #DIV/0! | CA68: =CD68 + ABS(CB68) + ABS(CC68) -> 0 | CH68: FALSE | CI68: FALSE | CJ68: =(CE68-BV68)/BV68 -> #DIV/0! | CK68: =(CD68-BS68)/BS68 -> #DIV/0! | CL68: =CO68 + ABS(CM68) + ABS(CN68) -> 0 | CS68: FALSE | CT68: FALSE | CU68: =(CP68-CE68)/CE68 -> #DIV/0! | CV68: =(CO68-CD68)/CD68 -> #DIV/0! | CW68: =CZ68 + ABS(CX68) + ABS(CY68) -> 0 | DD68: FALSE | DE68: FALSE | DF68: =(DA68-CR68)/CR68 -> #DIV/0! | DG68: =(CZ68-CO68)/CO68 -> #DIV/0! | DH68: =DK68 + ABS(DI68) + ABS(DJ68) -> 0 | DO68: FALSE | DP68: FALSE | DQ68: =(DL68-DA68)/DA68 -> #DIV/0! | DR68: =(DK68-CZ68)/CZ68 -> #DIV/0! | DS68: =DV68 + ABS(DT68) + ABS(DU68) -> 0 | DZ68: FALSE | EA68: FALSE | EB68: =(DW68-DN68)/DN68 -> #DIV/0! | EC68: =(DV68-DK68)/DK68 -> #DIV/0! | ED68: =EG68 + ABS(EE68) + ABS(EF68) -> 0 | EK68: FALSE | EL68: FALSE | EM68: =(EH68-DW68)/DW68 -> #DIV/0! | EN68: =(EG68-DV68)/DV68 -> #DIV/0! | EO68: =ER68 + ABS(EP68) + ABS(EQ68) -> 0 | EV68: FALSE | EW68: FALSE | EX68: =(ES68-EJ68)/EJ68 -> #DIV/0! | EY68: =(ER68-EG68)/EG68 -> #DIV/0!
C69: PRESÍDIO DE BURITIS | D69: 1450022 | E69: 248 | F69: D17B0704769 | G69: 00140295399 | H69: COMPANHIA DE SANEAMENTO DE MINAS GERAIS COPASA MG | I69: 17.281.106/0001-03 | N69: 107 | P69: 1017.89 | R69: 20188.06 | S69: 740 | T69: 1450.01.0005511/2026-51 | X69: =AA69 + ABS(Y69) + ABS(Z69) -> 22385.89 | Y69: -1074.52 | Z69: 0 | AA69: 21311.37 | AB69: 779 | AC69: 10/03/2026 | AD69: 1450.01.0029372/2026-78 | AE69: TRUE | AF69: TRUE | AG69: =(AB69-S69)/S69 -> 0.052702703 | AH69: =(AA69-R69)/R69 -> 0.055642295 | AI69: =AL69 + ABS(AJ69) + ABS(AK69) -> 20243.12 | AJ69: -971.67 | AK69: 0 | AL69: 19271.45 | AM69: 685 | AN69: 46122 | AO69: 1450.01.0046622/2026-25 | AP69: TRUE | AQ69: TRUE | AR69: =(AM69-AB69)/AB69 -> -0.12066752 | AS69: =(AL69-AA69)/AA69 -> -0.095719797 | AT69: =AW69 + ABS(AU69) + ABS(AV69) -> 0 | BA69: FALSE | BB69: FALSE | BC69: =(AX69-AM69)/AM69 -> -1 | BD69: =(AW69-AL69)/AL69 -> -1 | BE69: =BH69 + ABS(BF69) + ABS(BG69) -> 0 | BL69: FALSE | BM69: FALSE | BN69: =(BI69-AZ69)/AZ69 -> #DIV/0! | BO69: =(BH69-AW69)/AW69 -> #DIV/0! | BP69: =BS69 + ABS(BQ69) + ABS(BR69) -> 0 | BW69: FALSE | BX69: FALSE | BY69: =(BT69-BI69)/BI69 -> #DIV/0! | BZ69: =(BS69-BH69)/BH69 -> #DIV/0! | CA69: =CD69 + ABS(CB69) + ABS(CC69) -> 0 | CH69: FALSE | CI69: FALSE | CJ69: =(CE69-BV69)/BV69 -> #DIV/0! | CK69: =(CD69-BS69)/BS69 -> #DIV/0! | CL69: =CO69 + ABS(CM69) + ABS(CN69) -> 0 | CS69: FALSE | CT69: FALSE | CU69: =(CP69-CE69)/CE69 -> #DIV/0! | CV69: =(CO69-CD69)/CD69 -> #DIV/0! | CW69: =CZ69 + ABS(CX69) + ABS(CY69) -> 0 | DD69: FALSE | DE69: FALSE | DF69: =(DA69-CR69)/CR69 -> #DIV/0! | DG69: =(CZ69-CO69)/CO69 -> #DIV/0! | DH69: =DK69 + ABS(DI69) + ABS(DJ69) -> 0 | DO69: FALSE | DP69: FALSE | DQ69: =(DL69-DA69)/DA69 -> #DIV/0! | DR69: =(DK69-CZ69)/CZ69 -> #DIV/0! | DS69: =DV69 + ABS(DT69) + ABS(DU69) -> 0 | DZ69: FALSE | EA69: FALSE | EB69: =(DW69-DN69)/DN69 -> #DIV/0! | EC69: =(DV69-DK69)/DK69 -> #DIV/0! | ED69: =EG69 + ABS(EE69) + ABS(EF69) -> 0 | EK69: FALSE | EL69: FALSE | EM69: =(EH69-DW69)/DW69 -> #DIV/0! | EN69: =(EG69-DV69)/DV69 -> #DIV/0! | EO69: =ER69 + ABS(EP69) + ABS(EQ69) -> 0 | EV69: FALSE | EW69: FALSE | EX69: =(ES69-EJ69)/EJ69 -> #DIV/0! | EY69: =(ER69-EG69)/EG69 -> #DIV/0!
C70: PRESÍDIO DE BURITIS | D70: 1450022 | E70: 248 | F70: A22G0206143 | G70: 00017552249 | H70: COMPANHIA DE SANEAMENTO DE MINAS GERAIS COPASA MG | I70: 17.281.106/0001-03 | N70: 107 | P70: 688.23 | R70: 13649.83 | S70: 513 | T70: 1450.01.0005511/2026-51 | X70: =AA70 + ABS(Y70) + ABS(Z70) -> 12825.31 | Y70: -615.61 | Z70: 0 | AA70: 12209.7 | AB70: 463 | AC70: 10/03/2026 | AD70: 1450.01.0029372/2026-78 | AE70: TRUE | AF70: TRUE | AG70: =(AB70-S70)/S70 -> -0.097465887 | AH70: =(AA70-R70)/R70 -> -0.10550534 | AI70: =AL70 + ABS(AJ70) + ABS(AK70) -> 19585.15 | AJ70: -940.09 | AK70: 0 | AL70: 18645.06 | AM70: 664 | AN70: 46122 | AO70: 1450.01.0046622/2026-25 | AP70: TRUE | AQ70: TRUE | AR70: =(AM70-AB70)/AB70 -> 0.43412527 | AS70: =(AL70-AA70)/AA70 -> 0.52706946 | AT70: =AW70 + ABS(AU70) + ABS(AV70) -> 0 | BA70: FALSE | BB70: FALSE | BC70: =(AX70-AM70)/AM70 -> -1 | BD70: =(AW70-AL70)/AL70 -> -1 | BE70: =BH70 + ABS(BF70) + ABS(BG70) -> 0 | BL70: FALSE | BM70: FALSE | BN70: =(BI70-AZ70)/AZ70 -> #DIV/0! | BO70: =(BH70-AW70)/AW70 -> #DIV/0! | BP70: =BS70 + ABS(BQ70) + ABS(BR70) -> 0 | BW70: FALSE | BX70: FALSE | BY70: =(BT70-BI70)/BI70 -> #DIV/0! | BZ70: =(BS70-BH70)/BH70 -> #DIV/0! | CA70: =CD70 + ABS(CB70) + ABS(CC70) -> 0 | CH70: FALSE | CI70: FALSE | CJ70: =(CE70-BV70)/BV70 -> #DIV/0! | CK70: =(CD70-BS70)/BS70 -> #DIV/0! | CL70: =CO70 + ABS(CM70) + ABS(CN70) -> 0 | CS70: FALSE | CT70: FALSE | CU70: =(CP70-CE70)/CE70 -> #DIV/0! | CV70: =(CO70-CD70)/CD70 -> #DIV/0! | CW70: =CZ70 + ABS(CX70) + ABS(CY70) -> 0 | DD70: FALSE | DE70: FALSE | DF70: =(DA70-CR70)/CR70 -> #DIV/0! | DG70: =(CZ70-CO70)/CO70 -> #DIV/0! | DH70: =DK70 + ABS(DI70) + ABS(DJ70) -> 0 | DO70: FALSE | DP70: FALSE | DQ70: =(DL70-DA70)/DA70 -> #DIV/0! | DR70: =(DK70-CZ70)/CZ70 -> #DIV/0! | DS70: =DV70 + ABS(DT70) + ABS(DU70) -> 0 | DZ70: FALSE | EA70: FALSE | EB70: =(DW70-DN70)/DN70 -> #DIV/0! | EC70: =(DV70-DK70)/DK70 -> #DIV/0! | ED70: =EG70 + ABS(EE70) + ABS(EF70) -> 0 | EK70: FALSE | EL70: FALSE | EM70: =(EH70-DW70)/DW70 -> #DIV/0! | EN70: =(EG70-DV70)/DV70 -> #DIV/0! | EO70: =ER70 + ABS(EP70) + ABS(EQ70) -> 0 | EV70: FALSE | EW70: FALSE | EX70: =(ES70-EJ70)/EJ70 -> #DIV/0! | EY70: =(ER70-EG70)/EG70 -> #DIV/0!
C71: PRESÍDIO DE CAMPESTRE | D71: 1450022 | E71: 372 | F71: Y20G0948475 | G71: 00004955030 | H71: COMPANHIA DE SANEAMENTO DE MINAS GERAIS COPASA MG | I71: 17.281.106/0001-03 | N71: 107 | P71: 2.18 | R71: 43.32 | S71: 3 | T71: 1450.01.0005511/2026-51 | X71: =AA71 + ABS(Y71) + ABS(Z71) -> 46.43 | Y71: -2.23 | Z71: 0 | AA71: 44.2 | AB71: 3 | AC71: 10/03/2026 | AD71: 1450.01.0029372/2026-78 | AE71: TRUE | AF71: TRUE | AG71: =(AB71-S71)/S71 -> 0 | AH71: =(AA71-R71)/R71 -> 0.020313943 | AI71: =AL71 + ABS(AJ71) + ABS(AK71) -> 51.61 | AJ71: -2.48 | AK71: 0 | AL71: 49.13 | AM71: 3 | AN71: 46122 | AO71: 1450.01.0046622/2026-25 | AP71: TRUE | AQ71: TRUE | AR71: =(AM71-AB71)/AB71 -> 0 | AS71: =(AL71-AA71)/AA71 -> 0.11153846 | AT71: =AW71 + ABS(AU71) + ABS(AV71) -> 0 | BA71: FALSE | BB71: FALSE | BC71: =(AX71-AM71)/AM71 -> -1 | BD71: =(AW71-AL71)/AL71 -> -1 | BE71: =BH71 + ABS(BF71) + ABS(BG71) -> 0 | BL71: FALSE | BM71: FALSE | BN71: =(BI71-AZ71)/AZ71 -> #DIV/0! | BO71: =(BH71-AW71)/AW71 -> #DIV/0! | BP71: =BS71 + ABS(BQ71) + ABS(BR71) -> 0 | BW71: FALSE | BX71: FALSE | BY71: =(BT71-BI71)/BI71 -> #DIV/0! | BZ71: =(BS71-BH71)/BH71 -> #DIV/0! | CA71: =CD71 + ABS(CB71) + ABS(CC71) -> 0 | CH71: FALSE | CI71: FALSE | CJ71: =(CE71-BV71)/BV71 -> #DIV/0! | CK71: =(CD71-BS71)/BS71 -> #DIV/0! | CL71: =CO71 + ABS(CM71) + ABS(CN71) -> 0 | CS71: FALSE | CT71: FALSE | CU71: =(CP71-CE71)/CE71 -> #DIV/0! | CV71: =(CO71-CD71)/CD71 -> #DIV/0! | CW71: =CZ71 + ABS(CX71) + ABS(CY71) -> 0 | DD71: FALSE | DE71: FALSE | DF71: =(DA71-CR71)/CR71 -> #DIV/0! | DG71: =(CZ71-CO71)/CO71 -> #DIV/0! | DH71: =DK71 + ABS(DI71) + ABS(DJ71) -> 0 | DO71: FALSE | DP71: FALSE | DQ71: =(DL71-DA71)/DA71 -> #DIV/0! | DR71: =(DK71-CZ71)/CZ71 -> #DIV/0! | DS71: =DV71 + ABS(DT71) + ABS(DU71) -> 0 | DZ71: FALSE | EA71: FALSE | EB71: =(DW71-DN71)/DN71 -> #DIV/0! | EC71: =(DV71-DK71)/DK71 -> #DIV/0! | ED71: =EG71 + ABS(EE71) + ABS(EF71) -> 0 | EK71: FALSE | EL71: FALSE | EM71: =(EH71-DW71)/DW71 -> #DIV/0! | EN71: =(EG71-DV71)/DV71 -> #DIV/0! | EO71: =ER71 + ABS(EP71) + ABS(EQ71) -> 0 | EV71: FALSE | EW71: FALSE | EX71: =(ES71-EJ71)/EJ71 -> #DIV/0! | EY71: =(ER71-EG71)/EG71 -> #DIV/0!
C72: PRESÍDIO DE CANAPOLIS | D72: 1450022 | E72: 334 | F72: D18B0704321 | G72: 00006147348 | H72: COMPANHIA DE SANEAMENTO DE MINAS GERAIS COPASA MG | I72: 17.281.106/0001-03 | N72: 107 | P72: 483.15 | R72: 9582.44 | S72: 618 | T72: 1450.01.0005511/2026-51 | X72: =AA72 + ABS(Y72) + ABS(Z72) -> 11717.35 | Y72: -562.43 | Z72: 0 | AA72: 11154.92 | AB72: 713 | AC72: 10/03/2026 | AD72: 1450.01.0029372/2026-78 | AE72: TRUE | AF72: TRUE | AG72: =(AB72-S72)/S72 -> 0.15372168 | AH72: =(AA72-R72)/R72 -> 0.16410017 | AI72: =AL72 + ABS(AJ72) + ABS(AK72) -> 10249.41 | AJ72: -491.97 | AK72: 0 | AL72: 9757.44 | AM72: 605 | AN72: 46122 | AO72: 1450.01.0046622/2026-25 | AP72: TRUE | AQ72: TRUE | AR72: =(AM72-AB72)/AB72 -> -0.15147265 | AS72: =(AL72-AA72)/AA72 -> -0.12527925 | AT72: =AW72 + ABS(AU72) + ABS(AV72) -> 0 | BA72: FALSE | BB72: FALSE | BC72: =(AX72-AM72)/AM72 -> -1 | BD72: =(AW72-AL72)/AL72 -> -1 | BE72: =BH72 + ABS(BF72) + ABS(BG72) -> 0 | BL72: FALSE | BM72: FALSE | BN72: =(BI72-AZ72)/AZ72 -> #DIV/0! | BO72: =(BH72-AW72)/AW72 -> #DIV/0! | BP72: =BS72 + ABS(BQ72) + ABS(BR72) -> 0 | BW72: FALSE | BX72: FALSE | BY72: =(BT72-BI72)/BI72 -> #DIV/0! | BZ72: =(BS72-BH72)/BH72 -> #DIV/0! | CA72: =CD72 + ABS(CB72) + ABS(CC72) -> 0 | CH72: FALSE | CI72: FALSE | CJ72: =(CE72-BV72)/BV72 -> #DIV/0! | CK72: =(CD72-BS72)/BS72 -> #DIV/0! | CL72: =CO72 + ABS(CM72) + ABS(CN72) -> 0 | CS72: FALSE | CT72: FALSE | CU72: =(CP72-CE72)/CE72 -> #DIV/0! | CV72: =(CO72-CD72)/CD72 -> #DIV/0! | CW72: =CZ72 + ABS(CX72) + ABS(CY72) -> 0 | DD72: FALSE | DE72: FALSE | DF72: =(DA72-CR72)/CR72 -> #DIV/0! | DG72: =(CZ72-CO72)/CO72 -> #DIV/0! | DH72: =DK72 + ABS(DI72) + ABS(DJ72) -> 0 | DO72: FALSE | DP72: FALSE | DQ72: =(DL72-DA72)/DA72 -> #DIV/0! | DR72: =(DK72-CZ72)/CZ72 -> #DIV/0! | DS72: =DV72 + ABS(DT72) + ABS(DU72) -> 0 | DZ72: FALSE | EA72: FALSE | EB72: =(DW72-DN72)/DN72 -> #DIV/0! | EC72: =(DV72-DK72)/DK72 -> #DIV/0! | ED72: =EG72 + ABS(EE72) + ABS(EF72) -> 0 | EK72: FALSE | EL72: FALSE | EM72: =(EH72-DW72)/DW72 -> #DIV/0! | EN72: =(EG72-DV72)/DV72 -> #DIV/0! | EO72: =ER72 + ABS(EP72) + ABS(EQ72) -> 0 | EV72: FALSE | EW72: FALSE | EX72: =(ES72-EJ72)/EJ72 -> #DIV/0! | EY72: =(ER72-EG72)/EG72 -> #DIV/0!
C73: PRESÍDIO DE CAPELINHA | D73: 1450022 | E73: 160 | F73: A15F0030782 | G73: 00023705175 | H73: COMPANHIA DE SANEAMENTO DE MINAS GERAIS COPASA MG | I73: 17.281.106/0001-03 | N73: 107 | P73: 3.8 | R73: 75.34 | S73: 3 | T73: 1450.01.0005511/2026-51 | X73: =AA73 + ABS(Y73) + ABS(Z73) -> 87.48 | Y73: -4.2 | Z73: 0 | AA73: 83.28 | AB73: 4 | AC73: 10/03/2026 | AD73: 1450.01.0029372/2026-78 | AE73: TRUE | AF73: TRUE | AG73: =(AB73-S73)/S73 -> 0.33333333 | AH73: =(AA73-R73)/R73 -> 0.1053889 | AI73: =AL73 + ABS(AJ73) + ABS(AK73) -> 78.54 | AJ73: -3.77 | AK73: 0 | AL73: 74.77 | AM73: 2 | AN73: 46122 | AO73: 1450.01.0046622/2026-25 | AP73: TRUE | AQ73: TRUE | AR73: =(AM73-AB73)/AB73 -> -0.5 | AS73: =(AL73-AA73)/AA73 -> -0.1021854 | AT73: =AW73 + ABS(AU73) + ABS(AV73) -> 0 | BA73: FALSE | BB73: FALSE | BC73: =(AX73-AM73)/AM73 -> -1 | BD73: =(AW73-AL73)/AL73 -> -1 | BE73: =BH73 + ABS(BF73) + ABS(BG73) -> 0 | BL73: FALSE | BM73: FALSE | BN73: =(BI73-AZ73)/AZ73 -> #DIV/0! | BO73: =(BH73-AW73)/AW73 -> #DIV/0! | BP73: =BS73 + ABS(BQ73) + ABS(BR73) -> 0 | BW73: FALSE | BX73: FALSE | BY73: =(BT73-BI73)/BI73 -> #DIV/0! | BZ73: =(BS73-BH73)/BH73 -> #DIV/0! | CA73: =CD73 + ABS(CB73) + ABS(CC73) -> 0 | CH73: FALSE | CI73: FALSE | CJ73: =(CE73-BV73)/BV73 -> #DIV/0! | CK73: =(CD73-BS73)/BS73 -> #DIV/0! | CL73: =CO73 + ABS(CM73) + ABS(CN73) -> 0 | CS73: FALSE | CT73: FALSE | CU73: =(CP73-CE73)/CE73 -> #DIV/0! | CV73: =(CO73-CD73)/CD73 -> #DIV/0! | CW73: =CZ73 + ABS(CX73) + ABS(CY73) -> 0 | DD73: FALSE | DE73: FALSE | DF73: =(DA73-CR73)/CR73 -> #DIV/0! | DG73: =(CZ73-CO73)/CO73 -> #DIV/0! | DH73: =DK73 + ABS(DI73) + ABS(DJ73) -> 0 | DO73: FALSE | DP73: FALSE | DQ73: =(DL73-DA73)/DA73 -> #DIV/0! | DR73: =(DK73-CZ73)/CZ73 -> #DIV/0! | DS73: =DV73 + ABS(DT73) + ABS(DU73) -> 0 | DZ73: FALSE | EA73: FALSE | EB73: =(DW73-DN73)/DN73 -> #DIV/0! | EC73: =(DV73-DK73)/DK73 -> #DIV/0! | ED73: =EG73 + ABS(EE73) + ABS(EF73) -> 0 | EK73: FALSE | EL73: FALSE | EM73: =(EH73-DW73)/DW73 -> #DIV/0! | EN73: =(EG73-DV73)/DV73 -> #DIV/0! | EO73: =ER73 + ABS(EP73) + ABS(EQ73) -> 0 | EV73: FALSE | EW73: FALSE | EX73: =(ES73-EJ73)/EJ73 -> #DIV/0! | EY73: =(ER73-EG73)/EG73 -> #DIV/0!
C74: PRESÍDIO DE CAPELINHA | D74: 1450022 | E74: 162 | F74: B20G0015872 | G74: 00117550477 | H74: COMPANHIA DE SANEAMENTO DE MINAS GERAIS COPASA MG | I74: 17.281.106/0001-03 | N74: 107 | P74: 856.69 | R74: 16990.95 | S74: 629 | T74: 1450.01.0005511/2026-51 | X74: =AA74 + ABS(Y74) + ABS(Z74) -> 19723.46 | Y74: -946.73 | Z74: 0 | AA74: 18776.73 | AB74: 691 | AC74: 10/03/2026 | AD74: 1450.01.0029372/2026-78 | AE74: TRUE | AF74: TRUE | AG74: =(AB74-S74)/S74 -> 0.098569157 | AH74: =(AA74-R74)/R74 -> 0.10510183 | AI74: =AL74 + ABS(AJ74) + ABS(AK74) -> 17608.95 | AJ74: -845.23 | AK74: 0 | AL74: 16763.72 | AM74: 600 | AN74: 46122 | AO74: 1450.01.0046622/2026-25 | AP74: TRUE | AQ74: TRUE | AR74: =(AM74-AB74)/AB74 -> -0.1316932 | AS74: =(AL74-AA74)/AA74 -> -0.1072077 | AT74: =AW74 + ABS(AU74) + ABS(AV74) -> 0 | BA74: FALSE | BB74: FALSE | BC74: =(AX74-AM74)/AM74 -> -1 | BD74: =(AW74-AL74)/AL74 -> -1 | BE74: =BH74 + ABS(BF74) + ABS(BG74) -> 0 | BL74: FALSE | BM74: FALSE | BN74: =(BI74-AZ74)/AZ74 -> #DIV/0! | BO74: =(BH74-AW74)/AW74 -> #DIV/0! | BP74: =BS74 + ABS(BQ74) + ABS(BR74) -> 0 | BW74: FALSE | BX74: FALSE | BY74: =(BT74-BI74)/BI74 -> #DIV/0! | BZ74: =(BS74-BH74)/BH74 -> #DIV/0! | CA74: =CD74 + ABS(CB74) + ABS(CC74) -> 0 | CH74: FALSE | CI74: FALSE | CJ74: =(CE74-BV74)/BV74 -> #DIV/0! | CK74: =(CD74-BS74)/BS74 -> #DIV/0! | CL74: =CO74 + ABS(CM74) + ABS(CN74) -> 0 | CS74: FALSE | CT74: FALSE | CU74: =(CP74-CE74)/CE74 -> #DIV/0! | CV74: =(CO74-CD74)/CD74 -> #DIV/0! | CW74: =CZ74 + ABS(CX74) + ABS(CY74) -> 0 | DD74: FALSE | DE74: FALSE | DF74: =(DA74-CR74)/CR74 -> #DIV/0! | DG74: =(CZ74-CO74)/CO74 -> #DIV/0! | DH74: =DK74 + ABS(DI74) + ABS(DJ74) -> 0 | DO74: FALSE | DP74: FALSE | DQ74: =(DL74-DA74)/DA74 -> #DIV/0! | DR74: =(DK74-CZ74)/CZ74 -> #DIV/0! | DS74: =DV74 + ABS(DT74) + ABS(DU74) -> 0 | DZ74: FALSE | EA74: FALSE | EB74: =(DW74-DN74)/DN74 -> #DIV/0! | EC74: =(DV74-DK74)/DK74 -> #DIV/0! | ED74: =EG74 + ABS(EE74) + ABS(EF74) -> 0 | EK74: FALSE | EL74: FALSE | EM74: =(EH74-DW74)/DW74 -> #DIV/0! | EN74: =(EG74-DV74)/DV74 -> #DIV/0! | EO74: =ER74 + ABS(EP74) + ABS(EQ74) -> 0 | EV74: FALSE | EW74: FALSE | EX74: =(ES74-EJ74)/EJ74 -> #DIV/0! | EY74: =(ER74-EG74)/EG74 -> #DIV/0!
C75: PRESÍDIO DE CARANDAI | D75: 1450022 | E75: 366 | F75: Y25S1066727 | G75: 00009975616 | H75: COMPANHIA DE SANEAMENTO DE MINAS GERAIS COPASA MG | I75: 17.281.106/0001-03 | N75: 107 | P75: 3.34 | R75: 66.16 | S75: 7 | T75: 1450.01.0005511/2026-51 | X75: =AA75 + ABS(Y75) + ABS(Z75) -> 69.5 | Y75: -3.34 | Z75: 0 | AA75: 66.16 | AB75: 7 | AC75: 10/03/2026 | AD75: 1450.01.0029372/2026-78 | AE75: TRUE | AF75: TRUE | AG75: =(AB75-S75)/S75 -> 0 | AH75: =(AA75-R75)/R75 -> 0 | AI75: =AL75 + ABS(AJ75) + ABS(AK75) -> 65.45 | AJ75: -3.14 | AK75: 0 | AL75: 62.31 | AM75: 6 | AN75: 46122 | AO75: 1450.01.0046622/2026-25 | AP75: TRUE | AQ75: TRUE | AR75: =(AM75-AB75)/AB75 -> -0.14285714 | AS75: =(AL75-AA75)/AA75 -> -0.058192261 | AT75: =AW75 + ABS(AU75) + ABS(AV75) -> 0 | BA75: FALSE | BB75: FALSE | BC75: =(AX75-AM75)/AM75 -> -1 | BD75: =(AW75-AL75)/AL75 -> -1 | BE75: =BH75 + ABS(BF75) + ABS(BG75) -> 0 | BL75: FALSE | BM75: FALSE | BN75: =(BI75-AZ75)/AZ75 -> #DIV/0! | BO75: =(BH75-AW75)/AW75 -> #DIV/0! | BP75: =BS75 + ABS(BQ75) + ABS(BR75) -> 0 | BW75: FALSE | BX75: FALSE | BY75: =(BT75-BI75)/BI75 -> #DIV/0! | BZ75: =(BS75-BH75)/BH75 -> #DIV/0! | CA75: =CD75 + ABS(CB75) + ABS(CC75) -> 0 | CH75: FALSE | CI75: FALSE | CJ75: =(CE75-BV75)/BV75 -> #DIV/0! | CK75: =(CD75-BS75)/BS75 -> #DIV/0! | CL75: =CO75 + ABS(CM75) + ABS(CN75) -> 0 | CS75: FALSE | CT75: FALSE | CU75: =(CP75-CE75)/CE75 -> #DIV/0! | CV75: =(CO75-CD75)/CD75 -> #DIV/0! | CW75: =CZ75 + ABS(CX75) + ABS(CY75) -> 0 | DD75: FALSE | DE75: FALSE | DF75: =(DA75-CR75)/CR75 -> #DIV/0! | DG75: =(CZ75-CO75)/CO75 -> #DIV/0! | DH75: =DK75 + ABS(DI75) + ABS(DJ75) -> 0 | DO75: FALSE | DP75: FALSE | DQ75: =(DL75-DA75)/DA75 -> #DIV/0! | DR75: =(DK75-CZ75)/CZ75 -> #DIV/0! | DS75: =DV75 + ABS(DT75) + ABS(DU75) -> 0 | DZ75: FALSE | EA75: FALSE | EB75: =(DW75-DN75)/DN75 -> #DIV/0! | EC75: =(DV75-DK75)/DK75 -> #DIV/0! | ED75: =EG75 + ABS(EE75) + ABS(EF75) -> 0 | EK75: FALSE | EL75: FALSE | EM75: =(EH75-DW75)/DW75 -> #DIV/0! | EN75: =(EG75-DV75)/DV75 -> #DIV/0! | EO75: =ER75 + ABS(EP75) + ABS(EQ75) -> 0 | EV75: FALSE | EW75: FALSE | EX75: =(ES75-EJ75)/EJ75 -> #DIV/0! | EY75: =(ER75-EG75)/EG75 -> #DIV/0!
C76: PRESÍDIO DE CARLOS CHAGAS | D76: 1450022 | E76: 359 | F76: B23G0004575 | G76: 00026229714 | H76: COMPANHIA DE SANEAMENTO DE MINAS GERAIS COPASA MG | I76: 17.281.106/0001-03 | N76: 107 | P76: 971.41 | R76: 19266.38 | S76: 708 | T76: 1450.01.0005511/2026-51 | X76: =AA76 + ABS(Y76) + ABS(Z76) -> 19511.67 | Y76: -936.56 | Z76: 0 | AA76: 18575.11 | AB76: 684 | AC76: 10/03/2026 | AD76: 1450.01.0029372/2026-78 | AE76: TRUE | AF76: TRUE | AG76: =(AB76-S76)/S76 -> -0.033898305 | AH76: =(AA76-R76)/R76 -> -0.0358796 | AI76: =AL76 + ABS(AJ76) + ABS(AK76) -> 21803.17 | AJ76: -1046.55 | AK76: 0 | AL76: 20756.62 | AM76: 731 | AN76: 46122 | AO76: 1450.01.0046622/2026-25 | AP76: TRUE | AQ76: TRUE | AR76: =(AM76-AB76)/AB76 -> 0.06871345 | AS76: =(AL76-AA76)/AA76 -> 0.11744264 | AT76: =AW76 + ABS(AU76) + ABS(AV76) -> 0 | BA76: FALSE | BB76: FALSE | BC76: =(AX76-AM76)/AM76 -> -1 | BD76: =(AW76-AL76)/AL76 -> -1 | BE76: =BH76 + ABS(BF76) + ABS(BG76) -> 0 | BL76: FALSE | BM76: FALSE | BN76: =(BI76-AZ76)/AZ76 -> #DIV/0! | BO76: =(BH76-AW76)/AW76 -> #DIV/0! | BP76: =BS76 + ABS(BQ76) + ABS(BR76) -> 0 | BW76: FALSE | BX76: FALSE | BY76: =(BT76-BI76)/BI76 -> #DIV/0! | BZ76: =(BS76-BH76)/BH76 -> #DIV/0! | CA76: =CD76 + ABS(CB76) + ABS(CC76) -> 0 | CH76: FALSE | CI76: FALSE | CJ76: =(CE76-BV76)/BV76 -> #DIV/0! | CK76: =(CD76-BS76)/BS76 -> #DIV/0! | CL76: =CO76 + ABS(CM76) + ABS(CN76) -> 0 | CS76: FALSE | CT76: FALSE | CU76: =(CP76-CE76)/CE76 -> #DIV/0! | CV76: =(CO76-CD76)/CD76 -> #DIV/0! | CW76: =CZ76 + ABS(CX76) + ABS(CY76) -> 0 | DD76: FALSE | DE76: FALSE | DF76: =(DA76-CR76)/CR76 -> #DIV/0! | DG76: =(CZ76-CO76)/CO76 -> #DIV/0! | DH76: =DK76 + ABS(DI76) + ABS(DJ76) -> 0 | DO76: FALSE | DP76: FALSE | DQ76: =(DL76-DA76)/DA76 -> #DIV/0! | DR76: =(DK76-CZ76)/CZ76 -> #DIV/0! | DS76: =DV76 + ABS(DT76) + ABS(DU76) -> 0 | DZ76: FALSE | EA76: FALSE | EB76: =(DW76-DN76)/DN76 -> #DIV/0! | EC76: =(DV76-DK76)/DK76 -> #DIV/0! | ED76: =EG76 + ABS(EE76) + ABS(EF76) -> 0 | EK76: FALSE | EL76: FALSE | EM76: =(EH76-DW76)/DW76 -> #DIV/0! | EN76: =(EG76-DV76)/DV76 -> #DIV/0! | EO76: =ER76 + ABS(EP76) + ABS(EQ76) -> 0 | EV76: FALSE | EW76: FALSE | EX76: =(ES76-EJ76)/EJ76 -> #DIV/0! | EY76: =(ER76-EG76)/EG76 -> #DIV/0!
C77: PRESÍDIO DE CARMO DO RIO CLARO | D77: 1450022 | E77: 351 | F77: Y25L7114317 | G77: 00004509153 | H77: COMPANHIA DE SANEAMENTO DE MINAS GERAIS COPASA MG | I77: 17.281.106/0001-03 | N77: 107 | P77: 2.6 | R77: 51.52 | T77: 1450.01.0005511/2026-51 | X77: =AA77 + ABS(Y77) + ABS(Z77) -> 54.12 | Y77: -2.6 | Z77: 0 | AA77: 51.52 | AB77: 0 | AC77: 10/03/2026 | AD77: 1450.01.0029372/2026-78 | AE77: TRUE | AF77: TRUE | AG77: 0 | AH77: =(AA77-R77)/R77 -> 0 | AI77: =AL77 + ABS(AJ77) + ABS(AK77) -> 62.75 | AJ77: -3.01 | AK77: 0 | AL77: 59.74 | AM77: 0 | AN77: 46122 | AO77: 1450.01.0046622/2026-25 | AP77: TRUE | AQ77: TRUE | AR77: 0 | AS77: =(AL77-AA77)/AA77 -> 0.15954969 | AT77: =AW77 + ABS(AU77) + ABS(AV77) -> 0 | BA77: FALSE | BB77: FALSE | BC77: =(AX77-AM77)/AM77 -> #DIV/0! | BD77: =(AW77-AL77)/AL77 -> -1 | BE77: =BH77 + ABS(BF77) + ABS(BG77) -> 0 | BL77: FALSE | BM77: FALSE | BN77: =(BI77-AZ77)/AZ77 -> #DIV/0! | BO77: =(BH77-AW77)/AW77 -> #DIV/0! | BP77: =BS77 + ABS(BQ77) + ABS(BR77) -> 0 | BW77: FALSE | BX77: FALSE | BY77: =(BT77-BI77)/BI77 -> #DIV/0! | BZ77: =(BS77-BH77)/BH77 -> #DIV/0! | CA77: =CD77 + ABS(CB77) + ABS(CC77) -> 0 | CH77: FALSE | CI77: FALSE | CJ77: =(CE77-BV77)/BV77 -> #DIV/0! | CK77: =(CD77-BS77)/BS77 -> #DIV/0! | CL77: =CO77 + ABS(CM77) + ABS(CN77) -> 0 | CS77: FALSE | CT77: FALSE | CU77: =(CP77-CE77)/CE77 -> #DIV/0! | CV77: =(CO77-CD77)/CD77 -> #DIV/0! | CW77: =CZ77 + ABS(CX77) + ABS(CY77) -> 0 | DD77: FALSE | DE77: FALSE | DF77: =(DA77-CR77)/CR77 -> #DIV/0! | DG77: =(CZ77-CO77)/CO77 -> #DIV/0! | DH77: =DK77 + ABS(DI77) + ABS(DJ77) -> 0 | DO77: FALSE | DP77: FALSE | DQ77: =(DL77-DA77)/DA77 -> #DIV/0! | DR77: =(DK77-CZ77)/CZ77 -> #DIV/0! | DS77: =DV77 + ABS(DT77) + ABS(DU77) -> 0 | DZ77: FALSE | EA77: FALSE | EB77: =(DW77-DN77)/DN77 -> #DIV/0! | EC77: =(DV77-DK77)/DK77 -> #DIV/0! | ED77: =EG77 + ABS(EE77) + ABS(EF77) -> 0 | EK77: FALSE | EL77: FALSE | EM77: =(EH77-DW77)/DW77 -> #DIV/0! | EN77: =(EG77-DV77)/DV77 -> #DIV/0! | EO77: =ER77 + ABS(EP77) + ABS(EQ77) -> 0 | EV77: FALSE | EW77: FALSE | EX77: =(ES77-EJ77)/EJ77 -> #DIV/0! | EY77: =(ER77-EG77)/EG77 -> #DIV/0!
C78: PRESÍDIO DE CATAGUASES | D78: 1450022 | E78: 151 | F78: G23H0000051 | G78: 00026082756 | H78: COMPANHIA DE SANEAMENTO DE MINAS GERAIS COPASA MG | I78: 17.281.106/0001-03 | N78: 107 | P78: 4160.53 | R78: 82517.24 | S78: 2904 | T78: 1450.01.0005511/2026-51 | X78: =AA78 + ABS(Y78) + ABS(Z78) -> 101472.46 | Y78: -4870.68 | Z78: 0 | AA78: 96601.78 | AB78: 3393 | AC78: 10/03/2026 | AD78: 1450.01.0029372/2026-78 | AE78: TRUE | AF78: TRUE | AG78: =(AB78-S78)/S78 -> 0.16838843 | AH78: =(AA78-R78)/R78 -> 0.17068603 | AI78: =AL78 + ABS(AJ78) + ABS(AK78) -> 79663.23 | AJ78: -3823.84 | AK78: 0 | AL78: 75839.39 | AM78: 2611 | AN78: 46122 | AO78: 1450.01.0046622/2026-25 | AP78: TRUE | AQ78: TRUE | AR78: =(AM78-AB78)/AB78 -> -0.23047451 | AS78: =(AL78-AA78)/AA78 -> -0.21492761 | AT78: =AW78 + ABS(AU78) + ABS(AV78) -> 0 | BA78: FALSE | BB78: FALSE | BC78: =(AX78-AM78)/AM78 -> -1 | BD78: =(AW78-AL78)/AL78 -> -1 | BE78: =BH78 + ABS(BF78) + ABS(BG78) -> 0 | BL78: FALSE | BM78: FALSE | BN78: =(BI78-AZ78)/AZ78 -> #DIV/0! | BO78: =(BH78-AW78)/AW78 -> #DIV/0! | BP78: =BS78 + ABS(BQ78) + ABS(BR78) -> 0 | BW78: FALSE | BX78: FALSE | BY78: =(BT78-BI78)/BI78 -> #DIV/0! | BZ78: =(BS78-BH78)/BH78 -> #DIV/0! | CA78: =CD78 + ABS(CB78) + ABS(CC78) -> 0 | CH78: FALSE | CI78: FALSE | CJ78: =(CE78-BV78)/BV78 -> #DIV/0! | CK78: =(CD78-BS78)/BS78 -> #DIV/0! | CL78: =CO78 + ABS(CM78) + ABS(CN78) -> 0 | CS78: FALSE | CT78: FALSE | CU78: =(CP78-CE78)/CE78 -> #DIV/0! | CV78: =(CO78-CD78)/CD78 -> #DIV/0! | CW78: =CZ78 + ABS(CX78) + ABS(CY78) -> 0 | DD78: FALSE | DE78: FALSE | DF78: =(DA78-CR78)/CR78 -> #DIV/0! | DG78: =(CZ78-CO78)/CO78 -> #DIV/0! | DH78: =DK78 + ABS(DI78) + ABS(DJ78) -> 0 | DO78: FALSE | DP78: FALSE | DQ78: =(DL78-DA78)/DA78 -> #DIV/0! | DR78: =(DK78-CZ78)/CZ78 -> #DIV/0! | DS78: =DV78 + ABS(DT78) + ABS(DU78) -> 0 | DZ78: FALSE | EA78: FALSE | EB78: =(DW78-DN78)/DN78 -> #DIV/0! | EC78: =(DV78-DK78)/DK78 -> #DIV/0! | ED78: =EG78 + ABS(EE78) + ABS(EF78) -> 0 | EK78: FALSE | EL78: FALSE | EM78: =(EH78-DW78)/DW78 -> #DIV/0! | EN78: =(EG78-DV78)/DV78 -> #DIV/0! | EO78: =ER78 + ABS(EP78) + ABS(EQ78) -> 0 | EV78: FALSE | EW78: FALSE | EX78: =(ES78-EJ78)/EJ78 -> #DIV/0! | EY78: =(ER78-EG78)/EG78 -> #DIV/0!
C79: PRESÍDIO DE CONGONHAS | D79: 1450022 | E79: 306 | F79: D17B0703976 D17G0703912 | G79: 00108631036 | H79: COMPANHIA DE SANEAMENTO DE MINAS GERAIS COPASA MG | I79: 17.281.106/0001-03 | N79: 107 | P79: 3305.16 | R79: 65552.42 | S79: 2315 | T79: 1450.01.0005511/2026-51 | X79: =AA79 + ABS(Y79) + ABS(Z79) -> 77207.96 | Y79: -3705.98 | Z79: 0 | AA79: 73501.98 | AB79: 2591 | AC79: 10/03/2026 | AD79: 1450.01.0029372/2026-78 | AE79: TRUE | AF79: TRUE | AG79: =(AB79-S79)/S79 -> 0.11922246 | AH79: =(AA79-R79)/R79 -> 0.12127027 | AI79: =AL79 + ABS(AJ79) + ABS(AK79) -> 63532.32 | AJ79: -3049.55 | AK79: 0 | AL79: 60482.77 | AM79: 2060 | AN79: 46122 | AO79: 1450.01.0046622/2026-25 | AP79: TRUE | AQ79: TRUE | AR79: =(AM79-AB79)/AB79 -> -0.20494018 | AS79: =(AL79-AA79)/AA79 -> -0.17712734 | AT79: =AW79 + ABS(AU79) + ABS(AV79) -> 0 | BA79: FALSE | BB79: FALSE | BC79: =(AX79-AM79)/AM79 -> -1 | BD79: =(AW79-AL79)/AL79 -> -1 | BE79: =BH79 + ABS(BF79) + ABS(BG79) -> 0 | BL79: FALSE | BM79: FALSE | BN79: =(BI79-AZ79)/AZ79 -> #DIV/0! | BO79: =(BH79-AW79)/AW79 -> #DIV/0! | BP79: =BS79 + ABS(BQ79) + ABS(BR79) -> 0 | BW79: FALSE | BX79: FALSE | BY79: =(BT79-BI79)/BI79 -> #DIV/0! | BZ79: =(BS79-BH79)/BH79 -> #DIV/0! | CA79: =CD79 + ABS(CB79) + ABS(CC79) -> 0 | CH79: FALSE | CI79: FALSE | CJ79: =(CE79-BV79)/BV79 -> #DIV/0! | CK79: =(CD79-BS79)/BS79 -> #DIV/0! | CL79: =CO79 + ABS(CM79) + ABS(CN79) -> 0 | CS79: FALSE | CT79: FALSE | CU79: =(CP79-CE79)/CE79 -> #DIV/0! | CV79: =(CO79-CD79)/CD79 -> #DIV/0! | CW79: =CZ79 + ABS(CX79) + ABS(CY79) -> 0 | DD79: FALSE | DE79: FALSE | DF79: =(DA79-CR79)/CR79 -> #DIV/0! | DG79: =(CZ79-CO79)/CO79 -> #DIV/0! | DH79: =DK79 + ABS(DI79) + ABS(DJ79) -> 0 | DO79: FALSE | DP79: FALSE | DQ79: =(DL79-DA79)/DA79 -> #DIV/0! | DR79: =(DK79-CZ79)/CZ79 -> #DIV/0! | DS79: =DV79 + ABS(DT79) + ABS(DU79) -> 0 | DZ79: FALSE | EA79: FALSE | EB79: =(DW79-DN79)/DN79 -> #DIV/0! | EC79: =(DV79-DK79)/DK79 -> #DIV/0! | ED79: =EG79 + ABS(EE79) + ABS(EF79) -> 0 | EK79: FALSE | EL79: FALSE | EM79: =(EH79-DW79)/DW79 -> #DIV/0! | EN79: =(EG79-DV79)/DV79 -> #DIV/0! | EO79: =ER79 + ABS(EP79) + ABS(EQ79) -> 0 | EV79: FALSE | EW79: FALSE | EX79: =(ES79-EJ79)/EJ79 -> #DIV/0! | EY79: =(ER79-EG79)/EG79 -> #DIV/0!
C80: PRESÍDIO DE CONSELHEIRO LAFAIETE | D80: 1450022 | E80: 116 | F80: E17B0791216 | G80: 00014749564 | H80: COMPANHIA DE SANEAMENTO DE MINAS GERAIS COPASA MG | I80: 17.281.106/0001-03 | N80: 107 | P80: 2204.37 | R80: 43719.92 | S80: 1557 | T80: 1450.01.0005511/2026-51 | X80: =AA80 + ABS(Y80) + ABS(Z80) -> 48284.18 | Y80: -2317.64 | Z80: 0 | AA80: 45966.54 | AB80: 1635 | AC80: 10/03/2026 | AD80: 1450.01.0029372/2026-78 | AE80: TRUE | AF80: TRUE | AG80: =(AB80-S80)/S80 -> 0.050096339 | AH80: =(AA80-R80)/R80 -> 0.051386645 | AI80: =AL80 + ABS(AJ80) + ABS(AK80) -> 38826 | AJ80: -1863.65 | AK80: 0 | AL80: 36962.35 | AM80: 1266 | AN80: 46122 | AO80: 1450.01.0046622/2026-25 | AP80: TRUE | AQ80: TRUE | AR80: =(AM80-AB80)/AB80 -> -0.22568807 | AS80: =(AL80-AA80)/AA80 -> -0.19588575 | AT80: =AW80 + ABS(AU80) + ABS(AV80) -> 0 | BA80: FALSE | BB80: FALSE | BC80: =(AX80-AM80)/AM80 -> -1 | BD80: =(AW80-AL80)/AL80 -> -1 | BE80: =BH80 + ABS(BF80) + ABS(BG80) -> 0 | BL80: FALSE | BM80: FALSE | BN80: =(BI80-AZ80)/AZ80 -> #DIV/0! | BO80: =(BH80-AW80)/AW80 -> #DIV/0! | BP80: =BS80 + ABS(BQ80) + ABS(BR80) -> 0 | BW80: FALSE | BX80: FALSE | BY80: =(BT80-BI80)/BI80 -> #DIV/0! | BZ80: =(BS80-BH80)/BH80 -> #DIV/0! | CA80: =CD80 + ABS(CB80) + ABS(CC80) -> 0 | CH80: FALSE | CI80: FALSE | CJ80: =(CE80-BV80)/BV80 -> #DIV/0! | CK80: =(CD80-BS80)/BS80 -> #DIV/0! | CL80: =CO80 + ABS(CM80) + ABS(CN80) -> 0 | CS80: FALSE | CT80: FALSE | CU80: =(CP80-CE80)/CE80 -> #DIV/0! | CV80: =(CO80-CD80)/CD80 -> #DIV/0! | CW80: =CZ80 + ABS(CX80) + ABS(CY80) -> 0 | DD80: FALSE | DE80: FALSE | DF80: =(DA80-CR80)/CR80 -> #DIV/0! | DG80: =(CZ80-CO80)/CO80 -> #DIV/0! | DH80: =DK80 + ABS(DI80) + ABS(DJ80) -> 0 | DO80: FALSE | DP80: FALSE | DQ80: =(DL80-DA80)/DA80 -> #DIV/0! | DR80: =(DK80-CZ80)/CZ80 -> #DIV/0! | DS80: =DV80 + ABS(DT80) + ABS(DU80) -> 0 | DZ80: FALSE | EA80: FALSE | EB80: =(DW80-DN80)/DN80 -> #DIV/0! | EC80: =(DV80-DK80)/DK80 -> #DIV/0! | ED80: =EG80 + ABS(EE80) + ABS(EF80) -> 0 | EK80: FALSE | EL80: FALSE | EM80: =(EH80-DW80)/DW80 -> #DIV/0! | EN80: =(EG80-DV80)/DV80 -> #DIV/0! | EO80: =ER80 + ABS(EP80) + ABS(EQ80) -> 0 | EV80: FALSE | EW80: FALSE | EX80: =(ES80-EJ80)/EJ80 -> #DIV/0! | EY80: =(ER80-EG80)/EG80 -> #DIV/0!
C81: PRESÍDIO DE CORINTO | D81: 1450022 | E81: 328 | F81: B17B0702733 | G81: 00006290965 | H81: COMPANHIA DE SANEAMENTO DE MINAS GERAIS COPASA MG | I81: 17.281.106/0001-03 | N81: 107 | P81: 1128.26 | R81: 22377.07 | S81: 816 | T81: 1450.01.0005511/2026-51 | X81: =AA81 + ABS(Y81) + ABS(Z81) -> 25664.14 | Y81: -1231.88 | Z81: 0 | AA81: 24432.26 | AB81: 886 | AC81: 10/03/2026 | AD81: 1450.01.0029372/2026-78 | AE81: TRUE | AF81: TRUE | AG81: =(AB81-S81)/S81 -> 0.085784314 | AH81: =(AA81-R81)/R81 -> 0.09184357 | AI81: =AL81 + ABS(AJ81) + ABS(AK81) -> 26287.19 | AJ81: -1261.79 | AK81: 0 | AL81: 25025.4 | AM81: 867 | AN81: 46122 | AO81: 1450.01.0046622/2026-25 | AP81: TRUE | AQ81: TRUE | AR81: =(AM81-AB81)/AB81 -> -0.021444695 | AS81: =(AL81-AA81)/AA81 -> 0.024276919 | AT81: =AW81 + ABS(AU81) + ABS(AV81) -> 0 | BA81: FALSE | BB81: FALSE | BC81: =(AX81-AM81)/AM81 -> -1 | BD81: =(AW81-AL81)/AL81 -> -1 | BE81: =BH81 + ABS(BF81) + ABS(BG81) -> 0 | BL81: FALSE | BM81: FALSE | BN81: =(BI81-AZ81)/AZ81 -> #DIV/0! | BO81: =(BH81-AW81)/AW81 -> #DIV/0! | BP81: =BS81 + ABS(BQ81) + ABS(BR81) -> 0 | BW81: FALSE | BX81: FALSE | BY81: =(BT81-BI81)/BI81 -> #DIV/0! | BZ81: =(BS81-BH81)/BH81 -> #DIV/0! | CA81: =CD81 + ABS(CB81) + ABS(CC81) -> 0 | CH81: FALSE | CI81: FALSE | CJ81: =(CE81-BV81)/BV81 -> #DIV/0! | CK81: =(CD81-BS81)/BS81 -> #DIV/0! | CL81: =CO81 + ABS(CM81) + ABS(CN81) -> 0 | CS81: FALSE | CT81: FALSE | CU81: =(CP81-CE81)/CE81 -> #DIV/0! | CV81: =(CO81-CD81)/CD81 -> #DIV/0! | CW81: =CZ81 + ABS(CX81) + ABS(CY81) -> 0 | DD81: FALSE | DE81: FALSE | DF81: =(DA81-CR81)/CR81 -> #DIV/0! | DG81: =(CZ81-CO81)/CO81 -> #DIV/0! | DH81: =DK81 + ABS(DI81) + ABS(DJ81) -> 0 | DO81: FALSE | DP81: FALSE | DQ81: =(DL81-DA81)/DA81 -> #DIV/0! | DR81: =(DK81-CZ81)/CZ81 -> #DIV/0! | DS81: =DV81 + ABS(DT81) + ABS(DU81) -> 0 | DZ81: FALSE | EA81: FALSE | EB81: =(DW81-DN81)/DN81 -> #DIV/0! | EC81: =(DV81-DK81)/DK81 -> #DIV/0! | ED81: =EG81 + ABS(EE81) + ABS(EF81) -> 0 | EK81: FALSE | EL81: FALSE | EM81: =(EH81-DW81)/DW81 -> #DIV/0! | EN81: =(EG81-DV81)/DV81 -> #DIV/0! | EO81: =ER81 + ABS(EP81) + ABS(EQ81) -> 0 | EV81: FALSE | EW81: FALSE | EX81: =(ES81-EJ81)/EJ81 -> #DIV/0! | EY81: =(ER81-EG81)/EG81 -> #DIV/0!
C82: PRESÍDIO DE COROMANDEL 1 | D82: 1450022 | E82: 100 | F82: B18F0008499 | G82: 00005940389 | H82: COMPANHIA DE SANEAMENTO DE MINAS GERAIS COPASA MG | I82: 17.281.106/0001-03 | N82: 107 | P82: 311.23 | R82: 6172.63 | S82: 412 | T82: 1450.01.0005511/2026-51 | X82: =AA82 + ABS(Y82) + ABS(Z82) -> 5405.87 | Y82: -259.48 | Z82: 0 | AA82: 5146.39 | AB82: 350 | AC82: 10/03/2026 | AD82: 1450.01.0029372/2026-78 | AE82: TRUE | AF82: TRUE | AG82: =(AB82-S82)/S82 -> -0.15048544 | AH82: =(AA82-R82)/R82 -> -0.16625652 | AI82: =AL82 + ABS(AJ82) + ABS(AK82) -> 7512.5 | AJ82: -360.6 | AK82: 0 | AL82: 7151.9 | AM82: 452 | AN82: 46122 | AO82: 1450.01.0046622/2026-25 | AP82: TRUE | AQ82: TRUE | AR82: =(AM82-AB82)/AB82 -> 0.29142857 | AS82: =(AL82-AA82)/AA82 -> 0.38969258 | AT82: =AW82 + ABS(AU82) + ABS(AV82) -> 0 | BA82: FALSE | BB82: FALSE | BC82: =(AX82-AM82)/AM82 -> -1 | BD82: =(AW82-AL82)/AL82 -> -1 | BE82: =BH82 + ABS(BF82) + ABS(BG82) -> 0 | BL82: FALSE | BM82: FALSE | BN82: =(BI82-AZ82)/AZ82 -> #DIV/0! | BO82: =(BH82-AW82)/AW82 -> #DIV/0! | BP82: =BS82 + ABS(BQ82) + ABS(BR82) -> 0 | BW82: FALSE | BX82: FALSE | BY82: =(BT82-BI82)/BI82 -> #DIV/0! | BZ82: =(BS82-BH82)/BH82 -> #DIV/0! | CA82: =CD82 + ABS(CB82) + ABS(CC82) -> 0 | CH82: FALSE | CI82: FALSE | CJ82: =(CE82-BV82)/BV82 -> #DIV/0! | CK82: =(CD82-BS82)/BS82 -> #DIV/0! | CL82: =CO82 + ABS(CM82) + ABS(CN82) -> 0 | CS82: FALSE | CT82: FALSE | CU82: =(CP82-CE82)/CE82 -> #DIV/0! | CV82: =(CO82-CD82)/CD82 -> #DIV/0! | CW82: =CZ82 + ABS(CX82) + ABS(CY82) -> 0 | DD82: FALSE | DE82: FALSE | DF82: =(DA82-CR82)/CR82 -> #DIV/0! | DG82: =(CZ82-CO82)/CO82 -> #DIV/0! | DH82: =DK82 + ABS(DI82) + ABS(DJ82) -> 0 | DO82: FALSE | DP82: FALSE | DQ82: =(DL82-DA82)/DA82 -> #DIV/0! | DR82: =(DK82-CZ82)/CZ82 -> #DIV/0! | DS82: =DV82 + ABS(DT82) + ABS(DU82) -> 0 | DZ82: FALSE | EA82: FALSE | EB82: =(DW82-DN82)/DN82 -> #DIV/0! | EC82: =(DV82-DK82)/DK82 -> #DIV/0! | ED82: =EG82 + ABS(EE82) + ABS(EF82) -> 0 | EK82: FALSE | EL82: FALSE | EM82: =(EH82-DW82)/DW82 -> #DIV/0! | EN82: =(EG82-DV82)/DV82 -> #DIV/0! | EO82: =ER82 + ABS(EP82) + ABS(EQ82) -> 0 | EV82: FALSE | EW82: FALSE | EX82: =(ES82-EJ82)/EJ82 -> #DIV/0! | EY82: =(ER82-EG82)/EG82 -> #DIV/0!
C83: PRESÍDIO DE COROMANDEL 2 | D83: 1450022 | E83: 100 | F83: D17B7000870 | G83: 00005940168 | H83: COMPANHIA DE SANEAMENTO DE MINAS GERAIS COPASA MG | I83: 17.281.106/0001-03 | N83: 107 | P83: 683.45 | R83: 13555.02 | S83: 858 | T83: 1450.01.0005511/2026-51 | X83: =AA83 + ABS(Y83) + ABS(Z83) -> 15542.49 | Y83: -746.04 | Z83: 0 | AA83: 14796.45 | AB83: 933 | AC83: 10/03/2026 | AD83: 1450.01.0029372/2026-78 | AE83: TRUE | AF83: TRUE | AG83: =(AB83-S83)/S83 -> 0.087412587 | AH83: =(AA83-R83)/R83 -> 0.09158452 | AI83: =AL83 + ABS(AJ83) + ABS(AK83) -> 4275.91 | AJ83: -205.24 | AK83: 0 | AL83: 4070.67 | AM83: 274 | AN83: 46122 | AO83: 1450.01.0046622/2026-25 | AP83: TRUE | AQ83: TRUE | AR83: =(AM83-AB83)/AB83 -> -0.70632369 | AS83: =(AL83-AA83)/AA83 -> -0.72488874 | AT83: =AW83 + ABS(AU83) + ABS(AV83) -> 0 | BA83: FALSE | BB83: FALSE | BC83: =(AX83-AM83)/AM83 -> -1 | BD83: =(AW83-AL83)/AL83 -> -1 | BE83: =BH83 + ABS(BF83) + ABS(BG83) -> 0 | BL83: FALSE | BM83: FALSE | BN83: =(BI83-AZ83)/AZ83 -> #DIV/0! | BO83: =(BH83-AW83)/AW83 -> #DIV/0! | BP83: =BS83 + ABS(BQ83) + ABS(BR83) -> 0 | BW83: FALSE | BX83: FALSE | BY83: =(BT83-BI83)/BI83 -> #DIV/0! | BZ83: =(BS83-BH83)/BH83 -> #DIV/0! | CA83: =CD83 + ABS(CB83) + ABS(CC83) -> 0 | CH83: FALSE | CI83: FALSE | CJ83: =(CE83-BV83)/BV83 -> #DIV/0! | CK83: =(CD83-BS83)/BS83 -> #DIV/0! | CL83: =CO83 + ABS(CM83) + ABS(CN83) -> 0 | CS83: FALSE | CT83: FALSE | CU83: =(CP83-CE83)/CE83 -> #DIV/0! | CV83: =(CO83-CD83)/CD83 -> #DIV/0! | CW83: =CZ83 + ABS(CX83) + ABS(CY83) -> 0 | DD83: FALSE | DE83: FALSE | DF83: =(DA83-CR83)/CR83 -> #DIV/0! | DG83: =(CZ83-CO83)/CO83 -> #DIV/0! | DH83: =DK83 + ABS(DI83) + ABS(DJ83) -> 0 | DO83: FALSE | DP83: FALSE | DQ83: =(DL83-DA83)/DA83 -> #DIV/0! | DR83: =(DK83-CZ83)/CZ83 -> #DIV/0! | DS83: =DV83 + ABS(DT83) + ABS(DU83) -> 0 | DZ83: FALSE | EA83: FALSE | EB83: =(DW83-DN83)/DN83 -> #DIV/0! | EC83: =(DV83-DK83)/DK83 -> #DIV/0! | ED83: =EG83 + ABS(EE83) + ABS(EF83) -> 0 | EK83: FALSE | EL83: FALSE | EM83: =(EH83-DW83)/DW83 -> #DIV/0! | EN83: =(EG83-DV83)/DV83 -> #DIV/0! | EO83: =ER83 + ABS(EP83) + ABS(EQ83) -> 0 | EV83: FALSE | EW83: FALSE | EX83: =(ES83-EJ83)/EJ83 -> #DIV/0! | EY83: =(ER83-EG83)/EG83 -> #DIV/0!
C84: PRESÍDIO DE COROMANDEL 3 | D84: 1450022 | E84: 100 | F84: B18F0008497 | G84: 00005940397 | H84: COMPANHIA DE SANEAMENTO DE MINAS GERAIS COPASA MG | I84: 17.281.106/0001-03 | N84: 107 | P84: 138.47 | R84: 2746.29 | S84: 205 | T84: 1450.01.0005511/2026-51 | X84: =AA84 + ABS(Y84) + ABS(Z84) -> 7266.28 | Y84: -348.78 | Z84: 0 | AA84: 6917.5 | AB84: 457 | AC84: 10/03/2026 | AD84: 1450.01.0029372/2026-78 | AE84: TRUE | AF84: TRUE | AG84: =(AB84-S84)/S84 -> 1.2292683 | AH84: =(AA84-R84)/R84 -> 1.5188527 | AI84: =AL84 + ABS(AJ84) + ABS(AK84) -> 9530.82 | AJ84: -457.48 | AK84: 0 | AL84: 9073.34 | AM84: 563 | AN84: 46122 | AO84: 1450.01.0046622/2026-25 | AP84: TRUE | AQ84: TRUE | AR84: =(AM84-AB84)/AB84 -> 0.23194748 | AS84: =(AL84-AA84)/AA84 -> 0.31165016 | AT84: =AW84 + ABS(AU84) + ABS(AV84) -> 0 | BA84: FALSE | BB84: FALSE | BC84: =(AX84-AM84)/AM84 -> -1 | BD84: =(AW84-AL84)/AL84 -> -1 | BE84: =BH84 + ABS(BF84) + ABS(BG84) -> 0 | BL84: FALSE | BM84: FALSE | BN84: =(BI84-AZ84)/AZ84 -> #DIV/0! | BO84: =(BH84-AW84)/AW84 -> #DIV/0! | BP84: =BS84 + ABS(BQ84) + ABS(BR84) -> 0 | BW84: FALSE | BX84: FALSE | BY84: =(BT84-BI84)/BI84 -> #DIV/0! | BZ84: =(BS84-BH84)/BH84 -> #DIV/0! | CA84: =CD84 + ABS(CB84) + ABS(CC84) -> 0 | CH84: FALSE | CI84: FALSE | CJ84: =(CE84-BV84)/BV84 -> #DIV/0! | CK84: =(CD84-BS84)/BS84 -> #DIV/0! | CL84: =CO84 + ABS(CM84) + ABS(CN84) -> 0 | CS84: FALSE | CT84: FALSE | CU84: =(CP84-CE84)/CE84 -> #DIV/0! | CV84: =(CO84-CD84)/CD84 -> #DIV/0! | CW84: =CZ84 + ABS(CX84) + ABS(CY84) -> 0 | DD84: FALSE | DE84: FALSE | DF84: =(DA84-CR84)/CR84 -> #DIV/0! | DG84: =(CZ84-CO84)/CO84 -> #DIV/0! | DH84: =DK84 + ABS(DI84) + ABS(DJ84) -> 0 | DO84: FALSE | DP84: FALSE | DQ84: =(DL84-DA84)/DA84 -> #DIV/0! | DR84: =(DK84-CZ84)/CZ84 -> #DIV/0! | DS84: =DV84 + ABS(DT84) + ABS(DU84) -> 0 | DZ84: FALSE | EA84: FALSE | EB84: =(DW84-DN84)/DN84 -> #DIV/0! | EC84: =(DV84-DK84)/DK84 -> #DIV/0! | ED84: =EG84 + ABS(EE84) + ABS(EF84) -> 0 | EK84: FALSE | EL84: FALSE | EM84: =(EH84-DW84)/DW84 -> #DIV/0! | EN84: =(EG84-DV84)/DV84 -> #DIV/0! | EO84: =ER84 + ABS(EP84) + ABS(EQ84) -> 0 | EV84: FALSE | EW84: FALSE | EX84: =(ES84-EJ84)/EJ84 -> #DIV/0! | EY84: =(ER84-EG84)/EG84 -> #DIV/0!
C85: PRESÍDIO DE CORONEL FABRICIANO | D85: 1450022 | E85: 77 | F85: F15H0000381 | G85: 00114745943 | H85: COMPANHIA DE SANEAMENTO DE MINAS GERAIS COPASA MG | I85: 17.281.106/0001-03 | N85: 107 | P85: 5830.61 | R85: 115640.41 | S85: 4054 | T85: 1450.01.0005511/2026-51 | X85: =AA85 + ABS(Y85) + ABS(Z85) -> 147460.06 | Y85: -7078.08 | Z85: 0 | AA85: 140381.98 | AB85: 4913 | AC85: 10/03/2026 | AD85: 1450.01.0029372/2026-78 | AE85: TRUE | AF85: TRUE | AG85: =(AB85-S85)/S85 -> 0.21188949 | AH85: =(AA85-R85)/R85 -> 0.21395263 | AI85: =AL85 + ABS(AJ85) + ABS(AK85) -> 122534.86 | AJ85: -5881.67 | AK85: 0 | AL85: 116653.19 | AM85: 3937 | AN85: 46122 | AO85: 1450.01.0046622/2026-25 | AP85: TRUE | AQ85: TRUE | AR85: =(AM85-AB85)/AB85 -> -0.19865663 | AS85: =(AL85-AA85)/AA85 -> -0.16903017 | AT85: =AW85 + ABS(AU85) + ABS(AV85) -> 0 | BA85: FALSE | BB85: FALSE | BC85: =(AX85-AM85)/AM85 -> -1 | BD85: =(AW85-AL85)/AL85 -> -1 | BE85: =BH85 + ABS(BF85) + ABS(BG85) -> 0 | BL85: FALSE | BM85: FALSE | BN85: =(BI85-AZ85)/AZ85 -> #DIV/0! | BO85: =(BH85-AW85)/AW85 -> #DIV/0! | BP85: =BS85 + ABS(BQ85) + ABS(BR85) -> 0 | BW85: FALSE | BX85: FALSE | BY85: =(BT85-BI85)/BI85 -> #DIV/0! | BZ85: =(BS85-BH85)/BH85 -> #DIV/0! | CA85: =CD85 + ABS(CB85) + ABS(CC85) -> 0 | CH85: FALSE | CI85: FALSE | CJ85: =(CE85-BV85)/BV85 -> #DIV/0! | CK85: =(CD85-BS85)/BS85 -> #DIV/0! | CL85: =CO85 + ABS(CM85) + ABS(CN85) -> 0 | CS85: FALSE | CT85: FALSE | CU85: =(CP85-CE85)/CE85 -> #DIV/0! | CV85: =(CO85-CD85)/CD85 -> #DIV/0! | CW85: =CZ85 + ABS(CX85) + ABS(CY85) -> 0 | DD85: FALSE | DE85: FALSE | DF85: =(DA85-CR85)/CR85 -> #DIV/0! | DG85: =(CZ85-CO85)/CO85 -> #DIV/0! | DH85: =DK85 + ABS(DI85) + ABS(DJ85) -> 0 | DO85: FALSE | DP85: FALSE | DQ85: =(DL85-DA85)/DA85 -> #DIV/0! | DR85: =(DK85-CZ85)/CZ85 -> #DIV/0! | DS85: =DV85 + ABS(DT85) + ABS(DU85) -> 0 | DZ85: FALSE | EA85: FALSE | EB85: =(DW85-DN85)/DN85 -> #DIV/0! | EC85: =(DV85-DK85)/DK85 -> #DIV/0! | ED85: =EG85 + ABS(EE85) + ABS(EF85) -> 0 | EK85: FALSE | EL85: FALSE | EM85: =(EH85-DW85)/DW85 -> #DIV/0! | EN85: =(EG85-DV85)/DV85 -> #DIV/0! | EO85: =ER85 + ABS(EP85) + ABS(EQ85) -> 0 | EV85: FALSE | EW85: FALSE | EX85: =(ES85-EJ85)/EJ85 -> #DIV/0! | EY85: =(ER85-EG85)/EG85 -> #DIV/0!
C86: PRESÍDIO DE CURVELO | D86: 1450022 | E86: 114 | F86: A15F0035899 B19F0000505 | G86: 00006365027 | H86: COMPANHIA DE SANEAMENTO DE MINAS GERAIS COPASA MG | I86: 17.281.106/0001-03 | N86: 107 | P86: 2382.99 | R86: 47262.66 | S86: 1680 | T86: 1450.01.0005511/2026-51 | X86: =AA86 + ABS(Y86) + ABS(Z86) -> 55000.79 | Y86: -2640.04 | Z86: 0 | AA86: 52360.75 | AB86: 1857 | AC86: 10/03/2026 | AD86: 1450.01.0029372/2026-78 | AE86: TRUE | AF86: TRUE | AG86: =(AB86-S86)/S86 -> 0.10535714 | AH86: =(AA86-R86)/R86 -> 0.10786718 | AI86: =AL86 + ABS(AJ86) + ABS(AK86) -> 26104.85 | AJ86: -1253.03 | AK86: 0 | AL86: 24851.82 | AM86: 879 | AN86: 46122 | AO86: 1450.01.0046622/2026-25 | AP86: TRUE | AQ86: TRUE | AR86: =(AM86-AB86)/AB86 -> -0.5266559 | AS86: =(AL86-AA86)/AA86 -> -0.52537311 | AT86: =AW86 + ABS(AU86) + ABS(AV86) -> 0 | BA86: FALSE | BB86: FALSE | BC86: =(AX86-AM86)/AM86 -> -1 | BD86: =(AW86-AL86)/AL86 -> -1 | BE86: =BH86 + ABS(BF86) + ABS(BG86) -> 0 | BL86: FALSE | BM86: FALSE | BN86: =(BI86-AZ86)/AZ86 -> #DIV/0! | BO86: =(BH86-AW86)/AW86 -> #DIV/0! | BP86: =BS86 + ABS(BQ86) + ABS(BR86) -> 0 | BW86: FALSE | BX86: FALSE | BY86: =(BT86-BI86)/BI86 -> #DIV/0! | BZ86: =(BS86-BH86)/BH86 -> #DIV/0! | CA86: =CD86 + ABS(CB86) + ABS(CC86) -> 0 | CH86: FALSE | CI86: FALSE | CJ86: =(CE86-BV86)/BV86 -> #DIV/0! | CK86: =(CD86-BS86)/BS86 -> #DIV/0! | CL86: =CO86 + ABS(CM86) + ABS(CN86) -> 0 | CS86: FALSE | CT86: FALSE | CU86: =(CP86-CE86)/CE86 -> #DIV/0! | CV86: =(CO86-CD86)/CD86 -> #DIV/0! | CW86: =CZ86 + ABS(CX86) + ABS(CY86) -> 0 | DD86: FALSE | DE86: FALSE | DF86: =(DA86-CR86)/CR86 -> #DIV/0! | DG86: =(CZ86-CO86)/CO86 -> #DIV/0! | DH86: =DK86 + ABS(DI86) + ABS(DJ86) -> 0 | DO86: FALSE | DP86: FALSE | DQ86: =(DL86-DA86)/DA86 -> #DIV/0! | DR86: =(DK86-CZ86)/CZ86 -> #DIV/0! | DS86: =DV86 + ABS(DT86) + ABS(DU86) -> 0 | DZ86: FALSE | EA86: FALSE | EB86: =(DW86-DN86)/DN86 -> #DIV/0! | EC86: =(DV86-DK86)/DK86 -> #DIV/0! | ED86: =EG86 + ABS(EE86) + ABS(EF86) -> 0 | EK86: FALSE | EL86: FALSE | EM86: =(EH86-DW86)/DW86 -> #DIV/0! | EN86: =(EG86-DV86)/DV86 -> #DIV/0! | EO86: =ER86 + ABS(EP86) + ABS(EQ86) -> 0 | EV86: FALSE | EW86: FALSE | EX86: =(ES86-EJ86)/EJ86 -> #DIV/0! | EY86: =(ER86-EG86)/EG86 -> #DIV/0!
C87: PRESÍDIO DE DIAMANTINA | D87: 1450022 | E87: 217 | F87: D18B0704211 | G87: 00023190744 | H87: COMPANHIA DE SANEAMENTO DE MINAS GERAIS COPASA MG | I87: 17.281.106/0001-03 | N87: 107 | P87: 1356.26 | R87: 26899.1 | S87: 973 | T87: 1450.01.0005511/2026-51 | X87: =AA87 + ABS(Y87) + ABS(Z87) -> 35637.59 | Y87: -1710.6 | Z87: 0 | AA87: 33926.99 | AB87: 1217 | AC87: 10/03/2026 | AD87: 1450.01.0029372/2026-78 | AE87: TRUE | AF87: TRUE | AG87: =(AB87-S87)/S87 -> 0.25077081 | AH87: =(AA87-R87)/R87 -> 0.26126859 | AI87: =AL87 + ABS(AJ87) + ABS(AK87) -> 39801.54 | AJ87: -1910.47 | AK87: 0 | AL87: 37891.07 | AM87: 1316 | AN87: 46122 | AO87: 1450.01.0046622/2026-25 | AP87: TRUE | AQ87: TRUE | AR87: =(AM87-AB87)/AB87 -> 0.081347576 | AS87: =(AL87-AA87)/AA87 -> 0.11684149 | AT87: =AW87 + ABS(AU87) + ABS(AV87) -> 0 | BA87: FALSE | BB87: FALSE | BC87: =(AX87-AM87)/AM87 -> -1 | BD87: =(AW87-AL87)/AL87 -> -1 | BE87: =BH87 + ABS(BF87) + ABS(BG87) -> 0 | BL87: FALSE | BM87: FALSE | BN87: =(BI87-AZ87)/AZ87 -> #DIV/0! | BO87: =(BH87-AW87)/AW87 -> #DIV/0! | BP87: =BS87 + ABS(BQ87) + ABS(BR87) -> 0 | BW87: FALSE | BX87: FALSE | BY87: =(BT87-BI87)/BI87 -> #DIV/0! | BZ87: =(BS87-BH87)/BH87 -> #DIV/0! | CA87: =CD87 + ABS(CB87) + ABS(CC87) -> 0 | CH87: FALSE | CI87: FALSE | CJ87: =(CE87-BV87)/BV87 -> #DIV/0! | CK87: =(CD87-BS87)/BS87 -> #DIV/0! | CL87: =CO87 + ABS(CM87) + ABS(CN87) -> 0 | CS87: FALSE | CT87: FALSE | CU87: =(CP87-CE87)/CE87 -> #DIV/0! | CV87: =(CO87-CD87)/CD87 -> #DIV/0! | CW87: =CZ87 + ABS(CX87) + ABS(CY87) -> 0 | DD87: FALSE | DE87: FALSE | DF87: =(DA87-CR87)/CR87 -> #DIV/0! | DG87: =(CZ87-CO87)/CO87 -> #DIV/0! | DH87: =DK87 + ABS(DI87) + ABS(DJ87) -> 0 | DO87: FALSE | DP87: FALSE | DQ87: =(DL87-DA87)/DA87 -> #DIV/0! | DR87: =(DK87-CZ87)/CZ87 -> #DIV/0! | DS87: =DV87 + ABS(DT87) + ABS(DU87) -> 0 | DZ87: FALSE | EA87: FALSE | EB87: =(DW87-DN87)/DN87 -> #DIV/0! | EC87: =(DV87-DK87)/DK87 -> #DIV/0! | ED87: =EG87 + ABS(EE87) + ABS(EF87) -> 0 | EK87: FALSE | EL87: FALSE | EM87: =(EH87-DW87)/DW87 -> #DIV/0! | EN87: =(EG87-DV87)/DV87 -> #DIV/0! | EO87: =ER87 + ABS(EP87) + ABS(EQ87) -> 0 | EV87: FALSE | EW87: FALSE | EX87: =(ES87-EJ87)/EJ87 -> #DIV/0! | EY87: =(ER87-EG87)/EG87 -> #DIV/0!
C88: PRESÍDIO DE DIVINO | D88: 1450022 | E88: 362 | F88: Y25S1242901 | G88: 00012144959 | H88: COMPANHIA DE SANEAMENTO DE MINAS GERAIS COPASA MG | I88: 17.281.106/0001-03 | N88: 107 | P88: 5.2 | R88: 103.15 | S88: 6 | T88: 1450.01.0005511/2026-51 | X88: =AA88 + ABS(Y88) + ABS(Z88) -> 121.7 | Y88: -5.84 | Z88: 0 | AA88: 115.86 | AB88: 7 | AC88: 10/03/2026 | AD88: 1450.01.0029372/2026-78 | AE88: TRUE | AF88: TRUE | AG88: =(AB88-S88)/S88 -> 0.16666667 | AH88: =(AA88-R88)/R88 -> 0.12321861 | AI88: =AL88 + ABS(AJ88) + ABS(AK88) -> 98.63 | AJ88: -4.73 | AK88: 0 | AL88: 93.9 | AM88: 4 | AN88: 46122 | AO88: 1450.01.0046622/2026-25 | AP88: TRUE | AQ88: TRUE | AR88: =(AM88-AB88)/AB88 -> -0.42857143 | AS88: =(AL88-AA88)/AA88 -> -0.1895391 | AT88: =AW88 + ABS(AU88) + ABS(AV88) -> 0 | BA88: FALSE | BB88: FALSE | BC88: =(AX88-AM88)/AM88 -> -1 | BD88: =(AW88-AL88)/AL88 -> -1 | BE88: =BH88 + ABS(BF88) + ABS(BG88) -> 0 | BL88: FALSE | BM88: FALSE | BN88: =(BI88-AZ88)/AZ88 -> #DIV/0! | BO88: =(BH88-AW88)/AW88 -> #DIV/0! | BP88: =BS88 + ABS(BQ88) + ABS(BR88) -> 0 | BW88: FALSE | BX88: FALSE | BY88: =(BT88-BI88)/BI88 -> #DIV/0! | BZ88: =(BS88-BH88)/BH88 -> #DIV/0! | CA88: =CD88 + ABS(CB88) + ABS(CC88) -> 0 | CH88: FALSE | CI88: FALSE | CJ88: =(CE88-BV88)/BV88 -> #DIV/0! | CK88: =(CD88-BS88)/BS88 -> #DIV/0! | CL88: =CO88 + ABS(CM88) + ABS(CN88) -> 0 | CS88: FALSE | CT88: FALSE | CU88: =(CP88-CE88)/CE88 -> #DIV/0! | CV88: =(CO88-CD88)/CD88 -> #DIV/0! | CW88: =CZ88 + ABS(CX88) + ABS(CY88) -> 0 | DD88: FALSE | DE88: FALSE | DF88: =(DA88-CR88)/CR88 -> #DIV/0! | DG88: =(CZ88-CO88)/CO88 -> #DIV/0! | DH88: =DK88 + ABS(DI88) + ABS(DJ88) -> 0 | DO88: FALSE | DP88: FALSE | DQ88: =(DL88-DA88)/DA88 -> #DIV/0! | DR88: =(DK88-CZ88)/CZ88 -> #DIV/0! | DS88: =DV88 + ABS(DT88) + ABS(DU88) -> 0 | DZ88: FALSE | EA88: FALSE | EB88: =(DW88-DN88)/DN88 -> #DIV/0! | EC88: =(DV88-DK88)/DK88 -> #DIV/0! | ED88: =EG88 + ABS(EE88) + ABS(EF88) -> 0 | EK88: FALSE | EL88: FALSE | EM88: =(EH88-DW88)/DW88 -> #DIV/0! | EN88: =(EG88-DV88)/DV88 -> #DIV/0! | EO88: =ER88 + ABS(EP88) + ABS(EQ88) -> 0 | EV88: FALSE | EW88: FALSE | EX88: =(ES88-EJ88)/EJ88 -> #DIV/0! | EY88: =(ER88-EG88)/EG88 -> #DIV/0!
C89: PRESÍDIO DE DIVINÓPOLIS (FLORAMAR) | D89: 1450022 | E89: 42 | F89: G23C8002525 | G89: 00100266118 | H89: COMPANHIA DE SANEAMENTO DE MINAS GERAIS COPASA MG | I89: 17.281.106/0001-03 | N89: 107 | P89: 3048.53 | R89: 60462.44 | S89: 2350 | T89: 1450.01.0005511/2026-51 | X89: =AA89 + ABS(Y89) + ABS(Z89) -> 169870.18 | Y89: -8153.77 | Z89: 0 | AA89: 161716.41 | AB89: 6220 | AC89: 10/03/2026 | AD89: 1450.01.0029372/2026-78 | AE89: TRUE | AF89: TRUE | AG89: =(AB89-S89)/S89 -> 1.6468085 | AH89: =(AA89-R89)/R89 -> 1.674659 | AI89: =AL89 + ABS(AJ89) + ABS(AK89) -> 179379.29 | AJ89: -8610.21 | AK89: 0 | AL89: 170769.08 | AM89: 6566 | AN89: 46122 | AO89: 1450.01.0046622/2026-25 | AP89: TRUE | AQ89: TRUE | AR89: =(AM89-AB89)/AB89 -> 0.05562701 | AS89: =(AL89-AA89)/AA89 -> 0.055978673 | AT89: =AW89 + ABS(AU89) + ABS(AV89) -> 0 | BA89: FALSE | BB89: FALSE | BC89: =(AX89-AM89)/AM89 -> -1 | BD89: =(AW89-AL89)/AL89 -> -1 | BE89: =BH89 + ABS(BF89) + ABS(BG89) -> 0 | BL89: FALSE | BM89: FALSE | BN89: =(BI89-AZ89)/AZ89 -> #DIV/0! | BO89: =(BH89-AW89)/AW89 -> #DIV/0! | BP89: =BS89 + ABS(BQ89) + ABS(BR89) -> 0 | BW89: FALSE | BX89: FALSE | BY89: =(BT89-BI89)/BI89 -> #DIV/0! | BZ89: =(BS89-BH89)/BH89 -> #DIV/0! | CA89: =CD89 + ABS(CB89) + ABS(CC89) -> 0 | CH89: FALSE | CI89: FALSE | CJ89: =(CE89-BV89)/BV89 -> #DIV/0! | CK89: =(CD89-BS89)/BS89 -> #DIV/0! | CL89: =CO89 + ABS(CM89) + ABS(CN89) -> 0 | CS89: FALSE | CT89: FALSE | CU89: =(CP89-CE89)/CE89 -> #DIV/0! | CV89: =(CO89-CD89)/CD89 -> #DIV/0! | CW89: =CZ89 + ABS(CX89) + ABS(CY89) -> 0 | DD89: FALSE | DE89: FALSE | DF89: =(DA89-CR89)/CR89 -> #DIV/0! | DG89: =(CZ89-CO89)/CO89 -> #DIV/0! | DH89: =DK89 + ABS(DI89) + ABS(DJ89) -> 0 | DO89: FALSE | DP89: FALSE | DQ89: =(DL89-DA89)/DA89 -> #DIV/0! | DR89: =(DK89-CZ89)/CZ89 -> #DIV/0! | DS89: =DV89 + ABS(DT89) + ABS(DU89) -> 0 | DZ89: FALSE | EA89: FALSE | EB89: =(DW89-DN89)/DN89 -> #DIV/0! | EC89: =(DV89-DK89)/DK89 -> #DIV/0! | ED89: =EG89 + ABS(EE89) + ABS(EF89) -> 0 | EK89: FALSE | EL89: FALSE | EM89: =(EH89-DW89)/DW89 -> #DIV/0! | EN89: =(EG89-DV89)/DV89 -> #DIV/0! | EO89: =ER89 + ABS(EP89) + ABS(EQ89) -> 0 | EV89: FALSE | EW89: FALSE | EX89: =(ES89-EJ89)/EJ89 -> #DIV/0! | EY89: =(ER89-EG89)/EG89 -> #DIV/0!
... C99: PRESÍDIO DE GUARANÉSIA | D99: 1450022 | E99: 101 | F99: G24C8000364 | G99: 00127698710 | H99: COMPANHIA DE SANEAMENTO DE MINAS GERAIS COPASA MG | I99: 17.281.106/0001-03 | N99: 107 | P99: 4046.79 | R99: 80261.29 | S99: 4888 | T99: 1450.01.0005511/2026-51 | X99: =AA99 + ABS(Y99) + ABS(Z99) -> 92271.32 | Y99: -4429.02 | Z99: 0 | AA99: 87842.3 | AB99: 5346 | AC99: 10/03/2026 | AD99: 1450.01.0029372/2026-78 | AE99: TRUE | AF99: TRUE | AG99: =(AB99-S99)/S99 -> 0.093698854 | AH99: =(AA99-R99)/R99 -> 0.094454126 | AI99: =AL99 + ABS(AJ99) + ABS(AK99) -> 78236.32 | AJ99: -3755.34 | AK99: 0 | AL99: 74480.98 | AM99: 4391 | AN99: 46122 | AO99: 1450.01.0046622/2026-25 | AP99: TRUE | AQ99: TRUE | AR99: =(AM99-AB99)/AB99 -> -0.17863823 | AS99: =(AL99-AA99)/AA99 -> -0.15210576 | AT99: =AW99 + ABS(AU99) + ABS(AV99) -> 0 | BA99: FALSE | BB99: FALSE | BC99: =(AX99-AM99)/AM99 -> -1 | BD99: =(AW99-AL99)/AL99 -> -1 | BE99: =BH99 + ABS(BF99) + ABS(BG99) -> 0 | BL99: FALSE | BM99: FALSE | BN99: =(BI99-AZ99)/AZ99 -> #DIV/0! | BO99: =(BH99-AW99)/AW99 -> #DIV/0! | BP99: =BS99 + ABS(BQ99) + ABS(BR99) -> 0 | BW99: FALSE | BX99: FALSE | BY99: =(BT99-BI99)/BI99 -> #DIV/0! | BZ99: =(BS99-BH99)/BH99 -> #DIV/0! | CA99: =CD99 + ABS(CB99) + ABS(CC99) -> 0 | CH99: FALSE | CI99: FALSE | CJ99: =(CE99-BV99)/BV99 -> #DIV/0! | CK99: =(CD99-BS99)/BS99 -> #DIV/0! | CL99: =CO99 + ABS(CM99) + ABS(CN99) -> 0 | CS99: FALSE | CT99: FALSE | CU99: =(CP99-CE99)/CE99 -> #DIV/0! | CV99: =(CO99-CD99)/CD99 -> #DIV/0! | CW99: =CZ99 + ABS(CX99) + ABS(CY99) -> 0 | DD99: FALSE | DE99: FALSE | DF99: =(DA99-CR99)/CR99 -> #DIV/0! | DG99: =(CZ99-CO99)/CO99 -> #DIV/0! | DH99: =DK99 + ABS(DI99) + ABS(DJ99) -> 0 | DO99: FALSE | DP99: FALSE | DQ99: =(DL99-DA99)/DA99 -> #DIV/0! | DR99: =(DK99-CZ99)/CZ99 -> #DIV/0! | DS99: =DV99 + ABS(DT99) + ABS(DU99) -> 0 | DZ99: FALSE | EA99: FALSE | EB99: =(DW99-DN99)/DN99 -> #DIV/0! | EC99: =(DV99-DK99)/DK99 -> #DIV/0! | ED99: =EG99 + ABS(EE99) + ABS(EF99) -> 0 | EK99: FALSE | EL99: FALSE | EM99: =(EH99-DW99)/DW99 -> #DIV/0! | EN99: =(EG99-DV99)/DV99 -> #DIV/0! | EO99: =ER99 + ABS(EP99) + ABS(EQ99) -> 0 | EV99: FALSE | EW99: FALSE | EX99: =(ES99-EJ99)/EJ99 -> #DIV/0! | EY99: =(ER99-EG99)/EG99 -> #DIV/0!
C100: PRESÍDIO DE GUAXUPE | D100: 1450022 | E100: 373 | F100: Y23G1147986 | G100: 00004628101 | H100: COMPANHIA DE SANEAMENTO DE MINAS GERAIS COPASA MG | I100: 17.281.106/0001-03 | N100: 107 | P100: 2.6 | R100: 51.52 | T100: 1450.01.0005511/2026-51 | X100: =AA100 + ABS(Y100) + ABS(Z100) -> 175.28 | Y100: -8.41 | Z100: 0 | AA100: 166.87 | AB100: 11 | AC100: 10/03/2026 | AD100: 1450.01.0029372/2026-78 | AE100: TRUE | AF100: TRUE | AG100: =(AB100-S100)/S100 -> #DIV/0! | AH100: =(AA100-R100)/R100 -> 2.2389363 | AI100: =AL100 + ABS(AJ100) + ABS(AK100) -> 69.18 | AJ100: -3.32 | AK100: 0 | AL100: 65.86 | AM100: 1 | AN100: 46122 | AO100: 1450.01.0046622/2026-25 | AP100: TRUE | AQ100: TRUE | AR100: =(AM100-AB100)/AB100 -> -0.90909091 | AS100: =(AL100-AA100)/AA100 -> -0.60532151 | AT100: =AW100 + ABS(AU100) + ABS(AV100) -> 0 | BA100: FALSE | BB100: FALSE | BC100: =(AX100-AM100)/AM100 -> -1 | BD100: =(AW100-AL100)/AL100 -> -1 | BE100: =BH100 + ABS(BF100) + ABS(BG100) -> 0 | BL100: FALSE | BM100: FALSE | BN100: =(BI100-AZ100)/AZ100 -> #DIV/0! | BO100: =(BH100-AW100)/AW100 -> #DIV/0! | BP100: =BS100 + ABS(BQ100) + ABS(BR100) -> 0 | BW100: FALSE | BX100: FALSE | BY100: =(BT100-BI100)/BI100 -> #DIV/0! | BZ100: =(BS100-BH100)/BH100 -> #DIV/0! | CA100: =CD100 + ABS(CB100) + ABS(CC100) -> 0 | CH100: FALSE | CI100: FALSE | CJ100: =(CE100-BV100)/BV100 -> #DIV/0! | CK100: =(CD100-BS100)/BS100 -> #DIV/0! | CL100: =CO100 + ABS(CM100) + ABS(CN100) -> 0 | CS100: FALSE | CT100: FALSE | CU100: =(CP100-CE100)/CE100 -> #DIV/0! | CV100: =(CO100-CD100)/CD100 -> #DIV/0! | CW100: =CZ100 + ABS(CX100) + ABS(CY100) -> 0 | DD100: FALSE | DE100: FALSE | DF100: =(DA100-CR100)/CR100 -> #DIV/0! | DG100: =(CZ100-CO100)/CO100 -> #DIV/0! | DH100: =DK100 + ABS(DI100) + ABS(DJ100) -> 0 | DO100: FALSE | DP100: FALSE | DQ100: =(DL100-DA100)/DA100 -> #DIV/0! | DR100: =(DK100-CZ100)/CZ100 -> #DIV/0! | DS100: =DV100 + ABS(DT100) + ABS(DU100) -> 0 | DZ100: FALSE | EA100: FALSE | EB100: =(DW100-DN100)/DN100 -> #DIV/0! | EC100: =(DV100-DK100)/DK100 -> #DIV/0! | ED100: =EG100 + ABS(EE100) + ABS(EF100) -> 0 | EK100: FALSE | EL100: FALSE | EM100: =(EH100-DW100)/DW100 -> #DIV/0! | EN100: =(EG100-DV100)/DV100 -> #DIV/0! | EO100: =ER100 + ABS(EP100) + ABS(EQ100) -> 0 | EV100: FALSE | EW100: FALSE | EX100: =(ES100-EJ100)/EJ100 -> #DIV/0! | EY100: =(ER100-EG100)/EG100 -> #DIV/0!
C101: PRESÍDIO DE INHAPIM | D101: 1450022 | E101: 165 | F101: A20G0207451 | G101: 00007828837 | H101: COMPANHIA DE SANEAMENTO DE MINAS GERAIS COPASA MG | I101: 17.281.106/0001-03 | N101: 107 | P101: 1142.78 | R101: 22665.1 | S101: 826 | T101: 1450.01.0005511/2026-51 | X101: =AA101 + ABS(Y101) + ABS(Z101) -> 28406.64 | Y101: -1363.52 | Z101: 0 | AA101: 27043.12 | AB101: 978 | AC101: 10/03/2026 | AD101: 1450.01.0029372/2026-78 | AE101: TRUE | AF101: TRUE | AG101: =(AB101-S101)/S101 -> 0.18401937 | AH101: =(AA101-R101)/R101 -> 0.19316129 | AI101: =AL101 + ABS(AJ101) + ABS(AK101) -> 18771.02 | AJ101: -901.01 | AK101: 0 | AL101: 17870.01 | AM101: 643 | AN101: 46122 | AO101: 1450.01.0046622/2026-25 | AP101: TRUE | AQ101: TRUE | AR101: =(AM101-AB101)/AB101 -> -0.34253579 | AS101: =(AL101-AA101)/AA101 -> -0.33920309 | AT101: =AW101 + ABS(AU101) + ABS(AV101) -> 0 | BA101: FALSE | BB101: FALSE | BC101: =(AX101-AM101)/AM101 -> -1 | BD101: =(AW101-AL101)/AL101 -> -1 | BE101: =BH101 + ABS(BF101) + ABS(BG101) -> 0 | BL101: FALSE | BM101: FALSE | BN101: =(BI101-AZ101)/AZ101 -> #DIV/0! | BO101: =(BH101-AW101)/AW101 -> #DIV/0! | BP101: =BS101 + ABS(BQ101) + ABS(BR101) -> 0 | BW101: FALSE | BX101: FALSE | BY101: =(BT101-BI101)/BI101 -> #DIV/0! | BZ101: =(BS101-BH101)/BH101 -> #DIV/0! | CA101: =CD101 + ABS(CB101) + ABS(CC101) -> 0 | CH101: FALSE | CI101: FALSE | CJ101: =(CE101-BV101)/BV101 -> #DIV/0! | CK101: =(CD101-BS101)/BS101 -> #DIV/0! | CL101: =CO101 + ABS(CM101) + ABS(CN101) -> 0 | CS101: FALSE | CT101: FALSE | CU101: =(CP101-CE101)/CE101 -> #DIV/0! | CV101: =(CO101-CD101)/CD101 -> #DIV/0! | CW101: =CZ101 + ABS(CX101) + ABS(CY101) -> 0 | DD101: FALSE | DE101: FALSE | DF101: =(DA101-CR101)/CR101 -> #DIV/0! | DG101: =(CZ101-CO101)/CO101 -> #DIV/0! | DH101: =DK101 + ABS(DI101) + ABS(DJ101) -> 0 | DO101: FALSE | DP101: FALSE | DQ101: =(DL101-DA101)/DA101 -> #DIV/0! | DR101: =(DK101-CZ101)/CZ101 -> #DIV/0! | DS101: =DV101 + ABS(DT101) + ABS(DU101) -> 0 | DZ101: FALSE | EA101: FALSE | EB101: =(DW101-DN101)/DN101 -> #DIV/0! | EC101: =(DV101-DK101)/DK101 -> #DIV/0! | ED101: =EG101 + ABS(EE101) + ABS(EF101) -> 0 | EK101: FALSE | EL101: FALSE | EM101: =(EH101-DW101)/DW101 -> #DIV/0! | EN101: =(EG101-DV101)/DV101 -> #DIV/0! | EO101: =ER101 + ABS(EP101) + ABS(EQ101) -> 0 | EV101: FALSE | EW101: FALSE | EX101: =(ES101-EJ101)/EJ101 -> #DIV/0! | EY101: =(ER101-EG101)/EG101 -> #DIV/0!
C102: PRESÍDIO DE INHAPIM | D102: 1450022 | E102: 165 | F102: D17B7043860 | G102: 00014749963 | H102: COMPANHIA DE SANEAMENTO DE MINAS GERAIS COPASA MG | I102: 17.281.106/0001-03 | N102: 107 | P102: 185.51 | R102: 3679.27 | S102: 161 | T102: 1450.01.0005511/2026-51 | X102: =AA102 + ABS(Y102) + ABS(Z102) -> 8680.38 | Y102: -416.66 | Z102: 0 | AA102: 8263.72 | AB102: 326 | AC102: 10/03/2026 | AD102: 1450.01.0029372/2026-78 | AE102: TRUE | AF102: TRUE | AG102: =(AB102-S102)/S102 -> 1.0248447 | AH102: =(AA102-R102)/R102 -> 1.2460216 | AI102: =AL102 + ABS(AJ102) + ABS(AK102) -> 10629.24 | AJ102: -510.2 | AK102: 0 | AL102: 10119.04 | AM102: 381 | AN102: 46122 | AO102: 1450.01.0046622/2026-25 | AP102: TRUE | AQ102: TRUE | AR102: =(AM102-AB102)/AB102 -> 0.16871166 | AS102: =(AL102-AA102)/AA102 -> 0.2245139 | AT102: =AW102 + ABS(AU102) + ABS(AV102) -> 0 | BA102: FALSE | BB102: FALSE | BC102: =(AX102-AM102)/AM102 -> -1 | BD102: =(AW102-AL102)/AL102 -> -1 | BE102: =BH102 + ABS(BF102) + ABS(BG102) -> 0 | BL102: FALSE | BM102: FALSE | BN102: =(BI102-AZ102)/AZ102 -> #DIV/0! | BO102: =(BH102-AW102)/AW102 -> #DIV/0! | BP102: =BS102 + ABS(BQ102) + ABS(BR102) -> 0 | BW102: FALSE | BX102: FALSE | BY102: =(BT102-BI102)/BI102 -> #DIV/0! | BZ102: =(BS102-BH102)/BH102 -> #DIV/0! | CA102: =CD102 + ABS(CB102) + ABS(CC102) -> 0 | CH102: FALSE | CI102: FALSE | CJ102: =(CE102-BV102)/BV102 -> #DIV/0! | CK102: =(CD102-BS102)/BS102 -> #DIV/0! | CL102: =CO102 + ABS(CM102) + ABS(CN102) -> 0 | CS102: FALSE | CT102: FALSE | CU102: =(CP102-CE102)/CE102 -> #DIV/0! | CV102: =(CO102-CD102)/CD102 -> #DIV/0! | CW102: =CZ102 + ABS(CX102) + ABS(CY102) -> 0 | DD102: FALSE | DE102: FALSE | DF102: =(DA102-CR102)/CR102 -> #DIV/0! | DG102: =(CZ102-CO102)/CO102 -> #DIV/0! | DH102: =DK102 + ABS(DI102) + ABS(DJ102) -> 0 | DO102: FALSE | DP102: FALSE | DQ102: =(DL102-DA102)/DA102 -> #DIV/0! | DR102: =(DK102-CZ102)/CZ102 -> #DIV/0! | DS102: =DV102 + ABS(DT102) + ABS(DU102) -> 0 | DZ102: FALSE | EA102: FALSE | EB102: =(DW102-DN102)/DN102 -> #DIV/0! | EC102: =(DV102-DK102)/DK102 -> #DIV/0! | ED102: =EG102 + ABS(EE102) + ABS(EF102) -> 0 | EK102: FALSE | EL102: FALSE | EM102: =(EH102-DW102)/DW102 -> #DIV/0! | EN102: =(EG102-DV102)/DV102 -> #DIV/0! | EO102: =ER102 + ABS(EP102) + ABS(EQ102) -> 0 | EV102: FALSE | EW102: FALSE | EX102: =(ES102-EJ102)/EJ102 -> #DIV/0! | EY102: =(ER102-EG102)/EG102 -> #DIV/0!
C103: PRESÍDIO DE ITACARAMBI | D103: 1450022 | E103: 369 | F103: A15N0026928 | G103: 00103496386 | H103: COMPANHIA DE SANEAMENTO DE MINAS GERAIS COPASA MG | I103: 17.281.106/0001-03 | N103: 107 | P103: 724.53 | R103: 14369.91 | S103: 538 | T103: 1450.01.0005511/2026-51 | X103: =AA103 + ABS(Y103) + ABS(Z103) -> 14943.16 | Y103: -717.27 | Z103: 0 | AA103: 14225.89 | AB103: 533 | AC103: 10/03/2026 | AD103: 1450.01.0029372/2026-78 | AE103: TRUE | AF103: TRUE | AG103: =(AB103-S103)/S103 -> -0.0092936803 | AH103: =(AA103-R103)/R103 -> -0.010022331 | AI103: =AL103 + ABS(AJ103) + ABS(AK103) -> 18236.62 | AJ103: -875.36 | AK103: 0 | AL103: 17361.26 | AM103: 620 | AN103: 46122 | AO103: 1450.01.0046622/2026-25 | AP103: TRUE | AQ103: TRUE | AR103: =(AM103-AB103)/AB103 -> 0.16322702 | AS103: =(AL103-AA103)/AA103 -> 0.22039886 | AT103: =AW103 + ABS(AU103) + ABS(AV103) -> 0 | BA103: FALSE | BB103: FALSE | BC103: =(AX103-AM103)/AM103 -> -1 | BD103: =(AW103-AL103)/AL103 -> -1 | BE103: =BH103 + ABS(BF103) + ABS(BG103) -> 0 | BL103: FALSE | BM103: FALSE | BN103: =(BI103-AZ103)/AZ103 -> #DIV/0! | BO103: =(BH103-AW103)/AW103 -> #DIV/0! | BP103: =BS103 + ABS(BQ103) + ABS(BR103) -> 0 | BW103: FALSE | BX103: FALSE | BY103: =(BT103-BI103)/BI103 -> #DIV/0! | BZ103: =(BS103-BH103)/BH103 -> #DIV/0! | CA103: =CD103 + ABS(CB103) + ABS(CC103) -> 0 | CH103: FALSE | CI103: FALSE | CJ103: =(CE103-BV103)/BV103 -> #DIV/0! | CK103: =(CD103-BS103)/BS103 -> #DIV/0! | CL103: =CO103 + ABS(CM103) + ABS(CN103) -> 0 | CS103: FALSE | CT103: FALSE | CU103: =(CP103-CE103)/CE103 -> #DIV/0! | CV103: =(CO103-CD103)/CD103 -> #DIV/0! | CW103: =CZ103 + ABS(CX103) + ABS(CY103) -> 0 | DD103: FALSE | DE103: FALSE | DF103: =(DA103-CR103)/CR103 -> #DIV/0! | DG103: =(CZ103-CO103)/CO103 -> #DIV/0! | DH103: =DK103 + ABS(DI103) + ABS(DJ103) -> 0 | DO103: FALSE | DP103: FALSE | DQ103: =(DL103-DA103)/DA103 -> #DIV/0! | DR103: =(DK103-CZ103)/CZ103 -> #DIV/0! | DS103: =DV103 + ABS(DT103) + ABS(DU103) -> 0 | DZ103: FALSE | EA103: FALSE | EB103: =(DW103-DN103)/DN103 -> #DIV/0! | EC103: =(DV103-DK103)/DK103 -> #DIV/0! | ED103: =EG103 + ABS(EE103) + ABS(EF103) -> 0 | EK103: FALSE | EL103: FALSE | EM103: =(EH103-DW103)/DW103 -> #DIV/0! | EN103: =(EG103-DV103)/DV103 -> #DIV/0! | EO103: =ER103 + ABS(EP103) + ABS(EQ103) -> 0 | EV103: FALSE | EW103: FALSE | EX103: =(ES103-EJ103)/EJ103 -> #DIV/0! | EY103: =(ER103-EG103)/EG103 -> #DIV/0!
C104: PRESÍDIO DE ITACARAMBI | D104: 1450022 | E104: 369 | F104: A22S0206087 | G104: 00017561612 | H104: COMPANHIA DE SANEAMENTO DE MINAS GERAIS COPASA MG | I104: 17.281.106/0001-03 | N104: 107 | P104: 386.16 | R104: 7658.87 | S104: 305 | T104: 1450.01.0005511/2026-51 | X104: =AA104 + ABS(Y104) + ABS(Z104) -> 6320.49 | Y104: -303.38 | Z104: 0 | AA104: 6017.11 | AB104: 248 | AC104: 10/03/2026 | AD104: 1450.01.0029372/2026-78 | AE104: TRUE | AF104: TRUE | AG104: =(AB104-S104)/S104 -> -0.18688525 | AH104: =(AA104-R104)/R104 -> -0.2143606 | AI104: =AL104 + ABS(AJ104) + ABS(AK104) -> 2814.06 | AJ104: -135.07 | AK104: 0 | AL104: 2678.99 | AM104: 116 | AN104: 46122 | AO104: 1450.01.0046622/2026-25 | AP104: TRUE | AQ104: TRUE | AR104: =(AM104-AB104)/AB104 -> -0.53225806 | AS104: =(AL104-AA104)/AA104 -> -0.55477131 | AT104: =AW104 + ABS(AU104) + ABS(AV104) -> 0 | BA104: FALSE | BB104: FALSE | BC104: =(AX104-AM104)/AM104 -> -1 | BD104: =(AW104-AL104)/AL104 -> -1 | BE104: =BH104 + ABS(BF104) + ABS(BG104) -> 0 | BL104: FALSE | BM104: FALSE | BN104: =(BI104-AZ104)/AZ104 -> #DIV/0! | BO104: =(BH104-AW104)/AW104 -> #DIV/0! | BP104: =BS104 + ABS(BQ104) + ABS(BR104) -> 0 | BW104: FALSE | BX104: FALSE | BY104: =(BT104-BI104)/BI104 -> #DIV/0! | BZ104: =(BS104-BH104)/BH104 -> #DIV/0! | CA104: =CD104 + ABS(CB104) + ABS(CC104) -> 0 | CH104: FALSE | CI104: FALSE | CJ104: =(CE104-BV104)/BV104 -> #DIV/0! | CK104: =(CD104-BS104)/BS104 -> #DIV/0! | CL104: =CO104 + ABS(CM104) + ABS(CN104) -> 0 | CS104: FALSE | CT104: FALSE | CU104: =(CP104-CE104)/CE104 -> #DIV/0! | CV104: =(CO104-CD104)/CD104 -> #DIV/0! | CW104: =CZ104 + ABS(CX104) + ABS(CY104) -> 0 | DD104: FALSE | DE104: FALSE | DF104: =(DA104-CR104)/CR104 -> #DIV/0! | DG104: =(CZ104-CO104)/CO104 -> #DIV/0! | DH104: =DK104 + ABS(DI104) + ABS(DJ104) -> 0 | DO104: FALSE | DP104: FALSE | DQ104: =(DL104-DA104)/DA104 -> #DIV/0! | DR104: =(DK104-CZ104)/CZ104 -> #DIV/0! | DS104: =DV104 + ABS(DT104) + ABS(DU104) -> 0 | DZ104: FALSE | EA104: FALSE | EB104: =(DW104-DN104)/DN104 -> #DIV/0! | EC104: =(DV104-DK104)/DK104 -> #DIV/0! | ED104: =EG104 + ABS(EE104) + ABS(EF104) -> 0 | EK104: FALSE | EL104: FALSE | EM104: =(EH104-DW104)/DW104 -> #DIV/0! | EN104: =(EG104-DV104)/DV104 -> #DIV/0! | EO104: =ER104 + ABS(EP104) + ABS(EQ104) -> 0 | EV104: FALSE | EW104: FALSE | EX104: =(ES104-EJ104)/EJ104 -> #DIV/0! | EY104: =(ER104-EG104)/EG104 -> #DIV/0!
C105: PRESÍDIO DE ITACARAMBI | D105: 1450022 | E105: 369 | F105: Y23G1479192 | G105: 00142869163 | H105: COMPANHIA DE SANEAMENTO DE MINAS GERAIS COPASA MG | I105: 17.281.106/0001-03 | N105: 107 | P105: 3 | R105: 59.46 | S105: 1 | T105: 1450.01.0005511/2026-51 | X105: =AA105 + ABS(Y105) + ABS(Z105) -> 70.8 | Y105: -3.4 | Z105: 0 | AA105: 67.4 | AB105: 2 | AC105: 10/03/2026 | AD105: 1450.01.0029372/2026-78 | AE105: TRUE | AF105: TRUE | AG105: =(AB105-S105)/S105 -> 1 | AH105: =(AA105-R105)/R105 -> 0.13353515 | AI105: =AL105 + ABS(AJ105) + ABS(AK105) -> 69.84 | AJ105: -3.35 | AK105: 0 | AL105: 66.49 | AM105: 1 | AN105: 46122 | AO105: 1450.01.0046622/2026-25 | AP105: TRUE | AQ105: TRUE | AR105: =(AM105-AB105)/AB105 -> -0.5 | AS105: =(AL105-AA105)/AA105 -> -0.013501484 | AT105: =AW105 + ABS(AU105) + ABS(AV105) -> 0 | BA105: FALSE | BB105: FALSE | BC105: =(AX105-AM105)/AM105 -> -1 | BD105: =(AW105-AL105)/AL105 -> -1 | BE105: =BH105 + ABS(BF105) + ABS(BG105) -> 0 | BL105: FALSE | BM105: FALSE | BN105: =(BI105-AZ105)/AZ105 -> #DIV/0! | BO105: =(BH105-AW105)/AW105 -> #DIV/0! | BP105: =BS105 + ABS(BQ105) + ABS(BR105) -> 0 | BW105: FALSE | BX105: FALSE | BY105: =(BT105-BI105)/BI105 -> #DIV/0! | BZ105: =(BS105-BH105)/BH105 -> #DIV/0! | CA105: =CD105 + ABS(CB105) + ABS(CC105) -> 0 | CH105: FALSE | CI105: FALSE | CJ105: =(CE105-BV105)/BV105 -> #DIV/0! | CK105: =(CD105-BS105)/BS105 -> #DIV/0! | CL105: =CO105 + ABS(CM105) + ABS(CN105) -> 0 | CS105: FALSE | CT105: FALSE | CU105: =(CP105-CE105)/CE105 -> #DIV/0! | CV105: =(CO105-CD105)/CD105 -> #DIV/0! | CW105: =CZ105 + ABS(CX105) + ABS(CY105) -> 0 | DD105: FALSE | DE105: FALSE | DF105: =(DA105-CR105)/CR105 -> #DIV/0! | DG105: =(CZ105-CO105)/CO105 -> #DIV/0! | DH105: =DK105 + ABS(DI105) + ABS(DJ105) -> 0 | DO105: FALSE | DP105: FALSE | DQ105: =(DL105-DA105)/DA105 -> #DIV/0! | DR105: =(DK105-CZ105)/CZ105 -> #DIV/0! | DS105: =DV105 + ABS(DT105) + ABS(DU105) -> 0 | DZ105: FALSE | EA105: FALSE | EB105: =(DW105-DN105)/DN105 -> #DIV/0! | EC105: =(DV105-DK105)/DK105 -> #DIV/0! | ED105: =EG105 + ABS(EE105) + ABS(EF105) -> 0 | EK105: FALSE | EL105: FALSE | EM105: =(EH105-DW105)/DW105 -> #DIV/0! | EN105: =(EG105-DV105)/DV105 -> #DIV/0! | EO105: =ER105 + ABS(EP105) + ABS(EQ105) -> 0 | EV105: FALSE | EW105: FALSE | EX105: =(ES105-EJ105)/EJ105 -> #DIV/0! | EY105: =(ER105-EG105)/EG105 -> #DIV/0!
C106: PRESÍDIO DE ITAJUBÁ | D106: 1450022 | E106: 127 | F106: A14Z0111998 J21S0100086 | G106: 00115038248 | H106: COMPANHIA DE SANEAMENTO DE MINAS GERAIS COPASA MG | I106: 17.281.106/0001-03 | N106: 107 | P106: 11446.42 | R106: 227020.69 | S106: 7921 | T106: 1450.01.0005511/2026-51 | X106: =AA106 + ABS(Y106) + ABS(Z106) -> 301215.98 | Y106: -14458.37 | Z106: 0 | AA106: 286757.61 | AB106: 9995 | AC106: 10/03/2026 | AD106: 1450.01.0029372/2026-78 | AE106: TRUE | AF106: TRUE | AG106: =(AB106-S106)/S106 -> 0.26183563 | AH106: =(AA106-R106)/R106 -> 0.26313425 | AI106: =AL106 + ABS(AJ106) + ABS(AK106) -> 273994.33 | AJ106: -13151.73 | AK106: 0 | AL106: 260842.6 | AM106: 8856 | AN106: 46122 | AO106: 1450.01.0046622/2026-25 | AP106: TRUE | AQ106: TRUE | AR106: =(AM106-AB106)/AB106 -> -0.11395698 | AS106: =(AL106-AA106)/AA106 -> -0.090372528 | AT106: =AW106 + ABS(AU106) + ABS(AV106) -> 0 | BA106: FALSE | BB106: FALSE | BC106: =(AX106-AM106)/AM106 -> -1 | BD106: =(AW106-AL106)/AL106 -> -1 | BE106: =BH106 + ABS(BF106) + ABS(BG106) -> 0 | BL106: FALSE | BM106: FALSE | BN106: =(BI106-AZ106)/AZ106 -> #DIV/0! | BO106: =(BH106-AW106)/AW106 -> #DIV/0! | BP106: =BS106 + ABS(BQ106) + ABS(BR106) -> 0 | BW106: FALSE | BX106: FALSE | BY106: =(BT106-BI106)/BI106 -> #DIV/0! | BZ106: =(BS106-BH106)/BH106 -> #DIV/0! | CA106: =CD106 + ABS(CB106) + ABS(CC106) -> 0 | CH106: FALSE | CI106: FALSE | CJ106: =(CE106-BV106)/BV106 -> #DIV/0! | CK106: =(CD106-BS106)/BS106 -> #DIV/0! | CL106: =CO106 + ABS(CM106) + ABS(CN106) -> 0 | CS106: FALSE | CT106: FALSE | CU106: =(CP106-CE106)/CE106 -> #DIV/0! | CV106: =(CO106-CD106)/CD106 -> #DIV/0! | CW106: =CZ106 + ABS(CX106) + ABS(CY106) -> 0 | DD106: FALSE | DE106: FALSE | DF106: =(DA106-CR106)/CR106 -> #DIV/0! | DG106: =(CZ106-CO106)/CO106 -> #DIV/0! | DH106: =DK106 + ABS(DI106) + ABS(DJ106) -> 0 | DO106: FALSE | DP106: FALSE | DQ106: =(DL106-DA106)/DA106 -> #DIV/0! | DR106: =(DK106-CZ106)/CZ106 -> #DIV/0! | DS106: =DV106 + ABS(DT106) + ABS(DU106) -> 0 | DZ106: FALSE | EA106: FALSE | EB106: =(DW106-DN106)/DN106 -> #DIV/0! | EC106: =(DV106-DK106)/DK106 -> #DIV/0! | ED106: =EG106 + ABS(EE106) + ABS(EF106) -> 0 | EK106: FALSE | EL106: FALSE | EM106: =(EH106-DW106)/DW106 -> #DIV/0! | EN106: =(EG106-DV106)/DV106 -> #DIV/0! | EO106: =ER106 + ABS(EP106) + ABS(EQ106) -> 0 | EV106: FALSE | EW106: FALSE | EX106: =(ES106-EJ106)/EJ106 -> #DIV/0! | EY106: =(ER106-EG106)/EG106 -> #DIV/0!
C107: PRESÍDIO DE ITAMARANDIBA | D107: 1450022 | E107: 326 | F107: Y22G1227121 | G107: 00006448640 | H107: COMPANHIA DE SANEAMENTO DE MINAS GERAIS COPASA MG | I107: 17.281.106/0001-03 | N107: 107 | P107: 260.32 | R107: 5162.94 | S107: 351 | T107: 1450.01.0005511/2026-51 | X107: =AA107 + ABS(Y107) + ABS(Z107) -> 6362.16 | Y107: -305.38 | Z107: 0 | AA107: 6056.78 | AB107: 405 | AC107: 10/03/2026 | AD107: 1450.01.0029372/2026-78 | AE107: TRUE | AF107: TRUE | AG107: =(AB107-S107)/S107 -> 0.15384615 | AH107: =(AA107-R107)/R107 -> 0.17312616 | AI107: =AL107 + ABS(AJ107) + ABS(AK107) -> 6591 | AJ107: -316.37 | AK107: 0 | AL107: 6274.63 | AM107: 408 | AN107: 46122 | AO107: 1450.01.0046622/2026-25 | AP107: TRUE | AQ107: TRUE | AR107: =(AM107-AB107)/AB107 -> 0.0074074074 | AS107: =(AL107-AA107)/AA107 -> 0.035967957 | AT107: =AW107 + ABS(AU107) + ABS(AV107) -> 0 | BA107: FALSE | BB107: FALSE | BC107: =(AX107-AM107)/AM107 -> -1 | BD107: =(AW107-AL107)/AL107 -> -1 | BE107: =BH107 + ABS(BF107) + ABS(BG107) -> 0 | BL107: FALSE | BM107: FALSE | BN107: =(BI107-AZ107)/AZ107 -> #DIV/0! | BO107: =(BH107-AW107)/AW107 -> #DIV/0! | BP107: =BS107 + ABS(BQ107) + ABS(BR107) -> 0 | BW107: FALSE | BX107: FALSE | BY107: =(BT107-BI107)/BI107 -> #DIV/0! | BZ107: =(BS107-BH107)/BH107 -> #DIV/0! | CA107: =CD107 + ABS(CB107) + ABS(CC107) -> 0 | CH107: FALSE | CI107: FALSE | CJ107: =(CE107-BV107)/BV107 -> #DIV/0! | CK107: =(CD107-BS107)/BS107 -> #DIV/0! | CL107: =CO107 + ABS(CM107) + ABS(CN107) -> 0 | CS107: FALSE | CT107: FALSE | CU107: =(CP107-CE107)/CE107 -> #DIV/0! | CV107: =(CO107-CD107)/CD107 -> #DIV/0! | CW107: =CZ107 + ABS(CX107) + ABS(CY107) -> 0 | DD107: FALSE | DE107: FALSE | DF107: =(DA107-CR107)/CR107 -> #DIV/0! | DG107: =(CZ107-CO107)/CO107 -> #DIV/0! | DH107: =DK107 + ABS(DI107) + ABS(DJ107) -> 0 | DO107: FALSE | DP107: FALSE | DQ107: =(DL107-DA107)/DA107 -> #DIV/0! | DR107: =(DK107-CZ107)/CZ107 -> #DIV/0! | DS107: =DV107 + ABS(DT107) + ABS(DU107) -> 0 | DZ107: FALSE | EA107: FALSE | EB107: =(DW107-DN107)/DN107 -> #DIV/0! | EC107: =(DV107-DK107)/DK107 -> #DIV/0! | ED107: =EG107 + ABS(EE107) + ABS(EF107) -> 0 | EK107: FALSE | EL107: FALSE | EM107: =(EH107-DW107)/DW107 -> #DIV/0! | EN107: =(EG107-DV107)/DV107 -> #DIV/0! | EO107: =ER107 + ABS(EP107) + ABS(EQ107) -> 0 | EV107: FALSE | EW107: FALSE | EX107: =(ES107-EJ107)/EJ107 -> #DIV/0! | EY107: =(ER107-EG107)/EG107 -> #DIV/0!
C108: PRESÍDIO DE ITAOBIM | D108: 1450022 | E108: 135 | F108: E17B0791020 | G108: 00106427288 | H108: COMPANHIA DE SANEAMENTO DE MINAS GERAIS COPASA MG | I108: 17.281.106/0001-03 | N108: 107 | P108: 2429.46 | R108: 48184.35 | S108: 1712 | T108: 1450.01.0005511/2026-51 | X108: =AA108 + ABS(Y108) + ABS(Z108) -> 55908.44 | Y108: -2683.61 | Z108: 0 | AA108: 53224.83 | AB108: 1887 | AC108: 10/03/2026 | AD108: 1450.01.0029372/2026-78 | AE108: TRUE | AF108: TRUE | AG108: =(AB108-S108)/S108 -> 0.10221963 | AH108: =(AA108-R108)/R108 -> 0.10460824 | AI108: =AL108 + ABS(AJ108) + ABS(AK108) -> 58629.35 | AJ108: -2814.21 | AK108: 0 | AL108: 55815.14 | AM108: 1900 | AN108: 46122 | AO108: 1450.01.0046622/2026-25 | AP108: TRUE | AQ108: TRUE | AR108: =(AM108-AB108)/AB108 -> 0.0068892422 | AS108: =(AL108-AA108)/AA108 -> 0.048667323 | AT108: =AW108 + ABS(AU108) + ABS(AV108) -> 0 | BA108: FALSE | BB108: FALSE | BC108: =(AX108-AM108)/AM108 -> -1 | BD108: =(AW108-AL108)/AL108 -> -1 | BE108: =BH108 + ABS(BF108) + ABS(BG108) -> 0 | BL108: FALSE | BM108: FALSE | BN108: =(BI108-AZ108)/AZ108 -> #DIV/0! | BO108: =(BH108-AW108)/AW108 -> #DIV/0! | BP108: =BS108 + ABS(BQ108) + ABS(BR108) -> 0 | BW108: FALSE | BX108: FALSE | BY108: =(BT108-BI108)/BI108 -> #DIV/0! | BZ108: =(BS108-BH108)/BH108 -> #DIV/0! | CA108: =CD108 + ABS(CB108) + ABS(CC108) -> 0 | CH108: FALSE | CI108: FALSE | CJ108: =(CE108-BV108)/BV108 -> #DIV/0! | CK108: =(CD108-BS108)/BS108 -> #DIV/0! | CL108: =CO108 + ABS(CM108) + ABS(CN108) -> 0 | CS108: FALSE | CT108: FALSE | CU108: =(CP108-CE108)/CE108 -> #DIV/0! | CV108: =(CO108-CD108)/CD108 -> #DIV/0! | CW108: =CZ108 + ABS(CX108) + ABS(CY108) -> 0 | DD108: FALSE | DE108: FALSE | DF108: =(DA108-CR108)/CR108 -> #DIV/0! | DG108: =(CZ108-CO108)/CO108 -> #DIV/0! | DH108: =DK108 + ABS(DI108) + ABS(DJ108) -> 0 | DO108: FALSE | DP108: FALSE | DQ108: =(DL108-DA108)/DA108 -> #DIV/0! | DR108: =(DK108-CZ108)/CZ108 -> #DIV/0! | DS108: =DV108 + ABS(DT108) + ABS(DU108) -> 0 | DZ108: FALSE | EA108: FALSE | EB108: =(DW108-DN108)/DN108 -> #DIV/0! | EC108: =(DV108-DK108)/DK108 -> #DIV/0! | ED108: =EG108 + ABS(EE108) + ABS(EF108) -> 0 | EK108: FALSE | EL108: FALSE | EM108: =(EH108-DW108)/DW108 -> #DIV/0! | EN108: =(EG108-DV108)/DV108 -> #DIV/0! | EO108: =ER108 + ABS(EP108) + ABS(EQ108) -> 0 | EV108: FALSE | EW108: FALSE | EX108: =(ES108-EJ108)/EJ108 -> #DIV/0! | EY108: =(ER108-EG108)/EG108 -> #DIV/0!
C109: PRESÍDIO DE ITAPAGIPE | D109: 1450022 | E109: 345 | F109: D18B0704505 | G109: 00006087787 | H109: COMPANHIA DE SANEAMENTO DE MINAS GERAIS COPASA MG | I109: 17.281.106/0001-03 | N109: 107 | P109: 1.49 | R109: 29.61 | T109: 1450.01.0005511/2026-51 | X109: =AA109 + ABS(Y109) + ABS(Z109) -> 91.64 | Y109: -4.4 | Z109: 0 | AA109: 87.24 | AB109: 10 | AC109: 10/03/2026 | AD109: 1450.01.0029372/2026-78 | AE109: TRUE | AF109: TRUE | AG109: =(AB109-S109)/S109 -> #DIV/0! | AH109: =(AA109-R109)/R109 -> 1.9463019 | AI109: =AL109 + ABS(AJ109) + ABS(AK109) -> 613.08 | AJ109: -29.43 | AK109: 0 | AL109: 583.65 | AM109: 50 | AN109: 46122 | AO109: 1450.01.0046622/2026-25 | AP109: TRUE | AQ109: TRUE | AR109: =(AM109-AB109)/AB109 -> 4 | AS109: =(AL109-AA109)/AA109 -> 5.6901651 | AT109: =AW109 + ABS(AU109) + ABS(AV109) -> 0 | BA109: FALSE | BB109: FALSE | BC109: =(AX109-AM109)/AM109 -> -1 | BD109: =(AW109-AL109)/AL109 -> -1 | BE109: =BH109 + ABS(BF109) + ABS(BG109) -> 0 | BL109: FALSE | BM109: FALSE | BN109: =(BI109-AZ109)/AZ109 -> #DIV/0! | BO109: =(BH109-AW109)/AW109 -> #DIV/0! | BP109: =BS109 + ABS(BQ109) + ABS(BR109) -> 0 | BW109: FALSE | BX109: FALSE | BY109: =(BT109-BI109)/BI109 -> #DIV/0! | BZ109: =(BS109-BH109)/BH109 -> #DIV/0! | CA109: =CD109 + ABS(CB109) + ABS(CC109) -> 0 | CH109: FALSE | CI109: FALSE | CJ109: =(CE109-BV109)/BV109 -> #DIV/0! | CK109: =(CD109-BS109)/BS109 -> #DIV/0! | CL109: =CO109 + ABS(CM109) + ABS(CN109) -> 0 | CS109: FALSE | CT109: FALSE | CU109: =(CP109-CE109)/CE109 -> #DIV/0! | CV109: =(CO109-CD109)/CD109 -> #DIV/0! | CW109: =CZ109 + ABS(CX109) + ABS(CY109) -> 0 | DD109: FALSE | DE109: FALSE | DF109: =(DA109-CR109)/CR109 -> #DIV/0! | DG109: =(CZ109-CO109)/CO109 -> #DIV/0! | DH109: =DK109 + ABS(DI109) + ABS(DJ109) -> 0 | DO109: FALSE | DP109: FALSE | DQ109: =(DL109-DA109)/DA109 -> #DIV/0! | DR109: =(DK109-CZ109)/CZ109 -> #DIV/0! | DS109: =DV109 + ABS(DT109) + ABS(DU109) -> 0 | DZ109: FALSE | EA109: FALSE | EB109: =(DW109-DN109)/DN109 -> #DIV/0! | EC109: =(DV109-DK109)/DK109 -> #DIV/0! | ED109: =EG109 + ABS(EE109) + ABS(EF109) -> 0 | EK109: FALSE | EL109: FALSE | EM109: =(EH109-DW109)/DW109 -> #DIV/0! | EN109: =(EG109-DV109)/DV109 -> #DIV/0! | EO109: =ER109 + ABS(EP109) + ABS(EQ109) -> 0 | EV109: FALSE | EW109: FALSE | EX109: =(ES109-EJ109)/EJ109 -> #DIV/0! | EY109: =(ER109-EG109)/EG109 -> #DIV/0!
C110: PRESÍDIO DE JABOTICATUBAS | D110: 1450022 | E110: 205 | F110: Y25S1333393 | G110: 00007185821 | H110: COMPANHIA DE SANEAMENTO DE MINAS GERAIS COPASA MG | I110: 17.281.106/0001-03 | N110: 107 | P110: 532.84 | R110: 10567.94 | S110: 406 | T110: 1450.01.0005511/2026-51 | X110: =AA110 + ABS(Y110) + ABS(Z110) -> 13400.16 | Y110: -643.21 | Z110: 0 | AA110: 12756.95 | AB110: 482 | AC110: 10/03/2026 | AD110: 1450.01.0029372/2026-78 | AE110: TRUE | AF110: TRUE | AG110: =(AB110-S110)/S110 -> 0.18719212 | AH110: =(AA110-R110)/R110 -> 0.20713687 | AI110: =AL110 + ABS(AJ110) + ABS(AK110) -> 10373.58 | AJ110: -497.93 | AK110: 0 | AL110: 9875.65 | AM110: 370 | AN110: 46122 | AO110: 1450.01.0046622/2026-25 | AP110: TRUE | AQ110: TRUE | AR110: =(AM110-AB110)/AB110 -> -0.23236515 | AS110: =(AL110-AA110)/AA110 -> -0.2258612 | AT110: =AW110 + ABS(AU110) + ABS(AV110) -> 0 | BA110: FALSE | BB110: FALSE | BC110: =(AX110-AM110)/AM110 -> -1 | BD110: =(AW110-AL110)/AL110 -> -1 | BE110: =BH110 + ABS(BF110) + ABS(BG110) -> 0 | BL110: FALSE | BM110: FALSE | BN110: =(BI110-AZ110)/AZ110 -> #DIV/0! | BO110: =(BH110-AW110)/AW110 -> #DIV/0! | BP110: =BS110 + ABS(BQ110) + ABS(BR110) -> 0 | BW110: FALSE | BX110: FALSE | BY110: =(BT110-BI110)/BI110 -> #DIV/0! | BZ110: =(BS110-BH110)/BH110 -> #DIV/0! | CA110: =CD110 + ABS(CB110) + ABS(CC110) -> 0 | CH110: FALSE | CI110: FALSE | CJ110: =(CE110-BV110)/BV110 -> #DIV/0! | CK110: =(CD110-BS110)/BS110 -> #DIV/0! | CL110: =CO110 + ABS(CM110) + ABS(CN110) -> 0 | CS110: FALSE | CT110: FALSE | CU110: =(CP110-CE110)/CE110 -> #DIV/0! | CV110: =(CO110-CD110)/CD110 -> #DIV/0! | CW110: =CZ110 + ABS(CX110) + ABS(CY110) -> 0 | DD110: FALSE | DE110: FALSE | DF110: =(DA110-CR110)/CR110 -> #DIV/0! | DG110: =(CZ110-CO110)/CO110 -> #DIV/0! | DH110: =DK110 + ABS(DI110) + ABS(DJ110) -> 0 | DO110: FALSE | DP110: FALSE | DQ110: =(DL110-DA110)/DA110 -> #DIV/0! | DR110: =(DK110-CZ110)/CZ110 -> #DIV/0! | DS110: =DV110 + ABS(DT110) + ABS(DU110) -> 0 | DZ110: FALSE | EA110: FALSE | EB110: =(DW110-DN110)/DN110 -> #DIV/0! | EC110: =(DV110-DK110)/DK110 -> #DIV/0! | ED110: =EG110 + ABS(EE110) + ABS(EF110) -> 0 | EK110: FALSE | EL110: FALSE | EM110: =(EH110-DW110)/DW110 -> #DIV/0! | EN110: =(EG110-DV110)/DV110 -> #DIV/0! | EO110: =ER110 + ABS(EP110) + ABS(EQ110) -> 0 | EV110: FALSE | EW110: FALSE | EX110: =(ES110-EJ110)/EJ110 -> #DIV/0! | EY110: =(ER110-EG110)/EG110 -> #DIV/0!
C111: PRESÍDIO DE JACINTO | D111: 1450022 | E111: 314 | F111: B22G0013321 | G111: 00007255411 | H111: COMPANHIA DE SANEAMENTO DE MINAS GERAIS COPASA MG | I111: 17.281.106/0001-03 | N111: 107 | P111: 1106.47 | R111: 21945.04 | S111: 801 | T111: 1450.01.0005511/2026-51 | X111: =AA111 + ABS(Y111) + ABS(Z111) -> 24897.06 | Y111: -1195.06 | Z111: 0 | AA111: 23702 | AB111: 862 | AC111: 10/03/2026 | AD111: 1450.01.0029372/2026-78 | AE111: TRUE | AF111: TRUE | AG111: =(AB111-S111)/S111 -> 0.076154806 | AH111: =(AA111-R111)/R111 -> 0.080061827 | AI111: =AL111 + ABS(AJ111) + ABS(AK111) -> 22461.9 | AJ111: -1078.17 | AK111: 0 | AL111: 21383.73 | AM111: 757 | AN111: 46122 | AO111: 1450.01.0046622/2026-25 | AP111: TRUE | AQ111: TRUE | AR111: =(AM111-AB111)/AB111 -> -0.12180974 | AS111: =(AL111-AA111)/AA111 -> -0.097809046 | AT111: =AW111 + ABS(AU111) + ABS(AV111) -> 0 | BA111: FALSE | BB111: FALSE | BC111: =(AX111-AM111)/AM111 -> -1 | BD111: =(AW111-AL111)/AL111 -> -1 | BE111: =BH111 + ABS(BF111) + ABS(BG111) -> 0 | BL111: FALSE | BM111: FALSE | BN111: =(BI111-AZ111)/AZ111 -> #DIV/0! | BO111: =(BH111-AW111)/AW111 -> #DIV/0! | BP111: =BS111 + ABS(BQ111) + ABS(BR111) -> 0 | BW111: FALSE | BX111: FALSE | BY111: =(BT111-BI111)/BI111 -> #DIV/0! | BZ111: =(BS111-BH111)/BH111 -> #DIV/0! | CA111: =CD111 + ABS(CB111) + ABS(CC111) -> 0 | CH111: FALSE | CI111: FALSE | CJ111: =(CE111-BV111)/BV111 -> #DIV/0! | CK111: =(CD111-BS111)/BS111 -> #DIV/0! | CL111: =CO111 + ABS(CM111) + ABS(CN111) -> 0 | CS111: FALSE | CT111: FALSE | CU111: =(CP111-CE111)/CE111 -> #DIV/0! | CV111: =(CO111-CD111)/CD111 -> #DIV/0! | CW111: =CZ111 + ABS(CX111) + ABS(CY111) -> 0 | DD111: FALSE | DE111: FALSE | DF111: =(DA111-CR111)/CR111 -> #DIV/0! | DG111: =(CZ111-CO111)/CO111 -> #DIV/0! | DH111: =DK111 + ABS(DI111) + ABS(DJ111) -> 0 | DO111: FALSE | DP111: FALSE | DQ111: =(DL111-DA111)/DA111 -> #DIV/0! | DR111: =(DK111-CZ111)/CZ111 -> #DIV/0! | DS111: =DV111 + ABS(DT111) + ABS(DU111) -> 0 | DZ111: FALSE | EA111: FALSE | EB111: =(DW111-DN111)/DN111 -> #DIV/0! | EC111: =(DV111-DK111)/DK111 -> #DIV/0! | ED111: =EG111 + ABS(EE111) + ABS(EF111) -> 0 | EK111: FALSE | EL111: FALSE | EM111: =(EH111-DW111)/DW111 -> #DIV/0! | EN111: =(EG111-DV111)/DV111 -> #DIV/0! | EO111: =ER111 + ABS(EP111) + ABS(EQ111) -> 0 | EV111: FALSE | EW111: FALSE | EX111: =(ES111-EJ111)/EJ111 -> #DIV/0! | EY111: =(ER111-EG111)/EG111 -> #DIV/0!
C112: PRESÍDIO DE JANAÚBA | D112: 1450022 | E112: 159 | F112: A25H0016004 | G112: 00024091626 | H112: COMPANHIA DE SANEAMENTO DE MINAS GERAIS COPASA MG | I112: 17.281.106/0001-03 | N112: 107 | P112: 48.42 | R112: 960.33 | S112: 50 | T112: 1450.01.0005511/2026-51 | X112: =AA112 + ABS(Y112) + ABS(Z112) -> 1677.73 | Y112: -80.53 | Z112: 0 | AA112: 1597.2 | AB112: 76 | AC112: 10/03/2026 | AD112: 1450.01.0029372/2026-78 | AE112: TRUE | AF112: TRUE | AG112: =(AB112-S112)/S112 -> 0.52 | AH112: =(AA112-R112)/R112 -> 0.66317828 | AI112: =AL112 + ABS(AJ112) + ABS(AK112) -> 2014.89 | AJ112: -96.71 | AK112: 0 | AL112: 1918.18 | AM112: 87 | AN112: 46122 | AO112: 1450.01.0046622/2026-25 | AP112: TRUE | AQ112: TRUE | AR112: =(AM112-AB112)/AB112 -> 0.14473684 | AS112: =(AL112-AA112)/AA112 -> 0.20096419 | AT112: =AW112 + ABS(AU112) + ABS(AV112) -> 0 | BA112: FALSE | BB112: FALSE | BC112: =(AX112-AM112)/AM112 -> -1 | BD112: =(AW112-AL112)/AL112 -> -1 | BE112: =BH112 + ABS(BF112) + ABS(BG112) -> 0 | BL112: FALSE | BM112: FALSE | BN112: =(BI112-AZ112)/AZ112 -> #DIV/0! | BO112: =(BH112-AW112)/AW112 -> #DIV/0! | BP112: =BS112 + ABS(BQ112) + ABS(BR112) -> 0 | BW112: FALSE | BX112: FALSE | BY112: =(BT112-BI112)/BI112 -> #DIV/0! | BZ112: =(BS112-BH112)/BH112 -> #DIV/0! | CA112: =CD112 + ABS(CB112) + ABS(CC112) -> 0 | CH112: FALSE | CI112: FALSE | CJ112: =(CE112-BV112)/BV112 -> #DIV/0! | CK112: =(CD112-BS112)/BS112 -> #DIV/0! | CL112: =CO112 + ABS(CM112) + ABS(CN112) -> 0 | CS112: FALSE | CT112: FALSE | CU112: =(CP112-CE112)/CE112 -> #DIV/0! | CV112: =(CO112-CD112)/CD112 -> #DIV/0! | CW112: =CZ112 + ABS(CX112) + ABS(CY112) -> 0 | DD112: FALSE | DE112: FALSE | DF112: =(DA112-CR112)/CR112 -> #DIV/0! | DG112: =(CZ112-CO112)/CO112 -> #DIV/0! | DH112: =DK112 + ABS(DI112) + ABS(DJ112) -> 0 | DO112: FALSE | DP112: FALSE | DQ112: =(DL112-DA112)/DA112 -> #DIV/0! | DR112: =(DK112-CZ112)/CZ112 -> #DIV/0! | DS112: =DV112 + ABS(DT112) + ABS(DU112) -> 0 | DZ112: FALSE | EA112: FALSE | EB112: =(DW112-DN112)/DN112 -> #DIV/0! | EC112: =(DV112-DK112)/DK112 -> #DIV/0! | ED112: =EG112 + ABS(EE112) + ABS(EF112) -> 0 | EK112: FALSE | EL112: FALSE | EM112: =(EH112-DW112)/DW112 -> #DIV/0! | EN112: =(EG112-DV112)/DV112 -> #DIV/0! | EO112: =ER112 + ABS(EP112) + ABS(EQ112) -> 0 | EV112: FALSE | EW112: FALSE | EX112: =(ES112-EJ112)/EJ112 -> #DIV/0! | EY112: =(ER112-EG112)/EG112 -> #DIV/0!
C113: PRESÍDIO DE JANAÚBA | D113: 1450022 | E113: 159 | F113: A18N0346204 | G113: 00108248721 | H113: COMPANHIA DE SANEAMENTO DE MINAS GERAIS COPASA MG | I113: 17.281.106/0001-03 | N113: 107 | P113: 2.6 | R113: 51.52 | T113: 1450.01.0005511/2026-51 | X113: =AA113 + ABS(Y113) + ABS(Z113) -> 54.12 | Y113: -2.6 | Z113: 0 | AA113: 51.52 | AB113: 0 | AC113: 10/03/2026 | AD113: 1450.01.0029372/2026-78 | AE113: TRUE | AF113: TRUE | AG113: =(AB113-S113)/S113 -> #DIV/0! | AH113: =(AA113-R113)/R113 -> 0 | AI113: =AL113 + ABS(AJ113) + ABS(AK113) -> 67.51 | AJ113: -3.24 | AK113: 0 | AL113: 64.27 | AM113: 1 | AN113: 46122 | AO113: 1450.01.0046622/2026-25 | AP113: TRUE | AQ113: TRUE | AR113: =(AM113-AB113)/AB113 -> #DIV/0! | AS113: =(AL113-AA113)/AA113 -> 0.24747671 | AT113: =AW113 + ABS(AU113) + ABS(AV113) -> 0 | BA113: FALSE | BB113: FALSE | BC113: =(AX113-AM113)/AM113 -> -1 | BD113: =(AW113-AL113)/AL113 -> -1 | BE113: =BH113 + ABS(BF113) + ABS(BG113) -> 0 | BL113: FALSE | BM113: FALSE | BN113: =(BI113-AZ113)/AZ113 -> #DIV/0! | BO113: =(BH113-AW113)/AW113 -> #DIV/0! | BP113: =BS113 + ABS(BQ113) + ABS(BR113) -> 0 | BW113: FALSE | BX113: FALSE | BY113: =(BT113-BI113)/BI113 -> #DIV/0! | BZ113: =(BS113-BH113)/BH113 -> #DIV/0! | CA113: =CD113 + ABS(CB113) + ABS(CC113) -> 0 | CH113: FALSE | CI113: FALSE | CJ113: =(CE113-BV113)/BV113 -> #DIV/0! | CK113: =(CD113-BS113)/BS113 -> #DIV/0! | CL113: =CO113 + ABS(CM113) + ABS(CN113) -> 0 | CS113: FALSE | CT113: FALSE | CU113: =(CP113-CE113)/CE113 -> #DIV/0! | CV113: =(CO113-CD113)/CD113 -> #DIV/0! | CW113: =CZ113 + ABS(CX113) + ABS(CY113) -> 0 | DD113: FALSE | DE113: FALSE | DF113: =(DA113-CR113)/CR113 -> #DIV/0! | DG113: =(CZ113-CO113)/CO113 -> #DIV/0! | DH113: =DK113 + ABS(DI113) + ABS(DJ113) -> 0 | DO113: FALSE | DP113: FALSE | DQ113: =(DL113-DA113)/DA113 -> #DIV/0! | DR113: =(DK113-CZ113)/CZ113 -> #DIV/0! | DS113: =DV113 + ABS(DT113) + ABS(DU113) -> 0 | DZ113: FALSE | EA113: FALSE | EB113: =(DW113-DN113)/DN113 -> #DIV/0! | EC113: =(DV113-DK113)/DK113 -> #DIV/0! | ED113: =EG113 + ABS(EE113) + ABS(EF113) -> 0 | EK113: FALSE | EL113: FALSE | EM113: =(EH113-DW113)/DW113 -> #DIV/0! | EN113: =(EG113-DV113)/DV113 -> #DIV/0! | EO113: =ER113 + ABS(EP113) + ABS(EQ113) -> 0 | EV113: FALSE | EW113: FALSE | EX113: =(ES113-EJ113)/EJ113 -> #DIV/0! | EY113: =(ER113-EG113)/EG113 -> #DIV/0!
C114: PRESÍDIO DE JANAÚBA | D114: 1450022 | E114: 159 | F114: B18F0007809 A18N0345841 | G114: 00020483406 | H114: COMPANHIA DE SANEAMENTO DE MINAS GERAIS COPASA MG | I114: 17.281.106/0001-03 | N114: 107 | P114: 485.73 | R114: 9633.72 | S114: 400 | T114: 1450.01.0005511/2026-51 | X114: =AA114 + ABS(Y114) + ABS(Z114) -> 15790.31 | Y114: -757.93 | Z114: 0 | AA114: 15032.38 | AB114: 561 | AC114: 10/03/2026 | AD114: 1450.01.0029372/2026-78 | AE114: TRUE | AF114: TRUE | AG114: =(AB114-S114)/S114 -> 0.4025 | AH114: =(AA114-R114)/R114 -> 0.56039204 | AI114: =AL114 + ABS(AJ114) + ABS(AK114) -> 11022.59 | AJ114: -529.08 | AK114: 0 | AL114: 10493.51 | AM114: 390 | AN114: 46122 | AO114: 1450.01.0046622/2026-25 | AP114: TRUE | AQ114: TRUE | AR114: =(AM114-AB114)/AB114 -> -0.30481283 | AS114: =(AL114-AA114)/AA114 -> -0.30193955 | AT114: =AW114 + ABS(AU114) + ABS(AV114) -> 0 | BA114: FALSE | BB114: FALSE | BC114: =(AX114-AM114)/AM114 -> -1 | BD114: =(AW114-AL114)/AL114 -> -1 | BE114: =BH114 + ABS(BF114) + ABS(BG114) -> 0 | BL114: FALSE | BM114: FALSE | BN114: =(BI114-AZ114)/AZ114 -> #DIV/0! | BO114: =(BH114-AW114)/AW114 -> #DIV/0! | BP114: =BS114 + ABS(BQ114) + ABS(BR114) -> 0 | BW114: FALSE | BX114: FALSE | BY114: =(BT114-BI114)/BI114 -> #DIV/0! | BZ114: =(BS114-BH114)/BH114 -> #DIV/0! | CA114: =CD114 + ABS(CB114) + ABS(CC114) -> 0 | CH114: FALSE | CI114: FALSE | CJ114: =(CE114-BV114)/BV114 -> #DIV/0! | CK114: =(CD114-BS114)/BS114 -> #DIV/0! | CL114: =CO114 + ABS(CM114) + ABS(CN114) -> 0 | CS114: FALSE | CT114: FALSE | CU114: =(CP114-CE114)/CE114 -> #DIV/0! | CV114: =(CO114-CD114)/CD114 -> #DIV/0! | CW114: =CZ114 + ABS(CX114) + ABS(CY114) -> 0 | DD114: FALSE | DE114: FALSE | DF114: =(DA114-CR114)/CR114 -> #DIV/0! | DG114: =(CZ114-CO114)/CO114 -> #DIV/0! | DH114: =DK114 + ABS(DI114) + ABS(DJ114) -> 0 | DO114: FALSE | DP114: FALSE | DQ114: =(DL114-DA114)/DA114 -> #DIV/0! | DR114: =(DK114-CZ114)/CZ114 -> #DIV/0! | DS114: =DV114 + ABS(DT114) + ABS(DU114) -> 0 | DZ114: FALSE | EA114: FALSE | EB114: =(DW114-DN114)/DN114 -> #DIV/0! | EC114: =(DV114-DK114)/DK114 -> #DIV/0! | ED114: =EG114 + ABS(EE114) + ABS(EF114) -> 0 | EK114: FALSE | EL114: FALSE | EM114: =(EH114-DW114)/DW114 -> #DIV/0! | EN114: =(EG114-DV114)/DV114 -> #DIV/0! | EO114: =ER114 + ABS(EP114) + ABS(EQ114) -> 0 | EV114: FALSE | EW114: FALSE | EX114: =(ES114-EJ114)/EJ114 -> #DIV/0! | EY114: =(ER114-EG114)/EG114 -> #DIV/0!
C115: PRESÍDIO DE JANAÚBA | D115: 1450022 | E115: 159 | F115: D17B0704461 | G115: 00108248747 | H115: COMPANHIA DE SANEAMENTO DE MINAS GERAIS COPASA MG | I115: 17.281.106/0001-03 | N115: 107 | P115: 833.8 | R115: 16537 | S115: 327 | T115: 1450.01.0005511/2026-51 | X115: =AA115 + ABS(Y115) + ABS(Z115) -> 17701.15 | Y115: -849.66 | Z115: 0 | AA115: 16851.49 | AB115: 346 | AC115: 10/03/2026 | AD115: 1450.01.0029372/2026-78 | AE115: TRUE | AF115: TRUE | AG115: =(AB115-S115)/S115 -> 0.058103976 | AH115: =(AA115-R115)/R115 -> 0.019017355 | AI115: =AL115 + ABS(AJ115) + ABS(AK115) -> 18493.83 | AJ115: -887.7 | AK115: 0 | AL115: 17606.13 | AM115: 365 | AN115: 46122 | AP115: TRUE | AQ115: TRUE | AR115: =(AM115-AB115)/AB115 -> 0.054913295 | AS115: =(AL115-AA115)/AA115 -> 0.044781797 | AT115: =AW115 + ABS(AU115) + ABS(AV115) -> 0 | BA115: FALSE | BB115: FALSE | BC115: =(AX115-AM115)/AM115 -> -1 | BD115: =(AW115-AL115)/AL115 -> -1 | BE115: =BH115 + ABS(BF115) + ABS(BG115) -> 0 | BL115: FALSE | BM115: FALSE | BN115: =(BI115-AZ115)/AZ115 -> #DIV/0! | BO115: =(BH115-AW115)/AW115 -> #DIV/0! | BP115: =BS115 + ABS(BQ115) + ABS(BR115) -> 0 | BW115: FALSE | BX115: FALSE | BY115: =(BT115-BI115)/BI115 -> #DIV/0! | BZ115: =(BS115-BH115)/BH115 -> #DIV/0! | CA115: =CD115 + ABS(CB115) + ABS(CC115) -> 0 | CH115: FALSE | CI115: FALSE | CJ115: =(CE115-BV115)/BV115 -> #DIV/0! | CK115: =(CD115-BS115)/BS115 -> #DIV/0! | CL115: =CO115 + ABS(CM115) + ABS(CN115) -> 0 | CS115: FALSE | CT115: FALSE | CU115: =(CP115-CE115)/CE115 -> #DIV/0! | CV115: =(CO115-CD115)/CD115 -> #DIV/0! | CW115: =CZ115 + ABS(CX115) + ABS(CY115) -> 0 | DD115: FALSE | DE115: FALSE | DF115: =(DA115-CR115)/CR115 -> #DIV/0! | DG115: =(CZ115-CO115)/CO115 -> #DIV/0! | DH115: =DK115 + ABS(DI115) + ABS(DJ115) -> 0 | DO115: FALSE | DP115: FALSE | DQ115: =(DL115-DA115)/DA115 -> #DIV/0! | DR115: =(DK115-CZ115)/CZ115 -> #DIV/0! | DS115: =DV115 + ABS(DT115) + ABS(DU115) -> 0 | DZ115: FALSE | EA115: FALSE | EB115: =(DW115-DN115)/DN115 -> #DIV/0! | EC115: =(DV115-DK115)/DK115 -> #DIV/0! | ED115: =EG115 + ABS(EE115) + ABS(EF115) -> 0 | EK115: FALSE | EL115: FALSE | EM115: =(EH115-DW115)/DW115 -> #DIV/0! | EN115: =(EG115-DV115)/DV115 -> #DIV/0! | EO115: =ER115 + ABS(EP115) + ABS(EQ115) -> 0 | EV115: FALSE | EW115: FALSE | EX115: =(ES115-EJ115)/EJ115 -> #DIV/0! | EY115: =(ER115-EG115)/EG115 -> #DIV/0!
